Workbook
Name ___________fl1111: {"Fecha_Novembro",#N/A,FALSE,"FECHAMENTO-2002 ";"Defer_Novembro",#N/A,FALSE,"DIFERIDO";"Pis_Novembro",#N/A,FALSE,"PIS COFINS";"Iss_Novembro",#N/A,FALSE,"ISS"}
Name __________fl1111: {"Fecha_Novembro",#N/A,FALSE,"FECHAMENTO-2002 ";"Defer_Novembro",#N/A,FALSE,"DIFERIDO";"Pis_Novembro",#N/A,FALSE,"PIS COFINS";"Iss_Novembro",#N/A,FALSE,"ISS"}
Name _________fl1111: {"Fecha_Novembro",#N/A,FALSE,"FECHAMENTO-2002 ";"Defer_Novembro",#N/A,FALSE,"DIFERIDO";"Pis_Novembro",#N/A,FALSE,"PIS COFINS";"Iss_Novembro",#N/A,FALSE,"ISS"}
Name ________fl1111: {"Fecha_Novembro",#N/A,FALSE,"FECHAMENTO-2002 ";"Defer_Novembro",#N/A,FALSE,"DIFERIDO";"Pis_Novembro",#N/A,FALSE,"PIS COFINS";"Iss_Novembro",#N/A,FALSE,"ISS"}
Name _______fl1111: {"Fecha_Novembro",#N/A,FALSE,"FECHAMENTO-2002 ";"Defer_Novembro",#N/A,FALSE,"DIFERIDO";"Pis_Novembro",#N/A,FALSE,"PIS COFINS";"Iss_Novembro",#N/A,FALSE,"ISS"}
Name ______fl1111: {"Fecha_Novembro",#N/A,FALSE,"FECHAMENTO-2002 ";"Defer_Novembro",#N/A,FALSE,"DIFERIDO";"Pis_Novembro",#N/A,FALSE,"PIS COFINS";"Iss_Novembro",#N/A,FALSE,"ISS"}
Name ____fl1111: {"Fecha_Novembro",#N/A,FALSE,"FECHAMENTO-2002 ";"Defer_Novembro",#N/A,FALSE,"DIFERIDO";"Pis_Novembro",#N/A,FALSE,"PIS COFINS";"Iss_Novembro",#N/A,FALSE,"ISS"}
Name ___dc1: {#N/A,#N/A,FALSE,"Aging Summary";#N/A,#N/A,FALSE,"Ratio Analysis";#N/A,#N/A,FALSE,"Test 120 Day Accts";#N/A,#N/A,FALSE,"Tickmarks"}
Name ___xlc_DefaultDisplayOption___: "caption"
Name ___xlc_DisplayNullValuesAs___: "___xlc_DisplayNullValuesAs_empty___"
Name ___xlc_PromptForInsertOnDrill___: FALSE
Name ___xlc_SuppressNULLSOnDrill___: TRUE
Name ___xlc_SuppressZerosOnDrill___: FALSE
Name __123Graph_AANIDRO: [1]PRODUCAO!$C$4:$F$4
Name __123Graph_AHIALCOOL: [1]PRODUCAO!$C$8:$F$8
Name __123Graph_AHIDRATADO: [1]PRODUCAO!$C$6:$F$6
Name __123Graph_AINDMES: [2]TESTE!$AG$74:$AP$74
Name __123Graph_AJAYME: '[3]RF-G7'!$AC$47:$AC$59
Name __123Graph_AMERC: [2]TESTE!$AR$4:$AR$26
Name __123Graph_ARESFIN: [2]TESTE!$V$131:$V$151
Name __123Graph_ASACAS: [1]PRODUCAO!$C$11:$F$11
Name __123Graph_ASIDECO: '[4]fluxo de caixa'!#REF!
Name __123Graph_AUSS: [2]TESTE!$H$132:$H$195
Name __123Graph_B: [5]ce!#REF!
Name __123Graph_BINDMES: [2]TESTE!$AG$75:$AP$75
Name __123Graph_BJAYME: '[3]RF-G7'!$AE$47:$AE$47
Name __123Graph_BMERC: [2]TESTE!$AY$4:$AY$26
Name __123Graph_BRESFIN: [2]TESTE!$W$131:$W$151
Name __123Graph_BSIDECO: '[4]fluxo de caixa'!#REF!
Name __123Graph_C: [2]TESTE!$AG$77:$AP$77
Name __123Graph_CINDMES: [2]TESTE!$AG$77:$AP$77
Name __123Graph_CJAYME: '[3]RF-G7'!$AD$47:$AD$59
Name __123Graph_CMERC: [2]TESTE!$BG$4:$BG$26
Name __123Graph_CRESFIN: [2]TESTE!$X$131:$X$152
Name __123Graph_CSIDECO: '[4]fluxo de caixa'!#REF!
Name __123Graph_D: '[6]Pag .11 À 13'!#REF!
Name __123Graph_DINDMES: [2]TESTE!$AG$79:$AP$79
Name __123Graph_F: '[3]RF-G7'!$AD$48:$AD$59
Name __123Graph_XANIDRO: [1]PRODUCAO!$C$3:$F$3
Name __123Graph_XHIALCOOL: [1]PRODUCAO!$C$3:$F$3
Name __123Graph_XHIDRATADO: [1]PRODUCAO!$C$3:$F$3
Name __123Graph_XINDMES: [2]TESTE!$AG$73:$AP$73
Name __123Graph_XJAYME: '[3]RF-G7'!$AB$47:$AB$59
Name __123Graph_XMERC: [2]TESTE!$AQ$4:$AQ$26
Name __123Graph_XRESFIN: [2]TESTE!$Q$131:$Q$152
Name __123Graph_XSACAS: [1]PRODUCAO!$C$3:$F$3
Name __123Graph_XSIDECO: '[4]fluxo de caixa'!#REF!
Name __123Graph_XUSS: [2]TESTE!$B$132:$B$195
Name __dc1: {#N/A,#N/A,FALSE,"Aging Summary";#N/A,#N/A,FALSE,"Ratio Analysis";#N/A,#N/A,FALSE,"Test 120 Day Accts";#N/A,#N/A,FALSE,"Tickmarks"}
Name __FDS_HYPERLINK_TOGGLE_STATE__: "ON"
Name __g4: {"VERGALHÃO",#N/A,FALSE,"DIÁRIA";"CATODO",#N/A,FALSE,"DIÁRIA"}
Name __IntlFixup: TRUE
Name __s2: '[7]sales vol.'!$J$398:$J$401
Name __s3: '[7]sales vol.'!$J$211:$J$214
Name __s4: '[7]sales vol.'!$I$1121:$I$1122
Name __s5: '[7]sales vol.'!$I$1632:$I$1635
Name __s6: '[7]sales vol.'!$I$2248:$I$2251
Name _1_0__123Grap: [8]ICATU!#REF!
Name _1_123Grap: [9]análise!#REF!
Name _12__123Graph_BCHART_1: '[10]#REF'!#REF!

Sheet Modelo
B7: Valores em R$ (Milhares) | C7: Unidade | D7: 1T17 | E7: 2T17 | F7: 3T17 | G7: 4T17 | H7: 1T18 | I7: 2T18 | J7: 3T18 | K7: 4T18 | L7: 1T19 | M7: 2T19 | N7: 3T19 | O7: 4T19 | P7: 1T20 | Q7: 2T20 | R7: 3T20 | S7: 4T20 | T7: 1T21 | U7: 2T21 | V7: 3T21 | W7: 4T21 | X7: 1T22 | Y7: 2T22 | Z7: 3T22 | AA7: 4T22 | AB7: 1T23 | AC7: 2T23 | AD7: 3T23 | AE7: 4T23 | AF7: 1T24 | AG7: 2T24 | AH7: 3T24 | AI7: 4T24 | AJ7: 1T25 | AK7: ='Build-Up'!AK7 -> 2T25 | AL7: ='Build-Up'!AL7 -> 3T25 | AM7: ='Build-Up'!AM7 -> 4T25 | AN7: ='Build-Up'!AN7 -> 1T26 | AO7: ='Build-Up'!AO7 -> 2T26 | AP7: ='Build-Up'!AP7 -> 3T26 | AQ7: ='Build-Up'!AQ7 -> 4T26 | AR7: ='Build-Up'!AR7 -> 1T27 | ... BW7: ='Build-Up'!BW7 -> 4T34 | BX7: x | BY7: ='Build-Up'!BY7 -> 2017 | BZ7: ='Build-Up'!BZ7 -> 2018 | CA7: ='Build-Up'!CA7 -> 2019 | CB7: ='Build-Up'!CB7 -> 2020 | CC7: ='Build-Up'!CC7 -> 2021 | CD7: ='Build-Up'!CD7 -> 2022 | CE7: ='Build-Up'!CE7 -> 2023 | CF7: ='Build-Up'!CF7 -> 2024 | ... CP7: ='Build-Up'!CP7 -> 2034 | CQ7: x
BX8: x | CQ8: x
A9: l | B9: DRE | BX9: x | CQ9: x
BX10: x | CQ10: x
B11: Receita Líquida | C11: [BRL 000] | D11: =Inputs!F141/1000 -> 52.292 | E11: =Inputs!G141/1000 -> 54.026 | F11: =Inputs!H141/1000 -> 61.399 | G11: =Inputs!I141/1000 -> 68.785 | H11: =Inputs!J141/1000 -> 76.096 | I11: =Inputs!K141/1000 -> 84.326 | J11: =Inputs!L141/1000 -> 79.884 | K11: =Inputs!M141/1000 -> 86.931 | ... AJ11: =Inputs!AL141/1000 -> 368.845 | AK11: ='Build-Up'!AK20 -> 354.5325 | AL11: ='Build-Up'!AL20 -> 359.18181 | AM11: ='Build-Up'!AM20 -> 409.38174 | AN11: ='Build-Up'!AN20 -> 384.94945 | AO11: ='Build-Up'!AO20 -> 385.23919 | AP11: ='Build-Up'!AP20 -> 402.18972 | AQ11: ='Build-Up'!AQ20 -> 455.09592 | AR11: ='Build-Up'!AR20 -> 425.82731 | ... BW11: ='Build-Up'!BW20 -> 924.48804 | BX11: x | BY11: =SUM(D11:G11) -> 236.502 | BZ11: =SUM(H11:K11) -> 327.237 | CA11: =SUM(L11:O11) -> 348.612 | CB11: =SUM(P11:S11) -> 242.213 | CC11: =SUM(T11:W11) -> 433.141 | CD11: =SUM(X11:AA11) -> 813.494 | CE11: =SUM(AB11:AE11) -> 1046.41 | CF11: =SUM(AF11:AI11) -> 1234.06 | CG11: =SUM(AJ11:AM11) -> 1491.9411 | CH11: =SUM(AN11:AQ11) -> 1627.4743 | CI11: =SUM(AR11:AU11) -> 1787.6551 | CJ11: =SUM(AV11:AY11) -> 1953.2532 | CK11: =SUM(AZ11:BC11) -> 2134.1912 | CL11: =SUM(BD11:BG11) -> 2331.8903 | CM11: =SUM(BH11:BK11) -> 2547.9032 | CN11: =SUM(BL11:BO11) -> 2783.9262 | CO11: =SUM(BP11:BS11) -> 3041.813 | CP11: =SUM(BT11:BW11) -> 3323.5889 | CQ11: x
B12: a/a % | H12: =H11/D11-1 -> 0.45521303 | I12: =I11/E11-1 -> 0.56084108 | J12: =J11/F11-1 -> 0.30106354 | K12: =K11/G11-1 -> 0.26380752 | L12: =L11/H11-1 -> 0.089150547 | M12: =M11/I11-1 -> 0.096411546 | N12: =N11/J11-1 -> 0.068899905 | O12: =O11/K11-1 -> 0.011008731 | ... BW12: =BW11/BS11-1 -> 0.09263421 | BX12: x | BZ12: =BZ11/BY11-1 -> 0.38365426 | CA12: =CA11/BZ11-1 -> 0.065319631 | CB12: =CB11/CA11-1 -> -0.30520751 | CC12: =CC11/CB11-1 -> 0.78826487 | CD12: =CD11/CC11-1 -> 0.87812745 | CE12: =CE11/CD11-1 -> 0.28631557 | CF12: =CF11/CE11-1 -> 0.17932741 | CG12: =CG11/CF11-1 -> 0.20896962 | ... CP12: =CP11/CO11-1 -> 0.09263421 | CQ12: x
BX13: x | CQ13: x
B14: COGS | C14: [BRL 000] | D14: =Inputs!F142/1000 -> -39.486 | E14: =Inputs!G142/1000 -> -44.543 | F14: =Inputs!H142/1000 -> -57.243 | G14: =Inputs!I142/1000 -> -61.827 | H14: =Inputs!J142/1000 -> -65.521 | I14: =Inputs!K142/1000 -> -77.319 | J14: =Inputs!L142/1000 -> -70.948 | K14: =Inputs!M142/1000 -> -68.426 | ... AJ14: =Inputs!AL142/1000 -> -295.005 | AK14: ='Build-Up'!AK50 -> -279.49002 | AL14: ='Build-Up'!AL50 -> -280.44507 | AM14: ='Build-Up'!AM50 -> -321.04799 | AN14: ='Build-Up'!AN50 -> -302.16683 | AO14: ='Build-Up'!AO50 -> -302.54252 | AP14: ='Build-Up'!AP50 -> -312.84841 | AQ14: ='Build-Up'!AQ50 -> -355.33199 | AR14: ='Build-Up'!AR50 -> -333.26288 | ... BW14: ='Build-Up'!BW50 -> -720.599 | BX14: x | BY14: =SUM(D14:G14) -> -203.099 | BZ14: =SUM(H14:K14) -> -282.214 | CA14: =SUM(L14:O14) -> -299.585 | CB14: =SUM(P14:S14) -> -215.064 | CC14: =SUM(T14:W14) -> -362.687 | CD14: =SUM(X14:AA14) -> -614.912 | CE14: =SUM(AB14:AE14) -> -830.84 | CF14: =SUM(AF14:AI14) -> -960.465 | CG14: =SUM(AJ14:AM14) -> -1175.9881 | CH14: =SUM(AN14:AQ14) -> -1272.8898 | CI14: =SUM(AR14:AU14) -> -1394.9603 | CJ14: =SUM(AV14:AY14) -> -1524.1814 | CK14: =SUM(AZ14:BC14) -> -1665.3727 | CL14: =SUM(BD14:BG14) -> -1819.6432 | CM14: =SUM(BH14:BK14) -> -1988.2044 | CN14: =SUM(BL14:BO14) -> -2172.3802 | CO14: =SUM(BP14:BS14) -> -2373.6169 | CP14: =SUM(BT14:BW14) -> -2593.495 | CQ14: x
B15: a/a % | C15: [%] | H15: =H14/D14-1 -> 0.65934762 | I15: =I14/E14-1 -> 0.7358283 | J15: =J14/F14-1 -> 0.23941792 | K15: =K14/G14-1 -> 0.1067333 | L15: =L14/H14-1 -> 0.10422613 | M15: =M14/I14-1 -> 0.031686907 | N15: =N14/J14-1 -> 0.052122681 | O15: =O14/K14-1 -> 0.064215357 | ... BW15: =BW14/BS14-1 -> 0.09263421 | BX15: x | BZ15: =BZ14/BY14-1 -> 0.38953909 | CA15: =CA14/BZ14-1 -> 0.061552581 | CB15: =CB14/CA14-1 -> -0.28212694 | CC15: =CC14/CB14-1 -> 0.68641428 | CD15: =CD14/CC14-1 -> 0.69543436 | CE15: =CE14/CD14-1 -> 0.35115269 | CF15: =CF14/CE14-1 -> 0.1560168 | CG15: =CG14/CF14-1 -> 0.22439451 | ... CP15: =CP14/CO14-1 -> 0.09263421 | CQ15: x
BX16: x | CQ16: x
B17: Lucro Bruto | C17: [BRL 000] | D17: =Inputs!F144/1000 -> 12.806 | E17: =Inputs!G144/1000 -> 9.483 | F17: =Inputs!H144/1000 -> 4.156 | G17: =Inputs!I144/1000 -> 6.958 | H17: =Inputs!J144/1000 -> 10.575 | I17: =Inputs!K144/1000 -> 7.007 | J17: =Inputs!L144/1000 -> 8.936 | K17: =Inputs!M144/1000 -> 18.505 | ... AJ17: =Inputs!AL144/1000 -> 73.84 | AK17: =AK11+AK14 -> 75.042484 | AL17: =AL11+AL14 -> 78.736739 | AM17: =AM11+AM14 -> 88.333756 | AN17: =AN11+AN14 -> 82.782618 | AO17: =AO11+AO14 -> 82.696673 | AP17: =AP11+AP14 -> 89.341308 | AQ17: =AQ11+AQ14 -> 99.76393 | AR17: =AR11+AR14 -> 92.564426 | ... BW17: =BW11+BW14 -> 203.88904 | BX17: x | BY17: =SUM(D17:G17) -> 33.403 | BZ17: =SUM(H17:K17) -> 45.023 | CA17: =SUM(L17:O17) -> 49.027 | CB17: =SUM(P17:S17) -> 27.149 | CC17: =SUM(T17:W17) -> 70.454 | CD17: =SUM(X17:AA17) -> 198.582 | CE17: =SUM(AB17:AE17) -> 215.57 | CF17: =SUM(AF17:AI17) -> 273.595 | CG17: =SUM(AJ17:AM17) -> 315.95298 | CH17: =SUM(AN17:AQ17) -> 354.58453 | CI17: =SUM(AR17:AU17) -> 392.69481 | CJ17: =SUM(AV17:AY17) -> 429.07179 | CK17: =SUM(AZ17:BC17) -> 468.81852 | CL17: =SUM(BD17:BG17) -> 512.24715 | CM17: =SUM(BH17:BK17) -> 559.69876 | CN17: =SUM(BL17:BO17) -> 611.54601 | CO17: =SUM(BP17:BS17) -> 668.19609 | CP17: =SUM(BT17:BW17) -> 730.09391 | CQ17: x
B18: a/a % | C18: [%] | H18: =H17/D17-1 -> -0.17421521 | I18: =I17/E17-1 -> -0.26109881 | J18: =J17/F17-1 -> 1.1501444 | K18: =K17/G17-1 -> 1.6595286 | L18: =L17/H17-1 -> -0.0042553191 | M18: =M17/I17-1 -> 0.81061795 | N18: =N17/J17-1 -> 0.20210385 | O18: =O17/K17-1 -> -0.18573359 | ... BW18: =BW17/BS17-1 -> 0.09263421 | BX18: x | BZ18: =BZ17/BY17-1 -> 0.34787295 | CA18: =CA17/BZ17-1 -> 0.088932323 | CB18: =CB17/CA17-1 -> -0.44624391 | CC18: =CC17/CB17-1 -> 1.5950864 | CD18: =CD17/CC17-1 -> 1.818605 | CE18: =CE17/CD17-1 -> 0.085546525 | CF18: =CF17/CE17-1 -> 0.26917011 | CG18: =CG17/CF17-1 -> 0.15482 | ... CP18: =CP17/CO17-1 -> 0.09263421 | CQ18: x
B19: Margem Bruta | C19: [%] | D19: =D17/D11 -> 0.24489406 | E19: =E17/E11 -> 0.1755266 | F19: =F17/F11 -> 0.067688399 | G19: =G17/G11 -> 0.10115578 | H19: =H17/H11 -> 0.1389692 | I19: =I17/I11 -> 0.083094182 | J19: =J17/J11 -> 0.1118622 | K19: =K17/K11 -> 0.21286998 | ... BW19: =BW17/BW11 -> 0.22054265 | BX19: x | BY19: =BY17/BY11 -> 0.14123771 | BZ19: =BZ17/BZ11 -> 0.1375853 | CA19: =CA17/CA11 -> 0.14063486 | CB19: =CB17/CB11 -> 0.1120873 | CC19: =CC17/CC11 -> 0.16265835 | CD19: =CD17/CD11 -> 0.24410998 | CE19: =CE17/CE11 -> 0.20600912 | CF19: =CF17/CF11 -> 0.22170316 | ... CP19: =CP17/CP11 -> 0.21967034 | CQ19: x
BX20: x | CQ20: x
B21: SG&A | C21: [BRL 000] | D21: =Inputs!F147/1000 -> -9.014 | E21: =Inputs!G147/1000 -> -10.452 | F21: =Inputs!H147/1000 -> -8.349 | G21: =Inputs!I147/1000 -> -13.301 | H21: =Inputs!J147/1000 -> -8.349 | I21: =Inputs!K147/1000 -> -4.123 | J21: =Inputs!L147/1000 -> -5.844 | K21: =Inputs!M147/1000 -> -12.059 | ... AJ21: =Inputs!AL147/1000 -> -52.195 | AK21: ='Build-Up'!AK100 -> -50.883909 | AL21: ='Build-Up'!AL100 -> -40.035246 | AM21: ='Build-Up'!AM100 -> -52.137101 | AN21: ='Build-Up'!AN100 -> -42.344439 | AO21: ='Build-Up'!AO100 -> -42.376311 | AP21: ='Build-Up'!AP100 -> -44.240869 | AQ21: ='Build-Up'!AQ100 -> -50.060552 | AR21: ='Build-Up'!AR100 -> -44.711867 | ... BW21: ='Build-Up'!BW100 -> -92.448804 | BX21: x | BY21: =SUM(D21:G21) -> -41.116 | BZ21: =SUM(H21:K21) -> -30.375 | CA21: =SUM(L21:O21) -> -42.064 | CB21: =SUM(P21:S21) -> -31.998 | CC21: =SUM(T21:W21) -> -49.962 | CD21: =SUM(X21:AA21) -> -94.124 | CE21: =SUM(AB21:AE21) -> -128.172 | CF21: =SUM(AF21:AI21) -> -162.113 | CG21: =SUM(AJ21:AM21) -> -195.25126 | CH21: =SUM(AN21:AQ21) -> -179.02217 | CI21: =SUM(AR21:AU21) -> -187.70379 | CJ21: =SUM(AV21:AY21) -> -195.32532 | CK21: =SUM(AZ21:BC21) -> -213.41912 | CL21: =SUM(BD21:BG21) -> -233.18903 | CM21: =SUM(BH21:BK21) -> -254.79032 | CN21: =SUM(BL21:BO21) -> -278.39262 | CO21: =SUM(BP21:BS21) -> -304.1813 | CP21: =SUM(BT21:BW21) -> -332.35889 | CQ21: x
B22: a/a % | C22: [%] | H22: =H21/D21-1 -> -0.073774129 | I22: =I21/E21-1 -> -0.60553004 | J22: =J21/F21-1 -> -0.30003593 | K22: =K21/G21-1 -> -0.093376438 | L22: =L21/H21-1 -> 0.13067433 | M22: =M21/I21-1 -> 1.643706 | N22: =N21/J21-1 -> 0.92060233 | O22: =O21/K21-1 -> -0.12928103 | ... BW22: =BW21/BS21-1 -> 0.09263421 | BX22: x | BZ22: =BZ21/BY21-1 -> -0.2612365 | CA22: =CA21/BZ21-1 -> 0.38482305 | CB22: =CB21/CA21-1 -> -0.23930202 | CC22: =CC21/CB21-1 -> 0.56141009 | CD22: =CD21/CC21-1 -> 0.88391177 | CE22: =CE21/CD21-1 -> 0.36173558 | CF22: =CF21/CE21-1 -> 0.26480823 | CG22: =CG21/CF21-1 -> 0.20441455 | ... CP22: =CP21/CO21-1 -> 0.09263421 | CQ22: x
B23: SG&A ex D&A | C23: [BRL 000] | BX23: x | CQ23: x
B24: Como % da Receita Líquida | D24: =D21/D$11 -> -0.17237818 | E24: =E21/E$11 -> -0.19346241 | F24: =F21/F$11 -> -0.13597941 | G24: =G21/G$11 -> -0.19337065 | H24: =H21/H$11 -> -0.10971667 | I24: =I21/I$11 -> -0.04889358 | J24: =J21/J$11 -> -0.073156076 | K24: =K21/K$11 -> -0.13871921 | ... BW24: =BW21/BW$11 -> -0.1 | BX24: x | BY24: =BY21/BY$11 -> -0.17385054 | BZ24: =BZ21/BZ$11 -> -0.092822633 | CA24: =CA21/CA$11 -> -0.12066137 | CB24: =CB21/CB$11 -> -0.13210686 | CC24: =CC21/CC$11 -> -0.11534812 | CD24: =CD21/CD$11 -> -0.11570337 | CE24: =CE21/CE$11 -> -0.12248736 | CF24: =CF21/CF$11 -> -0.13136557 | ... CP24: =CP21/CP$11 -> -0.1 | CQ24: x
BX25: x | CQ25: x
B26: Equivalência Patrimonial | C26: [BRL 000] | D26: =Inputs!F149/1000 -> 0.174 | E26: =Inputs!G149/1000 -> 0.061 | F26: =Inputs!H149/1000 -> 0.212 | G26: =Inputs!I149/1000 -> -0.261 | H26: =Inputs!J149/1000 -> 0.607 | I26: =Inputs!K149/1000 -> 0.438 | J26: =Inputs!L149/1000 -> 0.116 | K26: =Inputs!M149/1000 -> -0.713 | ... AJ26: =Inputs!AL149/1000 -> 0 | AK26: =0 -> 0 | AL26: =0 -> 0 | AM26: =0 -> 0 | AN26: =0 -> 0 | AO26: =0 -> 0 | AP26: =0 -> 0 | AQ26: =0 -> 0 | AR26: =0 -> 0 | ... BW26: =0 -> 0 | BX26: x | BY26: =SUM(D26:G26) -> 0.186 | BZ26: =SUM(H26:K26) -> 0.448 | CA26: =SUM(L26:O26) -> 0.797 | CB26: =SUM(P26:S26) -> 0.217 | CC26: =SUM(T26:W26) -> 0 | CD26: =SUM(X26:AA26) -> 0 | CE26: =SUM(AB26:AE26) -> 0 | CF26: =SUM(AF26:AI26) -> 0 | CG26: =SUM(AJ26:AM26) -> 0 | CH26: =SUM(AN26:AQ26) -> 0 | CI26: =SUM(AR26:AU26) -> 0 | CJ26: =SUM(AV26:AY26) -> 0 | CK26: =SUM(AQ26:AT26) -> 0 | CL26: =SUM(AU26:AX26) -> 0 | CM26: =SUM(AY26:BB26) -> 0 | CN26: =SUM(AT26:AW26) -> 0 | CO26: =SUM(AX26:BA26) -> 0 | CP26: =SUM(BB26:BE26) -> 0 | CQ26: x
B27: a/a % | C27: [%] | BX27: x | BZ27: =BZ26/BY26-1 -> 1.4086022 | CA27: =CA26/BZ26-1 -> 0.77901786 | CB27: =CB26/CA26-1 -> -0.72772898 | CC27: =CC26/CB26-1 -> -1 | CQ27: x
BX28: x | CQ28: x
B29: EBIT | C29: [BRL 000] | D29: =Inputs!F151/1000 -> 3.966 | E29: =Inputs!G151/1000 -> -0.908 | F29: =Inputs!H151/1000 -> -3.981 | G29: =Inputs!I151/1000 -> -6.604 | H29: =Inputs!J151/1000 -> 2.833 | I29: =Inputs!K151/1000 -> 3.322 | J29: =Inputs!L151/1000 -> 3.208 | K29: =Inputs!M151/1000 -> 5.733 | ... AJ29: =Inputs!AL151/1000 -> 21.645 | AK29: =AK17+AK21+AK26 -> 24.158576 | AL29: =AL17+AL21+AL26 -> 38.701493 | AM29: =AM17+AM21+AM26 -> 36.196654 | AN29: =AN17+AN21+AN26 -> 40.438179 | AO29: =AO17+AO21+AO26 -> 40.320362 | AP29: =AP17+AP21+AP26 -> 45.10044 | AQ29: =AQ17+AQ21+AQ26 -> 49.703378 | AR29: =AR17+AR21+AR26 -> 47.852559 | ... BW29: =BW17+BW21+BW26 -> 111.44024 | BX29: x | BY29: =SUM(D29:G29) -> -7.527 | BZ29: =SUM(H29:K29) -> 15.096 | CA29: =SUM(L29:O29) -> 7.76 | CB29: =SUM(P29:S29) -> -4.632 | CC29: =SUM(T29:W29) -> 20.492 | CD29: =SUM(X29:AA29) -> 104.458 | CE29: =SUM(AB29:AE29) -> 87.398 | CF29: =SUM(AF29:AI29) -> 111.482 | CG29: =SUM(AJ29:AM29) -> 120.70172 | CH29: =SUM(AN29:AQ29) -> 175.56236 | CI29: =SUM(AR29:AU29) -> 204.99103 | CJ29: =SUM(AV29:AY29) -> 233.74647 | CK29: =SUM(AZ29:BC29) -> 255.39939 | CL29: =SUM(BD29:BG29) -> 279.05811 | CM29: =SUM(BH29:BK29) -> 304.90844 | CN29: =SUM(BL29:BO29) -> 333.15339 | CO29: =SUM(BP29:BS29) -> 364.0148 | CP29: =SUM(BT29:BW29) -> 397.73502 | CQ29: x
B30: a/a % | C30: [%] | H30: =H29/D29-1 -> -0.28567827 | I30: =I29/E29-1 -> -4.6585903 | J30: =J29/F29-1 -> -1.8058277 | K30: =K29/G29-1 -> -1.8681102 | L30: =L29/H29-1 -> -0.67278503 | M30: =M29/I29-1 -> -0.37537628 | N30: =N29/J29-1 -> -1.2300499 | O30: =O29/K29-1 -> -0.041339613 | ... BW30: =BW29/BS29-1 -> 0.09263421 | BX30: x | BZ30: =BZ29/BY29-1 -> -3.0055799 | CA30: =CA29/BZ29-1 -> -0.48595654 | CB30: =CB29/CA29-1 -> -1.5969072 | CC30: =CC29/CB29-1 -> -5.4240069 | CD30: =CD29/CC29-1 -> 4.0975015 | CE30: =CE29/CD29-1 -> -0.16331923 | CF30: =CF29/CE29-1 -> 0.27556695 | CG30: =CG29/CF29-1 -> 0.082701451 | ... CP30: =CP29/CO29-1 -> 0.09263421 | CQ30: x
B31: Margem Operacional | C31: [%] | D31: =D29/D$11 -> 0.075843341 | E31: =E29/E$11 -> -0.016806723 | F31: =F29/F$11 -> -0.06483819 | G31: =G29/G$11 -> -0.096009304 | H31: =H29/H$11 -> 0.037229289 | I31: =I29/I$11 -> 0.03939473 | J31: =J29/J$11 -> 0.040158229 | K31: =K29/K$11 -> 0.065948856 | ... BW31: =BW29/BW$11 -> 0.12054265 | BX31: x | BY31: =BY29/BY$11 -> -0.031826369 | BZ31: =BZ29/BZ$11 -> 0.046131703 | CA31: =CA29/CA$11 -> 0.022259704 | CB31: =CB29/CB$11 -> -0.019123664 | CC31: =CC29/CC$11 -> 0.047310229 | CD31: =CD29/CD$11 -> 0.1284066 | CE31: =CE29/CE$11 -> 0.083521755 | CF31: =CF29/CF$11 -> 0.090337585 | ... CP31: =CP29/CP$11 -> 0.11967034 | CQ31: x
BX32: x | CQ32: x
B33: Financial Result | C33: [BRL 000] | D33: =+D35+D36 -> -0.868 | E33: =+E35+E36 -> -1.397 | F33: =+F35+F36 -> -2.506 | G33: =+G35+G36 -> -1.364 | H33: =+H35+H36 -> -2.428 | I33: =+I35+I36 -> -2.741 | J33: =+J35+J36 -> -2.071 | K33: =+K35+K36 -> -1.891 | ... BW33: =+BW35+BW36 -> 6.1974863 | BX33: x | BY33: =SUM(D33:G33) -> -6.135 | BZ33: =SUM(H33:K33) -> -9.131 | CA33: =SUM(L33:O33) -> -13.585 | CB33: =SUM(P33:S33) -> -6.51 | CC33: =SUM(T33:W33) -> -4.313 | CD33: =SUM(X33:AA33) -> -20.278 | CE33: =SUM(AB33:AE33) -> -44.988 | CF33: =SUM(AF33:AI33) -> -52.08 | CG33: =SUM(AJ33:AM33) -> -61.170767 | CH33: =SUM(AN33:AQ33) -> -50.055028 | CI33: =SUM(AR33:AU33) -> -40.96294 | CJ33: =SUM(AV33:AY33) -> -30.595345 | CK33: =SUM(AZ33:BC33) -> -23.681527 | CL33: =SUM(BD33:BG33) -> -17.804875 | CM33: =SUM(BH33:BK33) -> -11.205348 | CN33: =SUM(BL33:BO33) -> -3.7770395 | CO33: =SUM(BP33:BS33) -> 5.1320396 | CP33: =SUM(BT33:BW33) -> 17.300264 | CQ33: x
B34: a/a % | C34: [%] | H34: =H33/D33-1 -> 1.797235 | I34: =I33/E33-1 -> 0.96206156 | J34: =J33/F33-1 -> -0.1735834 | K34: =K33/G33-1 -> 0.38636364 | L34: =L33/H33-1 -> 0.030889621 | M34: =M33/I33-1 -> 0.44582269 | N34: =N33/J33-1 -> 0.76388218 | O34: =O33/K33-1 -> 0.83289265 | ... BW34: =BW33/BS33-1 -> 1.1063754 | BX34: x | BZ34: =BZ33/BY33-1 -> 0.48834556 | CA34: =CA33/BZ33-1 -> 0.48778885 | CB34: =CB33/CA33-1 -> -0.52079499 | CC34: =CC33/CB33-1 -> -0.3374808 | CD34: =CD33/CC33-1 -> 3.7015998 | CE34: =CE33/CD33-1 -> 1.218562 | CF34: =CF33/CE33-1 -> 0.15764204 | CG34: =CG33/CF33-1 -> 0.1745539 | ... CP34: =CP33/CO33-1 -> 2.3710309 | CQ34: x
B35: Receita Financeira | C35: [BRL 000] | D35: =Inputs!F154/1000 -> 0.544 | E35: =Inputs!G154/1000 -> 0.555 | F35: =Inputs!H154/1000 -> 0.776 | G35: =Inputs!I154/1000 -> 0.508 | H35: =Inputs!J154/1000 -> 0.895 | I35: =Inputs!K154/1000 -> 1.644 | J35: =Inputs!L154/1000 -> 2.601 | K35: =Inputs!M154/1000 -> 1.191 | ... AJ35: =Inputs!AL154/1000 -> 7.978 | AK35: =AK243 -> 7.978 | AL35: =AL243 -> 13.517288 | AM35: =AM243 -> 16.641643 | AN35: =AN243 -> 17.492021 | AO35: =AO243 -> 14.104637 | AP35: =AP243 -> 11.345184 | AQ35: =AQ243 -> 14.303383 | AR35: =AR243 -> 15.374316 | ... BW35: =BW243 -> 25.942027 | BX35: x | BY35: =SUM(D35:G35) -> 2.383 | BZ35: =SUM(H35:K35) -> 6.331 | CA35: =SUM(L35:O35) -> 4.465 | CB35: =SUM(P35:S35) -> 4.9 | CC35: =SUM(T35:W35) -> 4.211 | CD35: =SUM(X35:AA35) -> 9.765 | CE35: =SUM(AB35:AE35) -> 14.043 | CF35: =SUM(AF35:AI35) -> 23.376 | CG35: =SUM(AJ35:AM35) -> 46.114931 | CH35: =SUM(AN35:AQ35) -> 57.245224 | CI35: =SUM(AR35:AU35) -> 50.962464 | CJ35: =SUM(AV35:AY35) -> 50.810426 | CK35: =SUM(AZ35:BC35) -> 55.296637 | CL35: =SUM(BD35:BG35) -> 61.173289 | CM35: =SUM(BH35:BK35) -> 67.772816 | CN35: =SUM(BL35:BO35) -> 75.201125 | CO35: =SUM(BP35:BS35) -> 84.110204 | CP35: =SUM(BT35:BW35) -> 96.278428 | CQ35: x
B36: Despesa Financeira | C36: [BRL 000] | D36: =Inputs!F155/1000 -> -1.412 | E36: =Inputs!G155/1000 -> -1.952 | F36: =Inputs!H155/1000 -> -3.282 | G36: =Inputs!I155/1000 -> -1.872 | H36: =Inputs!J155/1000 -> -3.323 | I36: =Inputs!K155/1000 -> -4.385 | J36: =Inputs!L155/1000 -> -4.672 | K36: =Inputs!M155/1000 -> -3.082 | ... AJ36: =Inputs!AL155/1000 -> -23.776 | AK36: =AK240 -> -27.836566 | AL36: =AL240 -> -27.836566 | AM36: =AM240 -> -27.836566 | AN36: =AN240 -> -27.836566 | AO36: =AO240 -> -27.836566 | AP36: =AP240 -> -27.836566 | AQ36: =AQ240 -> -23.790554 | AR36: =AR240 -> -23.790554 | ... BW36: =BW240 -> -19.744541 | BX36: x | BY36: =SUM(D36:G36) -> -8.518 | BZ36: =SUM(H36:K36) -> -15.462 | CA36: =SUM(L36:O36) -> -18.05 | CB36: =SUM(P36:S36) -> -11.41 | CC36: =SUM(T36:W36) -> -8.524 | CD36: =SUM(X36:AA36) -> -30.043 | CE36: =SUM(AB36:AE36) -> -59.031 | CF36: =SUM(AF36:AI36) -> -75.456 | CG36: =SUM(AJ36:AM36) -> -107.2857 | CH36: =SUM(AN36:AQ36) -> -107.30025 | CI36: =SUM(AR36:AU36) -> -91.925404 | CJ36: =SUM(AV36:AY36) -> -81.405772 | CK36: =SUM(AZ36:BC36) -> -78.978164 | CL36: =SUM(BD36:BG36) -> -78.978164 | CM36: =SUM(BH36:BK36) -> -78.978164 | CN36: =SUM(BL36:BO36) -> -78.978164 | CO36: =SUM(BP36:BS36) -> -78.978164 | CP36: =SUM(BT36:BW36) -> -78.978164 | CQ36: x
BX37: x | CQ37: x | CV37: 264 | CW37: 400 | CX37: =(CW37/CV37)^(1/2)-1 -> 0.23091491
B38: EBT | C38: [BRL 000] | D38: =Inputs!F157/1000 -> 3.098 | E38: =Inputs!G157/1000 -> -2.305 | F38: =Inputs!H157/1000 -> -6.487 | G38: =Inputs!I157/1000 -> -7.968 | H38: =Inputs!J157/1000 -> 0.405 | I38: =Inputs!K157/1000 -> 0.581 | J38: =Inputs!L157/1000 -> 1.137 | K38: =Inputs!M157/1000 -> 3.842 | ... AJ38: =Inputs!AL157/1000 -> 5.847 | AK38: =AK29+AK33 -> 4.3000098 | AL38: =AL29+AL33 -> 24.382215 | AM38: =AM29+AM33 -> 25.001731 | AN38: =AN29+AN33 -> 30.093633 | AO38: =AO29+AO33 -> 26.588433 | AP38: =AP29+AP33 -> 28.609057 | AQ38: =AQ29+AQ33 -> 40.216208 | AR38: =AR29+AR33 -> 39.436321 | ... BW38: =BW29+BW33 -> 117.63773 | BX38: x | BY38: =SUM(D38:G38) -> -13.662 | BZ38: =SUM(H38:K38) -> 5.965 | CA38: =SUM(L38:O38) -> -5.825 | CB38: =SUM(P38:S38) -> -11.142 | CC38: =SUM(T38:W38) -> 16.179 | CD38: =SUM(X38:AA38) -> 84.18 | CE38: =SUM(AB38:AE38) -> 42.41 | CF38: =SUM(AF38:AI38) -> 59.402 | CG38: =SUM(AJ38:AM38) -> 59.530956 | CH38: =SUM(AN38:AQ38) -> 125.50733 | CI38: =SUM(AR38:AU38) -> 164.02809 | CJ38: =SUM(AV38:AY38) -> 203.15113 | CK38: =SUM(AZ38:BC38) -> 231.71787 | CL38: =SUM(BD38:BG38) -> 261.25324 | CM38: =SUM(BH38:BK38) -> 293.70309 | CN38: =SUM(BL38:BO38) -> 329.37635 | CO38: =SUM(BP38:BS38) -> 369.14684 | CP38: =SUM(BT38:BW38) -> 415.03528 | CQ38: x
B39: a/a % | C39: [%] | H39: =H38/D38-1 -> -0.8692705 | I39: =I38/E38-1 -> -1.2520607 | J39: =J38/F38-1 -> -1.1752736 | K39: =K38/G38-1 -> -1.4821787 | L39: =L38/H38-1 -> -4.891358 | M39: =M38/I38-1 -> -4.2495697 | N39: =N38/J38-1 -> -4.8619173 | O39: =O38/K38-1 -> -0.47162936 | ... BW39: =BW38/BS38-1 -> 0.12105843 | BX39: x | CQ39: x
B40: Margem EBT | C40: [%] | D40: =D38/D$11 -> 0.059244244 | E40: =E38/E$11 -> -0.042664643 | F40: =F38/F$11 -> -0.10565319 | G40: =G38/G$11 -> -0.11583921 | H40: =H38/H$11 -> 0.0053222246 | I40: =I38/I$11 -> 0.0068899272 | J40: =J38/J$11 -> 0.014233138 | K40: =K38/K$11 -> 0.044195972 | ... BW40: =BW38/BW$11 -> 0.12724635 | BX40: x | BZ40: =BZ38/BZ$11 -> 0.018228379 | CA40: =CA38/CA$11 -> -0.016709121 | CB40: =CB38/CB$11 -> -0.046000834 | CC40: =CC38/CC$11 -> 0.037352733 | CD40: =CD38/CD$11 -> 0.10347956 | CE40: =CE38/CE$11 -> 0.040529047 | CF40: =CF38/CF$11 -> 0.048135423 | CG40: =CG38/CG$11 -> 0.039901681 | ... CP40: =CP38/CP$11 -> 0.12487564 | CQ40: x
BX41: x | CQ41: x
B42: IR | C42: [BRL 000] | D42: =(Inputs!F159/1000)+(Inputs!F160/1000) -> -0.826 | E42: =(Inputs!G159/1000)+(Inputs!G160/1000) -> 0.952 | F42: =(Inputs!H159/1000)+(Inputs!H160/1000) -> 2.424 | G42: =(Inputs!I159/1000)+(Inputs!I160/1000) -> 3.724 | H42: =(Inputs!J159/1000)+(Inputs!J160/1000) -> 0.315 | I42: =(Inputs!K159/1000)+(Inputs!K160/1000) -> -0.423 | J42: =(Inputs!L159/1000)+(Inputs!L160/1000) -> -2.329 | K42: =(Inputs!M159/1000)+(Inputs!M160/1000) -> 1.612 | ... AJ42: =(Inputs!AL159/1000)+(Inputs!AL160/1000) -> -1.83 | AK42: =-AK38*AK43 -> -1.3458214 | AL42: =-AL38*AL43 -> -7.6311703 | AM42: =-AM38*AM43 -> -7.8250673 | AN42: =-AN38*AN43 -> -9.4187359 | AO42: =-AO38*AO43 -> -8.3216747 | AP42: =-AP38*AP43 -> -8.9540918 | AQ42: =-AQ38*AQ43 -> -12.58691 | AR42: =-AR38*AR43 -> -12.34282 | ... BW42: =-BW38*BW43 -> -36.818375 | BX42: x | BY42: =SUM(D42:G42) -> 6.274 | BZ42: =SUM(H42:K42) -> -0.825 | CA42: =SUM(L42:O42) -> -4.973 | CB42: =SUM(P42:S42) -> 8.046 | CC42: =SUM(T42:W42) -> -1.68 | CD42: =SUM(X42:AA42) -> -19.246 | CE42: =SUM(AB42:AE42) -> -17.331 | CF42: =SUM(AF42:AI42) -> -17.147 | CG42: =SUM(AJ42:AM42) -> -18.632059 | CH42: =SUM(AN42:AQ42) -> -39.281412 | CI42: =SUM(AR42:AU42) -> -51.337677 | CJ42: =SUM(AV42:AY42) -> -63.582446 | CK42: =SUM(AZ42:BC42) -> -72.523293 | CL42: =SUM(BD42:BG42) -> -81.767304 | CM42: =SUM(BH42:BK42) -> -91.923493 | CN42: =SUM(BL42:BO42) -> -103.08855 | CO42: =SUM(BP42:BS42) -> -115.53595 | CP42: =SUM(BT42:BW42) -> -129.89816 | CQ42: x
B43: Imposto de renda | C43: [%] | D43: =-D42/D38 -> 0.26662363 | E43: =-E42/E38 -> 0.41301518 | F43: =-F42/F38 -> 0.37367042 | G43: =-G42/G38 -> 0.46736948 | H43: =-H42/H38 -> -0.77777778 | I43: =-I42/I38 -> 0.72805508 | J43: =-J42/J38 -> 2.0483729 | K43: =-K42/K38 -> -0.41957314 | ... AJ43: =-AJ42/AJ38 -> 0.31298102 | AK43: =AJ43 -> 0.31298102 | AL43: =AK43 -> 0.31298102 | AM43: =AL43 -> 0.31298102 | AN43: =AM43 -> 0.31298102 | AO43: =AN43 -> 0.31298102 | AP43: =AO43 -> 0.31298102 | AQ43: =AP43 -> 0.31298102 | AR43: =AQ43 -> 0.31298102 | ... BW43: =BV43 -> 0.31298102 | BX43: x | BY43: =-BY42/BY38 -> 0.45922998 | BZ43: =-BZ42/BZ38 -> 0.13830679 | CA43: =-CA42/CA38 -> -0.85373391 | CB43: =-CB42/CB38 -> 0.72213247 | CC43: =-CC42/CC38 -> 0.10383831 | CD43: =-CD42/CD38 -> 0.22862913 | CE43: =-CE42/CE38 -> 0.40865362 | CF43: =-CF42/CF38 -> 0.28866031 | ... CP43: =-CP42/CP38 -> 0.31298102 | CQ43: x
B44: Diferido | C44: [BRL 000] | BX44: x | CQ44: x
B45: Corrente | C45: [BRL 000] | BX45: x | CQ45: x
BX46: x | CQ46: x
B47: Lucro Líquido | C47: [BRL 000] | D47: =Inputs!F162/1000 -> 2.272 | E47: =Inputs!G162/1000 -> -1.353 | F47: =Inputs!H162/1000 -> -4.063 | G47: =Inputs!I162/1000 -> -4.244 | H47: =Inputs!J162/1000 -> 0.72 | I47: =Inputs!K162/1000 -> 0.158 | J47: =Inputs!L162/1000 -> -1.192 | K47: =Inputs!M162/1000 -> 5.454 | ... AJ47: =Inputs!AL162/1000 -> 4.017 | AK47: =AK38+AK42 -> 2.9541884 | AL47: =AL38+AL42 -> 16.751044 | AM47: =AM38+AM42 -> 17.176664 | AN47: =AN38+AN42 -> 20.674897 | AO47: =AO38+AO42 -> 18.266758 | AP47: =AP38+AP42 -> 19.654965 | AQ47: =AQ38+AQ42 -> 27.629298 | AR47: =AR38+AR42 -> 27.093501 | ... BW47: =BW38+BW42 -> 80.819351 | BX47: x | BY47: =SUM(D47:G47) -> -7.388 | BZ47: =SUM(H47:K47) -> 5.14 | CA47: =SUM(L47:O47) -> -10.798 | CB47: =SUM(P47:S47) -> -3.096 | CC47: =SUM(T47:W47) -> 14.499 | CD47: =SUM(X47:AA47) -> 64.934 | CE47: =SUM(AB47:AE47) -> 25.079 | CF47: =SUM(AF47:AI47) -> 42.255 | CG47: =SUM(AJ47:AM47) -> 40.898897 | CH47: =SUM(AN47:AQ47) -> 86.225919 | CI47: =SUM(AR47:AU47) -> 112.69041 | CJ47: =SUM(AV47:AY47) -> 139.56868 | CK47: =SUM(AZ47:BC47) -> 159.19457 | CL47: =SUM(BD47:BG47) -> 179.48593 | CM47: =SUM(BH47:BK47) -> 201.7796 | CN47: =SUM(BL47:BO47) -> 226.28781 | CO47: =SUM(BP47:BS47) -> 253.61088 | CP47: =SUM(BT47:BW47) -> 285.13712 | CQ47: x
B48: a/a % | C48: [%] | H48: =H47/D47-1 -> -0.68309859 | I48: =I47/E47-1 -> -1.1167775 | J48: =J47/F47-1 -> -0.70662072 | K48: =K47/G47-1 -> -2.2851084 | L48: =L47/H47-1 -> -1.7013889 | M48: =M47/I47-1 -> -13.56962 | N48: =N47/J47-1 -> 1.4689597 | O48: =O47/K47-1 -> -1.9834984 | ... BW48: =BW47/BS47-1 -> 0.12105843 | BX48: x | BZ48: =BZ47/BY47-1 -> -1.6957228 | CA48: =CA47/BZ47-1 -> -3.1007782 | CB48: =CB47/CA47-1 -> -0.71328024 | CC48: =CC47/CB47-1 -> -5.6831395 | CD48: =CD47/CC47-1 -> 3.4785158 | CE48: =CE47/CD47-1 -> -0.61377707 | CF48: =CF47/CE47-1 -> 0.68487579 | CG48: =CG47/CF47-1 -> -0.032093318 | ... CP48: =CP47/CO47-1 -> 0.12430947 | CQ48: x
B49: Margem líquida | C49: [%] | D49: =D47/D$11 -> 0.043448329 | E49: =E47/E$11 -> -0.025043498 | F49: =F47/F$11 -> -0.066173716 | G49: =G47/G$11 -> -0.061699498 | H49: =H47/H$11 -> 0.0094617325 | I49: =I47/I$11 -> 0.0018736807 | J49: =J47/J$11 -> -0.014921636 | K49: =K47/K$11 -> 0.062739414 | ... BW49: =BW47/BW$11 -> 0.087420656 | BX49: x | BZ49: =BZ47/BZ$11 -> 0.01570727 | CA49: =CA47/CA$11 -> -0.030974264 | CB49: =CB47/CB$11 -> -0.012782138 | CC49: =CC47/CC$11 -> 0.033474088 | CD49: =CD47/CD$11 -> 0.079821117 | CE49: =CE47/CE$11 -> 0.023966705 | CF49: =CF47/CF$11 -> 0.034240637 | CG49: =CG47/CG$11 -> 0.027413212 | ... CP49: =CP47/CP$11 -> 0.085791934 | CQ49: x
BX50: x | CQ50: x
B51: (+) D&A | C51: [BRL 000] | D51: =(Inputs!F171/1000)+(Inputs!F178/1000) -> -2.305 | E51: =(Inputs!G171/1000)+(Inputs!G178/1000) -> -2.3554 | F51: =(Inputs!H171/1000)+(Inputs!H178/1000) -> -3.514 | G51: =(Inputs!I171/1000)+(Inputs!I178/1000) -> -4.0293 | H51: =(Inputs!J171/1000)+(Inputs!J178/1000) -> -4.091 | I51: =(Inputs!K171/1000)+(Inputs!K178/1000) -> -4.096 | J51: =(Inputs!L171/1000)+(Inputs!L178/1000) -> -4.0526617 | K51: =(Inputs!M171/1000)+(Inputs!M178/1000) -> -2.4413383 | ... AJ51: =(Inputs!AL171/1000)+(Inputs!AL178/1000) -> -18.464 | AK51: =-AK212 -> -18.06306 | AL51: =-AL212 -> -18.326848 | AM51: =-AM212 -> -18.390916 | AN51: =-AN212 -> -18.646488 | AO51: =-AO212 -> -18.756186 | AP51: =-AP212 -> -18.692107 | AQ51: =-AQ212 -> -19.244533 | AR51: =-AR212 -> -19.535542 | ... BW51: =-BW212 -> -30.538045 | BX51: x | BY51: =SUM(D51:G51) -> -12.2037 | BZ51: =SUM(H51:K51) -> -14.681 | CA51: =SUM(L51:O51) -> -19.705 | CB51: =SUM(P51:S51) -> -21.643 | CC51: =SUM(T51:W51) -> -20.910258 | CD51: =SUM(X51:AA51) -> -26.296882 | CE51: =SUM(AB51:AE51) -> -39.060936 | CF51: =SUM(AF51:AI51) -> -49.136333 | CG51: =SUM(AJ51:AM51) -> -73.244824 | CH51: =SUM(AN51:AQ51) -> -75.339315 | CI51: =SUM(AR51:AU51) -> -79.057828 | CJ51: =SUM(AV51:AY51) -> -83.054921 | CK51: =SUM(AZ51:BC51) -> -87.942324 | CL51: =SUM(BD51:BG51) -> -93.677403 | CM51: =SUM(BH51:BK51) -> -100.22702 | CN51: =SUM(BL51:BO51) -> -107.66441 | CO51: =SUM(BP51:BS51) -> -114.58463 | CP51: =SUM(BT51:BW51) -> -120.07188 | CQ51: x
B52: EBITDA | C52: [BRL 000] | D52: =D29-D51 -> 6.271 | E52: =E29-E51 -> 1.4474 | F52: =F29-F51 -> -0.467 | G52: =G29-G51 -> -2.5747 | H52: =H29-H51 -> 6.924 | I52: =I29-I51 -> 7.418 | J52: =J29-J51 -> 7.2606617 | K52: =K29-K51 -> 8.1743383 | ... BW52: =BW29-BW51 -> 141.97829 | BX52: x | BY52: =SUM(D52:G52) -> 4.6767 | BZ52: =SUM(H52:K52) -> 29.777 | CA52: =SUM(L52:O52) -> 27.465 | CB52: =SUM(P52:S52) -> 17.011 | CC52: =SUM(T52:W52) -> 41.402258 | CD52: =SUM(X52:AA52) -> 130.75488 | CE52: =SUM(AB52:AE52) -> 126.45894 | CF52: =SUM(AF52:AI52) -> 160.61833 | CG52: =SUM(AJ52:AM52) -> 193.94655 | CH52: =SUM(AN52:AQ52) -> 250.90167 | CI52: =SUM(AR52:AU52) -> 284.04885 | CJ52: =SUM(AV52:AY52) -> 316.80139 | CK52: =SUM(AZ52:BC52) -> 343.34172 | CL52: =SUM(BD52:BG52) -> 372.73552 | CM52: =SUM(BH52:BK52) -> 405.13546 | CN52: =SUM(BL52:BO52) -> 440.81781 | CO52: =SUM(BP52:BS52) -> 478.59943 | CP52: =SUM(BT52:BW52) -> 517.8069 | CQ52: x
B53: a/a % | C53: [%] | H53: =H52/D52-1 -> 0.10413012 | I53: =I52/E52-1 -> 4.1250518 | J53: =J52/F52-1 -> -16.547455 | K53: =K52/G52-1 -> -4.1748702 | L53: =L52/H52-1 -> -0.18756641 | M53: =M52/I52-1 -> -0.050417902 | N53: =N52/J52-1 -> -0.40922071 | O53: =O52/K52-1 -> 0.2852736 | ... BW53: =BW52/BS52-1 -> 0.083352826 | BX53: x | BZ53: =BZ52/BY52-1 -> 5.3670965 | CA53: =CA52/BZ52-1 -> -0.077643819 | CB53: =CB52/CA52-1 -> -0.38062989 | CC53: =CC52/CB52-1 -> 1.4338521 | CD53: =CD52/CC52-1 -> 2.1581583 | CE53: =CE52/CD52-1 -> -0.032854957 | CF53: =CF52/CE52-1 -> 0.27012244 | CG53: =CG52/CF52-1 -> 0.20749944 | ... CP53: =CP52/CO52-1 -> 0.081921268 | CQ53: x
B54: Margem EBITDA | C54: [%] | D54: =D52/D$11 -> 0.11992274 | E54: =E52/E$11 -> 0.026790804 | F54: =F52/F$11 -> -0.0076059871 | G54: =G52/G$11 -> -0.037431126 | H54: =H52/H$11 -> 0.090990328 | I54: =I52/I$11 -> 0.087968124 | J54: =J52/J$11 -> 0.090890062 | K54: =K52/K$11 -> 0.094032489 | ... BW54: =BW52/BW$11 -> 0.15357504 | BX54: x | BY54: =BY52/BY$11 -> 0.019774463 | BZ54: =BZ52/BZ$11 -> 0.090995211 | CA54: =CA52/CA$11 -> 0.078783863 | CB54: =CB52/CB$11 -> 0.070231573 | CC54: =CC52/CC$11 -> 0.095586097 | CD54: =CD52/CD$11 -> 0.16073245 | CE54: =CE52/CE$11 -> 0.12085027 | CF54: =CF52/CF$11 -> 0.13015439 | ... CP54: =CP52/CP$11 -> 0.15579752 | CQ54: x
BX55: x | CQ55: x
A56: l | B56: Balanço Patrimonial | BX56: x | CQ56: x
BX57: x | CQ57: x
B58: Ativos Totais | C58: [BRL 000] | D58: =+D60+D67 -> 117.04 | E58: =+E60+E67 -> 140.695 | F58: =+F60+F67 -> 173.054 | G58: =+G60+G67 -> 182.406 | H58: =+H60+H67 -> 192.752 | I58: =+I60+I67 -> 200.024 | J58: =+J60+J67 -> 198.706 | K58: =+K60+K67 -> 207.986 | ... BW58: =+BW60+BW67 -> 2916.0891 | BX58: x | BY58: =G58 -> 182.406 | BZ58: =K58 -> 207.986 | CA58: =O58 -> 239.541 | CB58: =S58 -> 336.63 | CC58: =W58 -> 374.377 | CD58: =AA58 -> 619.93919 | CE58: =AE58 -> 837.004 | CF58: =AI58 -> 1243.6 | CG58: =AM58 -> 1457.8969 | CH58: =AQ58 -> 1541.9498 | CI58: =AU58 -> 1644.671 | CJ58: =AY58 -> 1769.5759 | CK58: =BC58 -> 1911.074 | CL58: =BG58 -> 2069.8381 | CM58: =BK58 -> 2247.5595 | CN58: =BO58 -> 2446.1064 | CO58: =BS58 -> 2667.8164 | CP58: =BW58 -> 2916.0891 | CQ58: x
BX59: x | CQ59: x
B60: Ativos Circulantes | C60: [BRL 000] | D60: =+D61+D62+D63+D64+D65 -> 65.748 | E60: =+E61+E62+E63+E64+E65 -> 89.061 | F60: =+F61+F62+F63+F64+F65 -> 82.881 | G60: =+G61+G62+G63+G64+G65 -> 90.691 | H60: =+H61+H62+H63+H64+H65 -> 99.198 | I60: =+I61+I62+I63+I64+I65 -> 98.335 | J60: =+J61+J62+J63+J64+J65 -> 99.755 | K60: =+K61+K62+K63+K64+K65 -> 105.316 | ... BW60: =+BW61+BW62+BW63+BW64+BW65 -> 1900.4364 | BX60: x | BY60: =G60 -> 90.691 | BZ60: =K60 -> 105.316 | CA60: =O60 -> 127.862 | CB60: =S60 -> 204.847 | CC60: =W60 -> 212.104 | CD60: =AA60 -> 353.888 | CE60: =AE60 -> 445.227 | CF60: =AI60 -> 609.764 | CG60: =AM60 -> 808.87206 | CH60: =AQ60 -> 870.61585 | CI60: =AU60 -> 945.13558 | CJ60: =AY60 -> 1035.9002 | CK60: =BC60 -> 1137.2892 | CL60: =BG60 -> 1249.8173 | CM60: =BK60 -> 1374.8915 | CN60: =BO60 -> 1514.0673 | CO60: =BS60 -> 1698.2712 | CP60: =BW60 -> 1900.4364 | CQ60: x | CX60: =AH60-AG60 -> 154.472 | CY60: =AI60-AH60 -> -8.209
B61: =Inputs!B6 -> Caixa e equivalentes de caixa | D61: 9.843 | E61: 36.073 | F61: 4.845 | G61: 2.508 | H61: 2.408 | I61: =(Inputs!K6+Inputs!K7+Inputs!K8)/1000 -> 5.296 | J61: =(Inputs!L6+Inputs!L7+Inputs!L8)/1000 -> 5.107 | K61: =-(Inputs!M6+Inputs!M7+Inputs!M8)/1000 -> 3.428 | L61: =(Inputs!N6+Inputs!N7+Inputs!N8)/1000 -> 5.104 | M61: =(Inputs!O6+Inputs!O7+Inputs!O8)/1000 -> 26.91 | N61: =(Inputs!P6+Inputs!P7+Inputs!P8)/1000 -> 26.669 | O61: =(Inputs!Q6+Inputs!Q7+Inputs!Q8)/1000 -> 44.528 | P61: =(Inputs!R6+Inputs!R7+Inputs!R8)/1000 -> 147.452 | Q61: =(Inputs!S6+Inputs!S7+Inputs!S8)/1000 -> 149.107 | R61: =(Inputs!T6+Inputs!T7+Inputs!T8)/1000 -> 135.441 | S61: =(Inputs!U6+Inputs!U7+Inputs!U8)/1000 -> 110.422 | ... AJ61: =(Inputs!AL6+Inputs!AL7+Inputs!AL8)/1000 -> 360.461 | AK61: =AK158 -> 443.77715 | AL61: =AL158 -> 466.45388 | AM61: =AM158 -> 451.34838 | AN61: =AN158 -> 363.04588 | AO61: =AO158 -> 457.70826 | AP61: =AP158 -> 491.97811 | AQ61: =AQ158 -> 485.45592 | AR61: =AR158 -> 381.03053 | ... BW61: =BW158 -> 1139.1351 | BX61: x | BY61: =G61 -> 2.508 | BZ61: =K61 -> 3.428 | CA61: =O61 -> 44.528 | CB61: =S61 -> 110.422 | CC61: =W61 -> 76.649 | CD61: =AA61 -> 115.887 | CE61: =AE61 -> 136.902 | CF61: =AI61 -> 243.739 | CG61: =AM61 -> 451.34838 | CH61: =AQ61 -> 485.45592 | CI61: =AU61 -> 526.20332 | CJ61: =AY61 -> 580.05513 | CK61: =BC61 -> 641.11192 | CL61: =BG61 -> 709.57165 | CM61: =BK61 -> 786.49533 | CN61: =BO61 -> 873.06009 | CO61: =BS61 -> 999.77947 | CP61: =BW61 -> 1139.1351 | CQ61: x | CX61: =AH61-AG61 -> 1.569 | CY61: =AI61-AH61 -> 50.624
B62: =Inputs!B9 -> Contas a receber | D62: 49.519 | E62: 44.691 | F62: 58.978 | G62: 67.184 | H62: 76.973 | I62: =(Inputs!K9+Inputs!K10+Inputs!K11)/1000 -> 70.422 | J62: =(Inputs!L9+Inputs!L10+Inputs!L11)/1000 -> 66.556 | K62: =-(Inputs!M9+Inputs!M10+Inputs!M11)/1000 -> 69.815 | L62: =(Inputs!N9+Inputs!N10+Inputs!N11)/1000 -> 71.528 | M62: =(Inputs!O9+Inputs!O10+Inputs!O11)/1000 -> 65.509 | N62: =(Inputs!P9+Inputs!P10+Inputs!P11)/1000 -> 60.125 | O62: =(Inputs!Q9+Inputs!Q10+Inputs!Q11)/1000 -> 52.607 | P62: =(Inputs!R9+Inputs!R10+Inputs!R11)/1000 -> 69.492 | Q62: =(Inputs!S9+Inputs!S10+Inputs!S11)/1000 -> 51.624 | R62: =(Inputs!T9+Inputs!T10+Inputs!T11)/1000 -> 54.726 | S62: =(Inputs!U9+Inputs!U10+Inputs!U11)/1000 -> 63.078 | ... AJ62: =(Inputs!AL9+Inputs!AL10+Inputs!AL11)/1000 -> 380.24 | AK62: =AK170 -> 312.26864 | AL62: =AL170 -> 314.01571 | AM62: =AM170 -> 311.68253 | AN62: =AN170 -> 388.40473 | AO62: =AO170 -> 330.87119 | AP62: =AP170 -> 342.80038 | AQ62: =AQ170 -> 336.51229 | AR62: =AR170 -> 429.6495 | ... BW62: =BW170 -> 683.59564 | BX62: x | BY62: =G62 -> 67.184 | BZ62: =K62 -> 69.815 | CA62: =O62 -> 52.607 | CB62: =S62 -> 63.078 | CC62: =W62 -> 108.811 | CD62: =AA62 -> 205.273 | CE62: =AE62 -> 276.728 | CF62: =AI62 -> 319.533 | CG62: =AM62 -> 311.68253 | CH62: =AQ62 -> 336.51229 | CI62: =AU62 -> 367.68484 | CJ62: =AY62 -> 401.74503 | CK62: =BC62 -> 438.96037 | CL62: =BG62 -> 479.62311 | CM62: =BK62 -> 524.05262 | CN62: =BO62 -> 572.59782 | CO62: =BS62 -> 625.63997 | CP62: =BW62 -> 683.59564 | CQ62: x | CX62: =AH62-AG62 -> 132.678 | CY62: =AI62-AH62 -> -36.675
B63: =Inputs!B12 -> Estoques | D63: 0.027 | E63: 0.017 | F63: 0.313 | G63: 1.662 | H63: 0.067 | I63: =Inputs!K12/1000 -> 1.469 | J63: =Inputs!L12/1000 -> 1.529 | K63: =-Inputs!M12/1000 -> 1.052 | L63: =Inputs!N12/1000 -> 1.336 | M63: =Inputs!O12/1000 -> 0.684 | N63: =Inputs!P12/1000 -> 1.442 | O63: =Inputs!Q12/1000 -> 0.692 | P63: =Inputs!R12/1000 -> 0.924 | Q63: =Inputs!S12/1000 -> 0.639 | R63: =Inputs!T12/1000 -> 1.172 | S63: =Inputs!U12/1000 -> 1.282 | ... AJ63: =Inputs!AL12/1000 -> 6.781 | AK63: =AK174 -> 9.5678571 | AL63: =AL174 -> 5.2909114 | AM63: =AM174 -> 5.8434328 | AN63: =AN174 -> 6.9456222 | AO63: =AO174 -> 10.35702 | AP63: =AP174 -> 5.9022368 | AQ63: =AQ174 -> 6.4674401 | AR63: =AR174 -> 7.6603976 | ... BW63: =BW174 -> 13.115709 | BX63: x | BY63: =G63 -> 1.662 | BZ63: =K63 -> 1.052 | CA63: =O63 -> 0.692 | CB63: =S63 -> 1.282 | CC63: =W63 -> 3.628 | CD63: =AA63 -> 5.361 | CE63: =AE63 -> 4.609 | CF63: =AI63 -> 5.778 | CG63: =AM63 -> 5.8434328 | CH63: =AQ63 -> 6.4674401 | CI63: =AU63 -> 7.0545318 | CJ63: =AY63 -> 7.7080228 | CK63: =BC63 -> 8.4220494 | CL63: =BG63 -> 9.2022193 | CM63: =BK63 -> 10.05466 | CN63: =BO63 -> 10.986065 | CO63: =BS63 -> 12.003751 | CP63: =BW63 -> 13.115709 | CQ63: x | CX63: =AH63-AG63 -> 0.04 | CY63: =AI63-AH63 -> 0.046
B64: =Inputs!B14 -> Tributos a recuperar | D64: 5.349 | E64: 6.882 | F64: 10.926 | G64: 11.873 | H64: 12.686 | I64: =Inputs!K14/1000 -> 14.387 | J64: =Inputs!L14/1000 -> 18.521 | K64: =-Inputs!M14/1000 -> 23.011 | L64: =Inputs!N14/1000 -> 24.61 | M64: =Inputs!O14/1000 -> 25.535 | N64: =Inputs!P14/1000 -> 25.518 | O64: =Inputs!Q14/1000 -> 25.022 | P64: =Inputs!R14/1000 -> 25.696 | Q64: =Inputs!S14/1000 -> 27.577 | R64: =Inputs!T14/1000 -> 27.586 | S64: =Inputs!U14/1000 -> 22.788 | ... AJ64: =Inputs!AL14/1000 -> 27.294 | AK64: =AK178 -> 46.825373 | AL64: =AL178 -> 23.752086 | AM64: =AM178 -> 19.54472 | AN64: =AN178 -> 28.485706 | AO64: =AO178 -> 50.881002 | AP64: =AP178 -> 26.596126 | AQ64: =AQ178 -> 21.727208 | AR64: =AR178 -> 31.510609 | ... BW64: =BW178 -> 44.136945 | BX64: x | BY64: =G64 -> 11.873 | BZ64: =K64 -> 23.011 | CA64: =O64 -> 25.022 | CB64: =S64 -> 22.788 | CC64: =W64 -> 12.693 | CD64: =AA64 -> 12.392 | CE64: =AE64 -> 15.428 | CF64: =AI64 -> 20.037 | CG64: =AM64 -> 19.54472 | CH64: =AQ64 -> 21.727208 | CI64: =AU64 -> 23.739891 | CJ64: =AY64 -> 25.939017 | CK64: =BC64 -> 28.341857 | CL64: =BG64 -> 30.967282 | CM64: =BK64 -> 33.835912 | CN64: =BO64 -> 36.970275 | CO64: =BS64 -> 40.394987 | CP64: =BW64 -> 44.136945 | CQ64: x | CX64: =AH64-AG64 -> -1.143 | CY64: =AI64-AH64 -> -5.93
B65: =Inputs!B21 -> Outros ativos circulantes | D65: 1.01 | E65: 1.398 | F65: 7.819 | G65: 7.464 | H65: 7.064 | I65: =(Inputs!K22/1000)-SUM(Modelo!I61:I64) -> 6.761 | J65: =(Inputs!L22/1000)-SUM(Modelo!J61:J64) -> 8.042 | K65: =-(Inputs!M22/1000)-SUM(Modelo!K61:K64) -> 8.01 | L65: =(Inputs!N22/1000)-SUM(Modelo!L61:L64) -> 6.908 | M65: =(Inputs!O22/1000)-SUM(Modelo!M61:M64) -> 6.306 | N65: =(Inputs!P22/1000)-SUM(Modelo!N61:N64) -> 5.294 | O65: =(Inputs!Q22/1000)-SUM(Modelo!O61:O64) -> 5.013 | P65: =(Inputs!R22/1000)-SUM(Modelo!P61:P64) -> 18.75 | Q65: =(Inputs!S22/1000)-SUM(Modelo!Q61:Q64) -> 17.89 | R65: =(Inputs!T22/1000)-SUM(Modelo!R61:R64) -> 3.526 | S65: =(Inputs!U22/1000)-SUM(Modelo!S61:S64) -> 7.277 | ... AJ65: =(Inputs!AL22/1000)-SUM(Modelo!AJ61:AJ64) -> 20.453 | AK65: =AJ65 -> 20.453 | AL65: =AK65 -> 20.453 | AM65: =AL65 -> 20.453 | AN65: =AM65 -> 20.453 | AO65: =AN65 -> 20.453 | AP65: =AO65 -> 20.453 | AQ65: =AP65 -> 20.453 | AR65: =AQ65 -> 20.453 | ... BW65: =BV65 -> 20.453 | BX65: x | BY65: =G65 -> 7.464 | BZ65: =K65 -> 8.01 | CA65: =O65 -> 5.013 | CB65: =S65 -> 7.277 | CC65: =W65 -> 10.323 | CD65: =AA65 -> 14.975 | CE65: =AE65 -> 11.56 | CF65: =AI65 -> 20.677 | CG65: =AM65 -> 20.453 | CH65: =AQ65 -> 20.453 | CI65: =AU65 -> 20.453 | CJ65: =AY65 -> 20.453 | CK65: =BC65 -> 20.453 | CL65: =BG65 -> 20.453 | CM65: =BK65 -> 20.453 | CN65: =BO65 -> 20.453 | CO65: =BS65 -> 20.453 | CP65: =BW65 -> 20.453 | CQ65: x | CX65: =AH65-AG65 -> 21.328 | CY65: =AI65-AH65 -> -16.274
BX66: x | CQ66: x
B67: Ativos Não-Circulantes | C67: [BRL 000] | D67: =+D68+D69+D70+D71+D72 -> 51.292 | E67: =+E68+E69+E70+E71+E72 -> 51.634 | F67: =+F68+F69+F70+F71+F72 -> 90.173 | G67: =+G68+G69+G70+G71+G72 -> 91.715 | H67: =+H68+H69+H70+H71+H72 -> 93.554 | I67: =+I68+I69+I70+I71+I72 -> 101.689 | J67: =+J68+J69+J70+J71+J72 -> 98.951 | K67: =+K68+K69+K70+K71+K72 -> 102.67 | ... BW67: =+BW68+BW69+BW70+BW71+BW72 -> 1015.6528 | BX67: x | BY67: =G67 -> 91.715 | BZ67: =K67 -> 102.67 | CA67: =O67 -> 111.679 | CB67: =S67 -> 131.783 | CC67: =W67 -> 162.273 | CD67: =AA67 -> 266.05119 | CE67: =AE67 -> 391.777 | CF67: =AI67 -> 633.836 | CG67: =AM67 -> 649.0248 | CH67: =AQ67 -> 671.33394 | CI67: =AU67 -> 699.53542 | CJ67: =AY67 -> 733.67569 | CK67: =BC67 -> 773.78484 | CL67: =BG67 -> 820.02086 | CM67: =BK67 -> 872.66803 | CN67: =BO67 -> 932.03919 | CO67: =BS67 -> 969.5452 | CP67: =BW67 -> 1015.6528 | CQ67: x | CX67: =AH67-AG67 -> 137.905 | CY67: =AI67-AH67 -> 44.433
B68: Contas a Receber | D68: 0 | E68: 0 | F68: 0 | G68: 0 | H68: 0.334 | I68: =(Inputs!K24+Inputs!K25)/1000 -> 0.177 | J68: =(Inputs!L24+Inputs!L25)/1000 -> 0 | K68: =-(Inputs!M24+Inputs!M25)/1000 -> 0 | L68: =(Inputs!N24+Inputs!N25)/1000 -> 0 | M68: =(Inputs!O24+Inputs!O25)/1000 -> 0 | N68: =(Inputs!P24+Inputs!P25)/1000 -> 0.997 | O68: =(Inputs!Q24+Inputs!Q25)/1000 -> 0.997 | P68: =(Inputs!R24+Inputs!R25)/1000 -> 4.251 | Q68: =(Inputs!S24+Inputs!S25)/1000 -> 4.251 | R68: =(Inputs!T24+Inputs!T25)/1000 -> 4.251 | S68: =(Inputs!U24+Inputs!U25)/1000 -> 4.251 | ... AJ68: =(Inputs!AL24+Inputs!AL25)/1000 -> 5.123 | AK68: =AJ68 -> 5.123 | AL68: =AK68 -> 5.123 | AM68: =AL68 -> 5.123 | AN68: =AM68 -> 5.123 | AO68: =AN68 -> 5.123 | AP68: =AO68 -> 5.123 | AQ68: =AP68 -> 5.123 | AR68: =AQ68 -> 5.123 | ... BW68: =BV68 -> 5.123 | BX68: x | BY68: =G68 -> 0 | BZ68: =K68 -> 0 | CA68: =O68 -> 0.997 | CB68: =S68 -> 4.251 | CC68: =W68 -> 4.251 | CD68: =AA68 -> 4.2511883 | CE68: =AE68 -> 4.805 | CF68: =AI68 -> 5.1 | CG68: =AM68 -> 5.123 | CH68: =AQ68 -> 5.123 | CI68: =AU68 -> 5.123 | CJ68: =AY68 -> 5.123 | CK68: =BC68 -> 5.123 | CL68: =BG68 -> 5.123 | CM68: =BK68 -> 5.123 | CN68: =BO68 -> 5.123 | CO68: =BS68 -> 5.123 | CP68: =BW68 -> 5.123 | CQ68: x | CX68: =AH68-AG68 -> 0.647 | CY68: =AI68-AH68 -> -0.352
B69: =Inputs!B34 -> Tributos diferidos | D69: 5.9 | E69: 7.906 | F69: 9.433 | G69: 12.622 | H69: 12.783 | I69: =Inputs!K34/1000 -> 14.839 | J69: =Inputs!L34/1000 -> 13.511 | K69: =-Inputs!M34/1000 -> 16.813 | L69: =Inputs!N34/1000 -> 19.263 | M69: =Inputs!O34/1000 -> 20.598 | N69: =Inputs!P34/1000 -> 23.668 | O69: =Inputs!Q34/1000 -> 18.047 | P69: =Inputs!R34/1000 -> 14.699 | Q69: =Inputs!S34/1000 -> 13.739 | R69: =Inputs!T34/1000 -> 18.187 | S69: =Inputs!U34/1000 -> 34.592 | ... AJ69: =Inputs!AL34/1000 -> 81.2 | AK69: =AJ69 -> 81.2 | AL69: =AK69 -> 81.2 | AM69: =AL69 -> 81.2 | AN69: =AM69 -> 81.2 | AO69: =AN69 -> 81.2 | AP69: =AO69 -> 81.2 | AQ69: =AP69 -> 81.2 | AR69: =AQ69 -> 81.2 | ... BW69: =BV69 -> 81.2 | BX69: x | BY69: =G69 -> 12.622 | BZ69: =K69 -> 16.813 | CA69: =O69 -> 18.047 | CB69: =S69 -> 34.592 | CC69: =W69 -> 41.378 | CD69: =AA69 -> 48.007 | CE69: =AE69 -> 64.509 | CF69: =AI69 -> 71.891 | CG69: =AM69 -> 81.2 | CH69: =AQ69 -> 81.2 | CI69: =AU69 -> 81.2 | CJ69: =AY69 -> 81.2 | CK69: =BC69 -> 81.2 | CL69: =BG69 -> 81.2 | CM69: =BK69 -> 81.2 | CN69: =BO69 -> 81.2 | CO69: =BS69 -> 81.2 | CP69: =BW69 -> 81.2 | CQ69: x | CX69: =AH69-AG69 -> 4.493 | CY69: =AI69-AH69 -> -10.291
B70: =Inputs!B37 -> Imobilizado e ativo de direito de uso | D70: 42.391 | E70: 40.626 | F70: 76.175 | G70: 74.176 | H70: 67.664 | I70: =Inputs!K37/1000 -> 68.049 | J70: =Inputs!L37/1000 -> 66.735 | K70: =-Inputs!M37/1000 -> 67.964 | L70: =Inputs!N37/1000 -> 78.724 | M70: =Inputs!O37/1000 -> 80.36 | N70: =Inputs!P37/1000 -> 80.43 | O70: =Inputs!Q37/1000 -> 77.024 | P70: =Inputs!R37/1000 -> 74.242 | Q70: =Inputs!S37/1000 -> 70.589 | R70: =Inputs!T37/1000 -> 71.121 | S70: =Inputs!U37/1000 -> 75.485 | ... AJ70: =Inputs!AL37/1000 -> 295.894 | AK70: =AJ70/(AJ70+AJ71)*AK221 -> 298.96964 | AL70: =AK70/(AK70+AK71)*AL221 -> 308.45424 | AM70: =AL70/(AL70+AL71)*AM221 -> 313.40467 | AN70: =AM70/(AM70+AM71)*AN221 -> 315.92876 | AO70: =AN70/(AN70+AN71)*AO221 -> 318.4005 | AP70: =AO70/(AO70+AO71)*AP221 -> 321.48539 | AQ70: =AP70/(AP70+AP71)*AQ221 -> 326.05732 | AR70: =AQ70/(AQ70+AQ71)*AR221 -> 329.46822 | ... BW70: =BV70/(BV70+BV71)*BW221 -> 521.33807 | BX70: x | BY70: =G70 -> 74.176 | BZ70: =K70 -> 67.964 | CA70: =O70 -> 77.024 | CB70: =S70 -> 75.485 | CC70: =W70 -> 99.594 | CD70: =AA70 -> 174.189 | CE70: =AE70 -> 255.291 | CF70: =AI70 -> 301.842 | CG70: =AM70 -> 313.40467 | CH70: =AQ70 -> 326.05732 | CI70: =AU70 -> 342.05182 | CJ70: =AY70 -> 361.41451 | CK70: =BC70 -> 384.16245 | CL70: =BG70 -> 410.38525 | CM70: =BK70 -> 440.24414 | CN70: =BO70 -> 473.91655 | CO70: =BS70 -> 495.18813 | CP70: =BW70 -> 521.33807 | CQ70: x | CX70: =AH70-AG70 -> 22.694 | CY70: =AI70-AH70 -> 7.089
B71: =Inputs!B38 -> Intangível | H71: 7.589 | I71: =Inputs!K38/1000 -> 7.172 | J71: =Inputs!L38/1000 -> 6.763 | K71: =-Inputs!M38/1000 -> 6.38 | L71: =Inputs!N38/1000 -> 5.943 | M71: =Inputs!O38/1000 -> 5.461 | N71: =Inputs!P38/1000 -> 5.017 | O71: =Inputs!Q38/1000 -> 4.556 | P71: =Inputs!R38/1000 -> 4.123 | Q71: =Inputs!S38/1000 -> 5.134 | R71: =Inputs!T38/1000 -> 4.863 | S71: =Inputs!U38/1000 -> 9.888 | ... AJ71: =Inputs!AL38/1000 -> 225.826 | AK71: =AK221-AK70 -> 228.17332 | AL71: =AL221-AL70 -> 235.41196 | AM71: =AM221-AM70 -> 239.19013 | AN71: =AN221-AN70 -> 241.11651 | AO71: =AO221-AO70 -> 243.00294 | AP71: =AP221-AP70 -> 245.35733 | AQ71: =AQ221-AQ70 -> 248.84662 | AR71: =AR221-AR70 -> 251.44981 | ... BW71: =BW221-BW70 -> 397.88469 | BX71: x | BY71: =G71 | BZ71: =K71 -> 6.38 | CA71: =O71 -> 4.556 | CB71: =S71 -> 9.888 | CC71: =W71 -> 8.055 | CD71: =AA71 -> 31.596 | CE71: =AE71 -> 59.95 | CF71: =AI71 -> 245.411 | CG71: =AM71 -> 239.19013 | CH71: =AQ71 -> 248.84662 | CI71: =AU71 -> 261.0536 | CJ71: =AY71 -> 275.83118 | CK71: =BC71 -> 293.19239 | CL71: =BG71 -> 313.20561 | CM71: =BK71 -> 335.99388 | CN71: =BO71 -> 361.69263 | CO71: =BS71 -> 377.92707 | CP71: =BW71 -> 397.88469 | CQ71: x | CX71: =AH71-AG71 -> 109.413 | CY71: =AI71-AH71 -> 47.777
B72: =Inputs!B30 -> Outros ativos não circulantes | D72: 3.001 | E72: 3.102 | F72: 4.565 | G72: 4.917 | H72: 5.184 | I72: =(Inputs!K39/1000)-SUM(Modelo!I68:I71) -> 11.452 | J72: =(Inputs!L39/1000)-SUM(Modelo!J68:J71) -> 11.942 | K72: =-(Inputs!M39/1000)-SUM(Modelo!K68:K71) -> 11.513 | L72: =(Inputs!N39/1000)-SUM(Modelo!L68:L71) -> 11.448 | M72: =(Inputs!O39/1000)-SUM(Modelo!M68:M71) -> 10.953 | N72: =(Inputs!P39/1000)-SUM(Modelo!N68:N71) -> 10.743 | O72: =(Inputs!Q39/1000)-SUM(Modelo!O68:O71) -> 11.055 | P72: =(Inputs!R39/1000)-SUM(Modelo!P68:P71) -> 7.012 | Q72: =(Inputs!S39/1000)-SUM(Modelo!Q68:Q71) -> 5.107 | R72: =(Inputs!T39/1000)-SUM(Modelo!R68:R71) -> 7.627 | S72: =(Inputs!U39/1000)-SUM(Modelo!S68:S71) -> 7.567 | ... AJ72: =(Inputs!AL39/1000)-SUM(Modelo!AJ68:AJ71) -> 10.107 | AK72: =AJ72 -> 10.107 | AL72: =AK72 -> 10.107 | AM72: =AL72 -> 10.107 | AN72: =AM72 -> 10.107 | AO72: =AN72 -> 10.107 | AP72: =AO72 -> 10.107 | AQ72: =AP72 -> 10.107 | AR72: =AQ72 -> 10.107 | ... BW72: =BV72 -> 10.107 | BX72: x | BY72: =G72 -> 4.917 | BZ72: =K72 -> 11.513 | CA72: =O72 -> 11.055 | CB72: =S72 -> 7.567 | CC72: =W72 -> 8.995 | CD72: =AA72 -> 8.008 | CE72: =AE72 -> 7.222 | CF72: =AI72 -> 9.592 | CG72: =AM72 -> 10.107 | CH72: =AQ72 -> 10.107 | CI72: =AU72 -> 10.107 | CJ72: =AY72 -> 10.107 | CK72: =BC72 -> 10.107 | CL72: =BG72 -> 10.107 | CM72: =BK72 -> 10.107 | CN72: =BO72 -> 10.107 | CO72: =BS72 -> 10.107 | CP72: =BW72 -> 10.107 | CQ72: x | CX72: =AH72-AG72 -> 0.658 | CY72: =AI72-AH72 -> 0.21
BX73: x | CQ73: x
B74: Passivos Totais | C74: [BRL 000] | D74: =+D76+D86 -> 58.863 | E74: =+E76+E86 -> 83.691 | F74: =+F76+F86 -> 110.245 | G74: =+G76+G86 -> 127.632 | H74: =+H76+H86 -> 137.523 | I74: =+I76+I86 -> 138.157 | J74: =+J76+J86 -> 138.031 | K74: =+K76+K86 -> 141.857 | ... BW74: =+BW76+BW86 -> 1295.341 | BX74: x | BY74: =G74 -> 127.632 | BZ74: =K74 -> 141.857 | CA74: =O74 -> 164.932 | CB74: =S74 -> 111.044 | CC74: =W74 -> 145.297 | CD74: =AA74 -> 398.177 | CE74: =AE74 -> 598.3 | CF74: =AI74 -> 874.512 | CG74: =AM74 -> 1070.1344 | CH74: =AQ74 -> 1089.5179 | CI74: =AU74 -> 1107.7213 | CJ74: =AY74 -> 1127.9497 | CK74: =BC74 -> 1150.0519 | CL74: =BG74 -> 1174.2016 | CM74: =BK74 -> 1200.5883 | CN74: =BO74 -> 1229.4193 | CO74: =BS74 -> 1260.9211 | CP74: =BW74 -> 1295.341 | CQ74: x | CX74: =AH74-AG74 -> 250.105 | CY74: =AI74-AH74 -> 29.204
BX75: x | CQ75: x
B76: Passivos Circulantes | C76: [BRL 000] | D76: =+D77+D78+D79+D80+D81+D82+D84 -> 56.569 | E76: =+E77+E78+E79+E80+E81+E82+E84 -> 70.156 | F76: =+F77+F78+F79+F80+F81+F82+F84 -> 75.589 | G76: =+G77+G78+G79+G80+G81+G82+G84 -> 89.663 | H76: =+H77+H78+H79+H80+H81+H82+H83+H84 -> 106.524 | I76: =+I77+I78+I79+I80+I81+I82+I83+I84 -> 101.471 | J76: =+J77+J78+J79+J80+J81+J82+J83+J84 -> 108.174 | K76: =+K77+K78+K79+K80+K81+K82+K83+K84 -> 114.81 | L76: =+L77+L78+L79+L80+L81+L82+L83+L84 -> 131.132 | M76: =+M77+M78+M79+M80+M81+M82+M83+M84 -> 92.451 | N76: =+N77+N78+N79+N80+N81+N82+N83+N84 -> 101.252 | O76: =+O77+O78+O79+O80+O81+O82+O83+O84 -> 95.18 | ... BW76: =+BW77+BW78+BW79+BW80+BW81+BW82+BW83+BW84 -> 648.25702 | BX76: x | BY76: =G76 -> 89.663 | BZ76: =K76 -> 114.81 | CA76: =O76 -> 95.18 | CB76: =S76 -> 66.608 | CC76: =W76 -> 106.361 | CD76: =AA76 -> 259.122 | CE76: =AE76 -> 277.072 | CF76: =AI76 -> 546.806 | CG76: =AM76 -> 423.05043 | CH76: =AQ76 -> 442.43393 | CI76: =AU76 -> 460.63733 | CJ76: =AY76 -> 480.86571 | CK76: =BC76 -> 502.96793 | CL76: =BG76 -> 527.11757 | CM76: =BK76 -> 553.50429 | CN76: =BO76 -> 582.33533 | CO76: =BS76 -> 613.8371 | CP76: =BW76 -> 648.25702 | CQ76: x | CX76: =AH76-AG76 -> 131.191 | CY76: =AI76-AH76 -> 150.889
B77: =Inputs!B46 -> Fornecedores | D77: 2.432 | E77: 2.062 | F77: 6.477 | G77: 9.632 | H77: =(Inputs!J46+Inputs!J47)/1000 -> 11.537 | I77: =(Inputs!K46+Inputs!K47)/1000 -> 9.585 | J77: =(Inputs!L46+Inputs!L47)/1000 -> 9.888 | K77: =((Inputs!M46+Inputs!M47)/1000)*-1 -> 13.246 | L77: =(Inputs!N46+Inputs!N47)/1000 -> 14.953 | M77: =(Inputs!O46+Inputs!O47)/1000 -> 12.713 | N77: =(Inputs!P46+Inputs!P47)/1000 -> 12.764 | O77: =(Inputs!Q46+Inputs!Q47)/1000 -> 9.761 | P77: =(Inputs!R46+Inputs!R47)/1000 -> 8.681 | Q77: =(Inputs!S46+Inputs!S47)/1000 -> 6.606 | R77: =(Inputs!T46+Inputs!T47)/1000 -> 7.124 | S77: =(Inputs!U46+Inputs!U47)/1000 -> 11.478 | ... AJ77: =(Inputs!AL46+Inputs!AL47)/1000 -> 38.515 | AK77: =AK185 -> 41.768261 | AL77: =AL185 -> 61.565623 | AM77: =AM185 -> 52.108366 | AN77: =AN185 -> 39.450028 | AO77: =AO185 -> 45.213333 | AP77: =AP185 -> 68.679072 | AQ77: =AQ185 -> 57.672903 | AR77: =AR185 -> 43.509838 | ... BW77: =BW185 -> 116.95833 | BX77: x | BY77: =G77 -> 9.632 | BZ77: =K77 -> 13.246 | CA77: =O77 -> 9.761 | CB77: =S77 -> 11.478 | CC77: =W77 -> 17.25 | CD77: =AA77 -> 33.383 | CE77: =AE77 -> 38.577 | CF77: =AI77 -> 44.567 | CG77: =AM77 -> 52.108366 | CH77: =AQ77 -> 57.672903 | CI77: =AU77 -> 62.908249 | CJ77: =AY77 -> 68.735705 | CK77: =BC77 -> 75.102983 | CL77: =BG77 -> 82.060089 | CM77: =BK77 -> 89.66166 | CN77: =BO77 -> 97.967397 | CO77: =BS77 -> 107.04253 | CP77: =BW77 -> 116.95833 | CQ77: x | CX77: =AH77-AG77 -> 38.835 | CY77: =AI77-AH77 -> -15.472
B78: =Inputs!B49 -> Empréstimos e financiamentos | D78: 12.01 | E78: 22.747 | F78: 28.186 | G78: 43.774 | H78: =(Inputs!J49+Inputs!J50)/1000 -> 53.759 | I78: =(Inputs!K49+Inputs!K50)/1000 -> 43.836 | J78: =(Inputs!L49+Inputs!L50)/1000 -> 46.112 | K78: =((Inputs!M49+Inputs!M50)/1000)*-1 -> 53.735 | L78: =(Inputs!N49+Inputs!N50)/1000 -> 56.805 | M78: =(Inputs!O49+Inputs!O50)/1000 -> 12.561 | N78: =(Inputs!P49+Inputs!P50)/1000 -> 12.315 | O78: =(Inputs!Q49+Inputs!Q50)/1000 -> 20.367 | P78: =(Inputs!R49+Inputs!R50)/1000 -> 22.305 | Q78: =(Inputs!S49+Inputs!S50)/1000 -> 27.898 | R78: =(Inputs!T49+Inputs!T50)/1000 -> 26.594 | S78: =(Inputs!U49+Inputs!U50)/1000 -> 25.339 | ... AJ78: =(Inputs!AL49+Inputs!AL50)/1000 -> 127.847 | AK78: =AJ78/SUM(AJ78,AJ87)*AK106 -> 127.847 | AL78: =AK78/SUM(AK78,AK87)*AL106 -> 127.847 | AM78: =AL78/SUM(AL78,AL87)*AM106 -> 127.847 | AN78: =AM78/SUM(AM78,AM87)*AN106 -> 127.847 | AO78: =AN78/SUM(AN78,AN87)*AO106 -> 127.847 | AP78: =AO78/SUM(AO78,AO87)*AP106 -> 127.847 | AQ78: =AP78/SUM(AP78,AP87)*AQ106 -> 127.847 | AR78: =AQ78/SUM(AQ78,AQ87)*AR106 -> 127.847 | ... BW78: =BV78/SUM(BV78,BV87)*BW106 -> 127.847 | BX78: x | BY78: =G78 -> 43.774 | BZ78: =K78 -> 53.735 | CA78: =O78 -> 20.367 | CB78: =S78 -> 25.339 | CC78: =W78 -> 32.864 | CD78: =AA78 -> 35.653 | CE78: =AE78 -> 77.019 | CF78: =AI78 -> 267.358 | CG78: =AM78 -> 127.847 | CH78: =AQ78 -> 127.847 | CI78: =AU78 -> 127.847 | CJ78: =AY78 -> 127.847 | CK78: =BC78 -> 127.847 | CL78: =BG78 -> 127.847 | CM78: =BK78 -> 127.847 | CN78: =BO78 -> 127.847 | CO78: =BS78 -> 127.847 | CP78: =BW78 -> 127.847 | CQ78: x | CX78: =AH78-AG78 -> 2.503 | CY78: =AI78-AH78 -> 169.384
B79: =Inputs!B53 -> Salários e Encargos Sociais | D79: 14.027 | E79: 17.213 | F79: 27.149 | G79: 21.51 | H79: =Inputs!J53/1000 -> 26.582 | I79: =Inputs!K53/1000 -> 36.642 | J79: =Inputs!L53/1000 -> 34.914 | K79: =(Inputs!M53/1000)*-1 -> 28.385 | L79: =Inputs!N53/1000 -> 31.788 | M79: =Inputs!O53/1000 -> 35.377 | N79: =Inputs!P53/1000 -> 34.811 | O79: =Inputs!Q53/1000 -> 24.967 | P79: =Inputs!R53/1000 -> 21.521 | Q79: =Inputs!S53/1000 -> 21.683 | R79: =Inputs!T53/1000 -> 21.661 | S79: =Inputs!U53/1000 -> 17.778 | ... AJ79: =Inputs!AL53/1000 -> 110.759 | AK79: =AK189 -> 139.96848 | AL79: =AL189 -> 119.26959 | AM79: =AM189 -> 112.63405 | AN79: =AN189 -> 113.44789 | AO79: =AO189 -> 151.51316 | AP79: =AP189 -> 133.0503 | AQ79: =AQ189 -> 124.66199 | AR79: =AR189 -> 125.12284 | ... BW79: =BW189 -> 252.80951 | BX79: x | BY79: =G79 -> 21.51 | BZ79: =K79 -> 28.385 | CA79: =O79 -> 24.967 | CB79: =S79 -> 17.778 | CC79: =W79 -> 32.982 | CD79: =AA79 -> 69.116 | CE79: =AE79 -> 78.67 | CF79: =AI79 -> 100.936 | CG79: =AM79 -> 112.63405 | CH79: =AQ79 -> 124.66199 | CI79: =AU79 -> 135.97837 | CJ79: =AY79 -> 148.57462 | CK79: =BC79 -> 162.33772 | CL79: =BG79 -> 177.37574 | CM79: =BK79 -> 193.8068 | CN79: =BO79 -> 211.75994 | CO79: =BS79 -> 231.37616 | CP79: =BW79 -> 252.80951 | CQ79: x | CX79: =AH79-AG79 -> 41.422 | CY79: =AI79-AH79 -> -18.288
B80: =Inputs!B55 -> Tributos a Pagar | H80: =(Inputs!J54+Inputs!J55)/1000 -> 4.518 | I80: =(Inputs!K54+Inputs!K55)/1000 -> 3.969 | J80: =(Inputs!L54+Inputs!L55)/1000 -> 3.5 | K80: =((Inputs!M54+Inputs!M55)/1000)*-1 -> 4.281 | L80: =(Inputs!N54+Inputs!N55)/1000 -> 4.743 | M80: =(Inputs!O54+Inputs!O55)/1000 -> 4.553 | N80: =(Inputs!P54+Inputs!P55)/1000 -> 4.466 | O80: =(Inputs!Q54+Inputs!Q55)/1000 -> 4.615 | P80: =(Inputs!R54+Inputs!R55)/1000 -> 4.585 | Q80: =(Inputs!S54+Inputs!S55)/1000 -> 6.672 | R80: =(Inputs!T54+Inputs!T55)/1000 -> 4.106 | S80: =(Inputs!U54+Inputs!U55)/1000 -> 4.321 | ... AJ80: =(Inputs!AL54+Inputs!AL55)/1000 -> 14.651 | AK80: =AK193 -> 23.058603 | AL80: =AL193 -> 25.193657 | AM80: =AM193 -> 16.039019 | AN80: =AN193 -> 15.29069 | AO80: =AO193 -> 25.05575 | AP80: =AP193 -> 28.210309 | AQ80: =AQ193 -> 17.830038 | AR80: =AR193 -> 16.914411 | ... BW80: =BW193 -> 36.220182 | BX80: x | BY80: =G80 | BZ80: =K80 -> 4.281 | CA80: =O80 -> 4.615 | CB80: =S80 -> 4.321 | CC80: =W80 -> 4.58 | CD80: =AA80 -> 16.216 | CE80: =AE80 -> 17.007 | CF80: =AI80 -> 16.443 | CG80: =AM80 -> 16.039019 | CH80: =AQ80 -> 17.830038 | CI80: =AU80 -> 19.48171 | CJ80: =AY80 -> 21.286383 | CK80: =BC80 -> 23.25823 | CL80: =BG80 -> 25.412738 | CM80: =BK80 -> 27.766827 | CN80: =BO80 -> 30.338985 | CO80: =BS80 -> 33.149413 | CP80: =BW80 -> 36.220182 | CQ80: x | CX80: =AH80-AG80 -> 14.193 | CY80: =AI80-AH80 -> -11.1
B81: =Inputs!B57 -> Contas a pagar por aquisição societária | H81: =Inputs!J57/1000 -> 5.86 | I81: =Inputs!K57/1000 -> 0.983 | J81: =Inputs!L57/1000 -> 6.526 | K81: =(Inputs!M57/1000)*-1 -> 6.525 | L81: =Inputs!N57/1000 -> 6.543 | M81: =Inputs!O57/1000 -> 6.585 | N81: =Inputs!P57/1000 -> 8.139 | O81: =Inputs!Q57/1000 -> 7.864 | P81: =Inputs!R57/1000 -> 4.087 | Q81: =Inputs!S57/1000 -> 0 | R81: =Inputs!T57/1000 -> 3.312 | S81: =Inputs!U57/1000 -> 1.097 | ... AJ81: =Inputs!AL57/1000 -> 62.99 | AK81: =AJ81 -> 62.99 | AL81: =AK81 -> 62.99 | AM81: =AL81 -> 62.99 | AN81: =AM81 -> 62.99 | AO81: =AN81 -> 62.99 | AP81: =AO81 -> 62.99 | AQ81: =AP81 -> 62.99 | AR81: =AQ81 -> 62.99 | ... BW81: =BV81 -> 62.99 | BX81: x | BY81: =G81 | BZ81: =K81 -> 6.525 | CA81: =O81 -> 7.864 | CB81: =S81 -> 1.097 | CC81: =W81 -> 1.017 | CD81: =AA81 -> 14.473 | CE81: =AE81 -> 16.298 | CF81: =AI81 -> 67.038 | CG81: =AM81 -> 62.99 | CH81: =AQ81 -> 62.99 | CI81: =AU81 -> 62.99 | CJ81: =AY81 -> 62.99 | CK81: =BC81 -> 62.99 | CL81: =BG81 -> 62.99 | CM81: =BK81 -> 62.99 | CN81: =BO81 -> 62.99 | CO81: =BS81 -> 62.99 | CP81: =BW81 -> 62.99 | CQ81: x | CX81: =AH81-AG81 -> 35.39 | CY81: =AI81-AH81 -> 6.938
B82: =Inputs!B61 -> Provisões | H82: =Inputs!J61/1000 -> 1.683 | I82: =Inputs!K61/1000 -> 2.666 | J82: =Inputs!L61/1000 -> 2.187 | K82: =(Inputs!M61/1000)*-1 -> 3.173 | L82: =Inputs!N61/1000 -> 5.147 | M82: =Inputs!O61/1000 -> 3.147 | N82: =Inputs!P61/1000 -> 5.506 | O82: =Inputs!Q61/1000 -> 7.229 | P82: =Inputs!R61/1000 -> 6.923 | Q82: =Inputs!S61/1000 -> 4.452 | R82: =Inputs!T61/1000 -> 3.469 | S82: =Inputs!U61/1000 -> 4.255 | ... AJ82: =Inputs!AL61/1000 -> 29.821 | AK82: =AJ82 -> 29.821 | AL82: =AK82 -> 29.821 | AM82: =AL82 -> 29.821 | AN82: =AM82 -> 29.821 | AO82: =AN82 -> 29.821 | AP82: =AO82 -> 29.821 | AQ82: =AP82 -> 29.821 | AR82: =AQ82 -> 29.821 | ... BW82: =BV82 -> 29.821 | BX82: x | BY82: =G82 | BZ82: =K82 -> 3.173 | CA82: =O82 -> 7.229 | CB82: =S82 -> 4.255 | CC82: =W82 -> 9.773 | CD82: =AA82 -> 15.624 | CE82: =AE82 -> 29.299 | CF82: =AI82 -> 29.883 | CG82: =AM82 -> 29.821 | CH82: =AQ82 -> 29.821 | CI82: =AU82 -> 29.821 | CJ82: =AY82 -> 29.821 | CK82: =BC82 -> 29.821 | CL82: =BG82 -> 29.821 | CM82: =BK82 -> 29.821 | CN82: =BO82 -> 29.821 | CO82: =BS82 -> 29.821 | CP82: =BW82 -> 29.821 | CQ82: x | CX82: =AH82-AG82 -> 2.907 | CY82: =AI82-AH82 -> 6.15
B83: =Inputs!B52 -> Arrendamento financeiro a pagar - Direitos de uso CPC 06 | D83: 0 | H83: =Inputs!J52/1000 -> 0 | I83: =Inputs!K52/1000 -> 0 | J83: =Inputs!L52/1000 -> 0 | K83: =(Inputs!M52/1000)*-1 -> 0 | L83: =Inputs!N52/1000 -> 1.517 | M83: =Inputs!O52/1000 -> 1.847 | N83: =Inputs!P52/1000 -> 1.5 | O83: =Inputs!Q52/1000 -> 1.601 | P83: =Inputs!R52/1000 -> 1.639 | Q83: =Inputs!S52/1000 -> 1.731 | R83: =Inputs!T52/1000 -> 1.811 | S83: =Inputs!U52/1000 -> 2.085 | ... AJ83: =Inputs!AL52/1000 -> 5.889 | AK83: =AJ83 -> 5.889 | AL83: =AK83 -> 5.889 | AM83: =AL83 -> 5.889 | AN83: =AM83 -> 5.889 | AO83: =AN83 -> 5.889 | AP83: =AO83 -> 5.889 | AQ83: =AP83 -> 5.889 | AR83: =AQ83 -> 5.889 | ... BW83: =BV83 -> 5.889 | BX83: x | BY83: =G83 | BZ83: =K83 -> 0 | CA83: =O83 -> 1.601 | CB83: =S83 -> 2.085 | CC83: =W83 -> 2.343 | CD83: =AA83 -> 4.555 | CE83: =AE83 -> 5.127 | CF83: =AI83 -> 5.817 | CG83: =AM83 -> 5.889 | CH83: =AQ83 -> 5.889 | CI83: =AU83 -> 5.889 | CJ83: =AY83 -> 5.889 | CK83: =BC83 -> 5.889 | CL83: =BG83 -> 5.889 | CM83: =BK83 -> 5.889 | CN83: =BO83 -> 5.889 | CO83: =BS83 -> 5.889 | CP83: =BW83 -> 5.889 | CQ83: x | CX83: =AH83-AG83 -> 1.389 | CY83: =AI83-AH83 -> 0.385
B84: =Inputs!B63 -> Outros Passivos | D84: 28.1 | E84: 28.134 | F84: 13.777 | G84: 14.747 | H84: =Inputs!J64/1000-SUM(Modelo!H77:H83) -> 2.585 | I84: =Inputs!K64/1000-SUM(Modelo!I77:I83) -> 3.79 | J84: =Inputs!L64/1000-SUM(Modelo!J77:J83) -> 5.047 | K84: =-Inputs!M64/1000-SUM(Modelo!K77:K83) -> 5.465 | L84: =Inputs!N64/1000-SUM(Modelo!L77:L83) -> 9.636 | M84: =Inputs!O64/1000-SUM(Modelo!M77:M83) -> 15.668 | N84: =Inputs!P64/1000-SUM(Modelo!N77:N83) -> 21.751 | O84: =Inputs!Q64/1000-SUM(Modelo!O77:O83) -> 18.776 | P84: =Inputs!R64/1000-SUM(Modelo!P77:P83) -> 0.303 | Q84: =Inputs!S64/1000-SUM(Modelo!Q77:Q83) -> 0.338 | R84: =Inputs!T64/1000-SUM(Modelo!R77:R83) -> 0.224 | S84: =Inputs!U64/1000-SUM(Modelo!S77:S83) -> 0.255 | ... AJ84: =Inputs!AL64/1000-SUM(Modelo!AJ77:AJ83) -> 15.722 | AK84: =AJ84 -> 15.722 | AL84: =AK84 -> 15.722 | AM84: =AL84 -> 15.722 | AN84: =AM84 -> 15.722 | AO84: =AN84 -> 15.722 | AP84: =AO84 -> 15.722 | AQ84: =AP84 -> 15.722 | AR84: =AQ84 -> 15.722 | ... BW84: =BV84 -> 15.722 | BX84: x | BY84: =G84 -> 14.747 | BZ84: =K84 -> 5.465 | CA84: =O84 -> 18.776 | CB84: =S84 -> 0.255 | CC84: =W84 -> 5.552 | CD84: =AA84 -> 70.102 | CE84: =AE84 -> 15.075 | CF84: =AI84 -> 14.764 | CG84: =AM84 -> 15.722 | CH84: =AQ84 -> 15.722 | CI84: =AU84 -> 15.722 | CJ84: =AY84 -> 15.722 | CK84: =BC84 -> 15.722 | CL84: =BG84 -> 15.722 | CM84: =BK84 -> 15.722 | CN84: =BO84 -> 15.722 | CO84: =BS84 -> 15.722 | CP84: =BW84 -> 15.722 | CQ84: x | CX84: =AH84-AG84 -> -5.448 | CY84: =AI84-AH84 -> 12.892
BX85: x | CQ85: x
B86: Passivos Não-Circulantes | C86: [BRL 000] | D86: =+D87+D88+D89+D90+D91 -> 2.294 | E86: =+E87+E88+E89+E90+E91 -> 13.535 | F86: =+F87+F88+F89+F90+F91 -> 34.656 | G86: =+G87+G88+G89+G90+G91 -> 37.969 | H86: =+H87+H88+H89+H90+H91 -> 30.999 | I86: =+I87+I88+I89+I90+I91 -> 36.686 | J86: =+J87+J88+J89+J90+J91 -> 29.857 | K86: =+K87+K88+K89+K90+K91 -> 27.047 | ... BW86: =+BW87+BW88+BW89+BW90+BW91 -> 647.084 | BX86: x | BY86: =G86 -> 37.969 | BZ86: =K86 -> 27.047 | CA86: =O86 -> 69.752 | CB86: =S86 -> 44.436 | CC86: =W86 -> 38.936 | CD86: =AA86 -> 139.055 | CE86: =AE86 -> 321.228 | CF86: =AI86 -> 327.706 | CG86: =AM86 -> 647.084 | CH86: =AQ86 -> 647.084 | CI86: =AU86 -> 647.084 | CJ86: =AY86 -> 647.084 | CK86: =BC86 -> 647.084 | CL86: =BG86 -> 647.084 | CM86: =BK86 -> 647.084 | CN86: =BO86 -> 647.084 | CO86: =BS86 -> 647.084 | CP86: =BW86 -> 647.084 | CQ86: x | CX86: =AH86-AG86 -> 118.914 | CY86: =AI86-AH86 -> -121.685
B87: =Inputs!B67 -> Empréstimos e financiamentos | D87: 0.882 | E87: 12.069 | F87: 20.403 | G87: 21.702 | H87: =(Inputs!J67+Inputs!J68)/1000 -> 13.952 | I87: =(Inputs!K67+Inputs!K68)/1000 -> 16.906 | J87: =(Inputs!L67+Inputs!L68)/1000 -> 16.338 | K87: =((Inputs!M67+Inputs!M68)/1000)*-1 -> 13.902 | L87: =(Inputs!N67+Inputs!N68)/1000 -> 10.296 | M87: =(Inputs!O67+Inputs!O68)/1000 -> 70.582 | N87: =(Inputs!P67+Inputs!P68)/1000 -> 66.073 | O87: =(Inputs!Q67+Inputs!Q68)/1000 -> 57.444 | P87: =(Inputs!R67+Inputs!R68)/1000 -> 49.451 | Q87: =(Inputs!S67+Inputs!S68)/1000 -> 43.194 | R87: =(Inputs!T67+Inputs!T68)/1000 -> 37.076 | S87: =(Inputs!U67+Inputs!U68)/1000 -> 30.771 | ... AJ87: =(Inputs!AL67+Inputs!AL68)/1000 -> 519.515 | AK87: =AJ87/SUM(AJ87,AJ78)*AK106 -> 519.515 | AL87: =AK87/SUM(AK87,AK78)*AL106 -> 519.515 | AM87: =AL87/SUM(AL87,AL78)*AM106 -> 519.515 | AN87: =AM87/SUM(AM87,AM78)*AN106 -> 519.515 | AO87: =AN87/SUM(AN87,AN78)*AO106 -> 519.515 | AP87: =AO87/SUM(AO87,AO78)*AP106 -> 519.515 | AQ87: =AP87/SUM(AP87,AP78)*AQ106 -> 519.515 | AR87: =AQ87/SUM(AQ87,AQ78)*AR106 -> 519.515 | ... BW87: =BV87/SUM(BV87,BV78)*BW106 -> 519.515 | BX87: x | BY87: =G87 -> 21.702 | BZ87: =K87 -> 13.902 | CA87: =O87 -> 57.444 | CB87: =S87 -> 30.771 | CC87: =W87 -> 27.476 | CD87: =AA87 -> 100.695 | CE87: =AE87 -> 271.542 | CF87: =AI87 -> 196.225 | CG87: =AM87 -> 519.515 | CH87: =AQ87 -> 519.515 | CI87: =AU87 -> 519.515 | CJ87: =AY87 -> 519.515 | CK87: =BC87 -> 519.515 | CL87: =BG87 -> 519.515 | CM87: =BK87 -> 519.515 | CN87: =BO87 -> 519.515 | CO87: =BS87 -> 519.515 | CP87: =BW87 -> 519.515 | CQ87: x | CX87: =AH87-AG87 -> 46.184 | CY87: =AI87-AH87 -> -134.051
B88: =Inputs!B69 -> Arrendamento financeiro a pagar - Direitos de uso CPC 06 | D88: 0 | E88: 0 | F88: 0 | G88: 0 | H88: =Inputs!J69/1000 -> 0 | I88: =Inputs!K69/1000 -> 0 | J88: =Inputs!L69/1000 -> 0 | K88: =(Inputs!M69/1000)*-1 -> 0 | L88: =Inputs!N69/1000 -> 7.097 | M88: =Inputs!O69/1000 -> 7.25 | N88: =Inputs!P69/1000 -> 6.828 | O88: =Inputs!Q69/1000 -> 6.618 | P88: =Inputs!R69/1000 -> 6.24 | Q88: =Inputs!S69/1000 -> 5.853 | R88: =Inputs!T69/1000 -> 5.714 | S88: =Inputs!U69/1000 -> 5.944 | ... AJ88: =Inputs!AL69/1000 -> 18.898 | AK88: =AJ88 -> 18.898 | AL88: =AK88 -> 18.898 | AM88: =AL88 -> 18.898 | AN88: =AM88 -> 18.898 | AO88: =AN88 -> 18.898 | AP88: =AO88 -> 18.898 | AQ88: =AP88 -> 18.898 | AR88: =AQ88 -> 18.898 | ... BW88: =BV88 -> 18.898 | BX88: x | BY88: =G88 -> 0 | BZ88: =K88 -> 0 | CA88: =O88 -> 6.618 | CB88: =S88 -> 5.944 | CC88: =W88 -> 4.371 | CD88: =AA88 -> 16.31 | CE88: =AE88 -> 20.281 | CF88: =AI88 -> 19.108 | CG88: =AM88 -> 18.898 | CH88: =AQ88 -> 18.898 | CI88: =AU88 -> 18.898 | CJ88: =AY88 -> 18.898 | CK88: =BC88 -> 18.898 | CL88: =BG88 -> 18.898 | CM88: =BK88 -> 18.898 | CN88: =BO88 -> 18.898 | CO88: =BS88 -> 18.898 | CP88: =BW88 -> 18.898 | CQ88: x | CX88: =AH88-AG88 -> 2.234 | CY88: =AI88-AH88 -> -0.845
B89: =Inputs!B72 -> Contas a pagar por aquisição societária | D89: 0 | E89: 0 | F89: 0 | G89: 0 | H89: =Inputs!J72/1000 -> 4.503 | I89: =Inputs!K72/1000 -> 8.316 | J89: =Inputs!L72/1000 -> 2.373 | K89: =(Inputs!M72/1000)*-1 -> 2.193 | L89: =Inputs!N72/1000 -> 2.02 | M89: =Inputs!O72/1000 -> 1.836 | N89: =Inputs!P72/1000 -> 0 | O89: =Inputs!Q72/1000 -> 0 | P89: =Inputs!R72/1000 -> 0 | Q89: =Inputs!S72/1000 -> 3.894 | R89: =Inputs!T72/1000 -> 2.611 | S89: =Inputs!U72/1000 -> 3.476 | ... AJ89: =Inputs!AL72/1000 -> 95.117 | AK89: =AJ89 -> 95.117 | AL89: =AK89 -> 95.117 | AM89: =AL89 -> 95.117 | AN89: =AM89 -> 95.117 | AO89: =AN89 -> 95.117 | AP89: =AO89 -> 95.117 | AQ89: =AP89 -> 95.117 | AR89: =AQ89 -> 95.117 | ... BW89: =BV89 -> 95.117 | BX89: x | BY89: =G89 -> 0 | BZ89: =K89 -> 2.193 | CA89: =O89 -> 0 | CB89: =S89 -> 3.476 | CC89: =W89 -> 2.732 | CD89: =AA89 -> 15.044 | CE89: =AE89 -> 20.076 | CF89: =AI89 -> 98.717 | CG89: =AM89 -> 95.117 | CH89: =AQ89 -> 95.117 | CI89: =AU89 -> 95.117 | CJ89: =AY89 -> 95.117 | CK89: =BC89 -> 95.117 | CL89: =BG89 -> 95.117 | CM89: =BK89 -> 95.117 | CN89: =BO89 -> 95.117 | CO89: =BS89 -> 95.117 | CP89: =BW89 -> 95.117 | CQ89: x | CX89: =AH89-AG89 -> 69.042 | CY89: =AI89-AH89 -> 10.663
B90: =Inputs!B75 -> Provisão para riscos tributários, cíveis e trabalhistas | D90: 1.232 | E90: 1.289 | F90: 5.181 | G90: 5.489 | H90: =Inputs!J75/1000 -> 5.516 | I90: =Inputs!K75/1000 -> 5.268 | J90: =Inputs!L75/1000 -> 5.075 | K90: =(Inputs!M75/1000)*-1 -> 4.794 | L90: =Inputs!N75/1000 -> 5.051 | M90: =Inputs!O75/1000 -> 5.499 | N90: =Inputs!P75/1000 -> 5.327 | O90: =Inputs!Q75/1000 -> 5.258 | P90: =Inputs!R75/1000 -> 5.096 | Q90: =Inputs!S75/1000 -> 4.837 | R90: =Inputs!T75/1000 -> 4.822 | S90: =Inputs!U75/1000 -> 4.093 | ... AJ90: =Inputs!AL75/1000 -> 7.372 | AK90: =AJ90 -> 7.372 | AL90: =AK90 -> 7.372 | AM90: =AL90 -> 7.372 | AN90: =AM90 -> 7.372 | AO90: =AN90 -> 7.372 | AP90: =AO90 -> 7.372 | AQ90: =AP90 -> 7.372 | AR90: =AQ90 -> 7.372 | ... BW90: =BV90 -> 7.372 | BX90: x | BY90: =G90 -> 5.489 | BZ90: =K90 -> 4.794 | CA90: =O90 -> 5.258 | CB90: =S90 -> 4.093 | CC90: =W90 -> 4.273 | CD90: =AA90 -> 5.706 | CE90: =AE90 -> 8.953 | CF90: =AI90 -> 7.492 | CG90: =AM90 -> 7.372 | CH90: =AQ90 -> 7.372 | CI90: =AU90 -> 7.372 | CJ90: =AY90 -> 7.372 | CK90: =BC90 -> 7.372 | CL90: =BG90 -> 7.372 | CM90: =BK90 -> 7.372 | CN90: =BO90 -> 7.372 | CO90: =BS90 -> 7.372 | CP90: =BW90 -> 7.372 | CQ90: x | CX90: =AH90-AG90 -> -0.73 | CY90: =AI90-AH90 -> -0.128
B91: =Inputs!B77 -> Outros passivos não circulantes | D91: 0.18 | E91: 0.177 | F91: 9.072 | G91: 10.778 | H91: =(Inputs!J78/1000)-SUM(Modelo!H87:H90) -> 7.028 | I91: =(Inputs!K78/1000)-SUM(Modelo!I87:I90) -> 6.196 | J91: =(Inputs!L78/1000)-SUM(Modelo!J87:J90) -> 6.071 | K91: =-(Inputs!M78/1000)-SUM(Modelo!K87:K90) -> 6.158 | L91: =(Inputs!N78/1000)-SUM(Modelo!L87:L90) -> 3.644 | M91: =(Inputs!O78/1000)-SUM(Modelo!M87:M90) -> 1.782 | N91: =(Inputs!P78/1000)-SUM(Modelo!N87:N90) -> 0.45 | O91: =(Inputs!Q78/1000)-SUM(Modelo!O87:O90) -> 0.432 | P91: =(Inputs!R78/1000)-SUM(Modelo!P87:P90) -> 0.419 | Q91: =(Inputs!S78/1000)-SUM(Modelo!Q87:Q90) -> 0.33 | R91: =(Inputs!T78/1000)-SUM(Modelo!R87:R90) -> 0.313 | S91: =(Inputs!U78/1000)-SUM(Modelo!S87:S90) -> 0.152 | ... AJ91: =(Inputs!AL78/1000)-SUM(Modelo!AJ87:AJ90) -> 6.182 | AK91: =AJ91 -> 6.182 | AL91: =AK91 -> 6.182 | AM91: =AL91 -> 6.182 | AN91: =AM91 -> 6.182 | AO91: =AN91 -> 6.182 | AP91: =AO91 -> 6.182 | AQ91: =AP91 -> 6.182 | AR91: =AQ91 -> 6.182 | ... BW91: =BV91 -> 6.182 | BX91: x | BY91: =G91 -> 10.778 | BZ91: =K91 -> 6.158 | CA91: =O91 -> 0.432 | CB91: =S91 -> 0.152 | CC91: =W91 -> 0.084 | CD91: =AA91 -> 1.3 | CE91: =AE91 -> 0.376 | CF91: =AI91 -> 6.164 | CG91: =AM91 -> 6.182 | CH91: =AQ91 -> 6.182 | CI91: =AU91 -> 6.182 | CJ91: =AY91 -> 6.182 | CK91: =BC91 -> 6.182 | CL91: =BG91 -> 6.182 | CM91: =BK91 -> 6.182 | CN91: =BO91 -> 6.182 | CO91: =BS91 -> 6.182 | CP91: =BW91 -> 6.182 | CQ91: x | CX91: =AH91-AG91 -> 2.184 | CY91: =AI91-AH91 -> 2.676
BX92: x | CQ92: x | CY92: =AI92-AH92 -> 0
B93: Patrimônio Líquido | C93: [BRL 000] | D93: =+D94+D95+D96+D97+D98+D99+D100+D101+D102 -> 58.177 | E93: =+E94+E95+E96+E97+E98+E99+E100+E101+E102 -> 57.004 | F93: =+F94+F95+F96+F97+F98+F99+F100+F101+F102 -> 62.809 | G93: =+G94+G95+G96+G97+G98+G99+G100+G101+G102 -> 54.774 | H93: =+H94+H95+H96+H97+H98+H99+H100+H101+H102 -> 55.229 | I93: =+I94+I95+I96+I97+I98+I99+I100+I101+I102 -> 61.867 | J93: =+J94+J95+J96+J97+J98+J99+J100+J101+J102 -> 60.675 | K93: =+K94+K95+K96+K97+K98+K99+K100+K101+K102 -> 66.129 | ... BW93: =+BW94+BW95+BW96+BW97+BW98+BW99+BW100+BW101+BW102 -> 1620.7481 | BX93: x | BY93: =G93 -> 54.774 | BZ93: =K93 -> 66.129 | CA93: =O93 -> 74.609 | CB93: =S93 -> 225.586 | CC93: =W93 -> 229.07981 | CD93: =AA93 -> 221.762 | CE93: =AE93 -> 238.704 | CF93: =AI93 -> 369.088 | CG93: =AM93 -> 387.76242 | CH93: =AQ93 -> 452.43186 | CI93: =AU93 -> 536.94967 | CJ93: =AY93 -> 641.62618 | CK93: =BC93 -> 761.02211 | CL93: =BG93 -> 895.63656 | CM93: =BK93 -> 1046.9713 | CN93: =BO93 -> 1216.6871 | CO93: =BS93 -> 1406.8953 | CP93: =BW93 -> 1620.7481 | CQ93: x | CX93: =AH93-AG93 -> 42.272 | CY93: =AI93-AH93 -> 7.02
B94: =Inputs!B80 -> Capital social | D94: 41.861 | E94: 41.861 | F94: 41.861 | G94: 41.867 | H94: =Inputs!J80/1000 -> 41.867 | I94: =Inputs!K80/1000 -> 53.367 | J94: =Inputs!L80/1000 -> 53.367 | K94: =(Inputs!M80/1000)*-1 -> 53.367 | L94: =Inputs!N80/1000 -> 53.367 | M94: =Inputs!O80/1000 -> 53.367 | N94: =Inputs!P80/1000 -> 53.367 | O94: =Inputs!Q80/1000 -> 73.367 | P94: =Inputs!R80/1000 -> 230.879 | Q94: =Inputs!S80/1000 -> 230.774 | R94: =Inputs!T80/1000 -> 233.049 | S94: =Inputs!U80/1000 -> 233.146 | ... AJ94: =Inputs!AL80/1000 -> 318.284 | AK94: =AJ94+AK149 -> 318.284 | AL94: =AK94+AL149 -> 318.284 | AM94: =AL94+AM149 -> 318.284 | AN94: =AM94+AN149 -> 318.284 | AO94: =AN94+AO149 -> 318.284 | AP94: =AO94+AP149 -> 318.284 | AQ94: =AP94+AQ149 -> 318.284 | AR94: =AQ94+AR149 -> 318.284 | ... BW94: =BV94+BW149 -> 318.284 | BX94: x | BY94: =G94 -> 41.867 | BZ94: =K94 -> 53.367 | CA94: =O94 -> 73.367 | CB94: =S94 -> 233.146 | CC94: =W94 -> 233.451 | CD94: =AA94 -> 233.681 | CE94: =AE94 -> 233.681 | CF94: =AI94 -> 318.284 | CG94: =AM94 -> 318.284 | CH94: =AQ94 -> 318.284 | CI94: =AU94 -> 318.284 | CJ94: =AY94 -> 318.284 | CK94: =BC94 -> 318.284 | CL94: =BG94 -> 318.284 | CM94: =BK94 -> 318.284 | CN94: =BO94 -> 318.284 | CO94: =BS94 -> 318.284 | CP94: =BW94 -> 318.284 | CQ94: x | CX94: =AH94-AG94 -> 0 | CY94: =AI94-AH94 -> -0.094
B95: =Inputs!B81 -> Reserva de capital | D95: 1.734 | E95: 1.914 | F95: 2.096 | G95: 2.298 | H95: =Inputs!J81/1000 -> 2.298 | I95: =Inputs!K81/1000 -> 2.298 | J95: =Inputs!L81/1000 -> 2.298 | K95: =(Inputs!M81/1000)*-1 -> 2.298 | L95: =Inputs!N81/1000 -> 2.298 | M95: =Inputs!O81/1000 -> 2.298 | N95: =Inputs!P81/1000 -> 2.298 | O95: =Inputs!Q81/1000 -> 2.298 | P95: =Inputs!R81/1000 -> 2.298 | Q95: =Inputs!S81/1000 -> 2.298 | R95: =Inputs!T81/1000 -> 8.104 | S95: =Inputs!U81/1000 -> 8.104 | ... AJ95: =Inputs!AL81/1000 -> 21.224 | AK95: =AJ95 -> 21.224 | AL95: =AK95 -> 21.224 | AM95: =AL95 -> 21.224 | AN95: =AM95 -> 21.224 | AO95: =AN95 -> 21.224 | AP95: =AO95 -> 21.224 | AQ95: =AP95 -> 21.224 | AR95: =AQ95 -> 21.224 | ... BW95: =BV95 -> 21.224 | BX95: x | BY95: =G95 -> 2.298 | BZ95: =K95 -> 2.298 | CA95: =O95 -> 2.298 | CB95: =S95 -> 8.104 | CC95: =W95 -> 8.104 | CD95: =AA95 -> 8.104 | CE95: =AE95 -> 8.104 | CF95: =AI95 -> 19.79 | CG95: =AM95 -> 21.224 | CH95: =AQ95 -> 21.224 | CI95: =AU95 -> 21.224 | CJ95: =AY95 -> 21.224 | CK95: =BC95 -> 21.224 | CL95: =BG95 -> 21.224 | CM95: =BK95 -> 21.224 | CN95: =BO95 -> 21.224 | CO95: =BS95 -> 21.224 | CP95: =BW95 -> 21.224 | CQ95: x | CX95: =AH95-AG95 -> 10.252 | CY95: =AI95-AH95 -> 1.434
B96: =Inputs!B82 -> (-) Ações em tesouraria | H96: =Inputs!J82/1000 -> 0 | I96: =Inputs!K82/1000 -> 0 | J96: =Inputs!L82/1000 -> 0 | K96: =(Inputs!M82/1000)*-1 -> 0 | L96: =Inputs!N82/1000 -> 0 | M96: =Inputs!O82/1000 -> 0 | N96: =Inputs!P82/1000 -> 0 | O96: =Inputs!Q82/1000 -> 0 | P96: =Inputs!R82/1000 -> 0 | Q96: =Inputs!S82/1000 -> 0 | R96: =Inputs!T82/1000 -> 0 | S96: =Inputs!U82/1000 -> 0 | ... AJ96: =Inputs!AL82/1000 -> 0 | AK96: =AJ96 -> 0 | AL96: =AK96 -> 0 | AM96: =AL96 -> 0 | AN96: =AM96 -> 0 | AO96: =AN96 -> 0 | AP96: =AO96 -> 0 | AQ96: =AP96 -> 0 | AR96: =AQ96 -> 0 | ... BW96: =BV96 -> 0 | BX96: x | BY96: =G96 | BZ96: =K96 -> 0 | CA96: =O96 -> 0 | CB96: =S96 -> 0 | CC96: =W96 -> -6.581 | CD96: =AA96 -> -11.978 | CE96: =AE96 -> -11.978 | CF96: =AI96 -> 0 | CG96: =AM96 -> 0 | CH96: =AQ96 -> 0 | CI96: =AU96 -> 0 | CJ96: =AY96 -> 0 | CK96: =BC96 -> 0 | CL96: =BG96 -> 0 | CM96: =BK96 -> 0 | CN96: =BO96 -> 0 | CO96: =BS96 -> 0 | CP96: =BW96 -> 0 | CQ96: x | CX96: =AH96-AG96 -> 11.978 | CY96: =AI96-AH96 -> 0
B97: =Inputs!B83 -> Ajuste avaliação patrimonial | H97: =Inputs!J83/1000 -> 0 | I97: =Inputs!K83/1000 -> 0 | J97: =Inputs!L83/1000 -> 0 | K97: =(Inputs!M83/1000)*-1 -> 0 | L97: =Inputs!N83/1000 -> 0 | M97: =Inputs!O83/1000 -> 0 | N97: =Inputs!P83/1000 -> 0 | O97: =Inputs!Q83/1000 -> 0 | P97: =Inputs!R83/1000 -> 0 | Q97: =Inputs!S83/1000 -> 0 | R97: =Inputs!T83/1000 -> -11.278 | S97: =Inputs!U83/1000 -> -12.09 | ... AJ97: =Inputs!AL83/1000 -> -33.621 | AK97: =AJ97 -> -33.621 | AL97: =AK97 -> -33.621 | AM97: =AL97 -> -33.621 | AN97: =AM97 -> -33.621 | AO97: =AN97 -> -33.621 | AP97: =AO97 -> -33.621 | AQ97: =AP97 -> -33.621 | AR97: =AQ97 -> -33.621 | ... BW97: =BV97 -> -33.621 | BX97: x | BY97: =G97 | BZ97: =K97 -> 0 | CA97: =O97 -> 0 | CB97: =S97 -> -12.09 | CC97: =W97 -> -13.346 | CD97: =AA97 -> -32.314 | CE97: =AE97 -> -33.621 | CF97: =AI97 -> -33.621 | CG97: =AM97 -> -33.621 | CH97: =AQ97 -> -33.621 | CI97: =AU97 -> -33.621 | CJ97: =AY97 -> -33.621 | CK97: =BC97 -> -33.621 | CL97: =BG97 -> -33.621 | CM97: =BK97 -> -33.621 | CN97: =BO97 -> -33.621 | CO97: =BS97 -> -33.621 | CP97: =BW97 -> -33.621 | CQ97: x | CX97: =AH97-AG97 -> 0 | CY97: =AI97-AH97 -> 0
B98: =Inputs!B84 -> Reservas de lucros | H98: =Inputs!J84/1000 -> 2.453 | I98: =Inputs!K84/1000 -> 2.453 | J98: =Inputs!L84/1000 -> 2.453 | K98: =(Inputs!M84/1000)*-1 -> 4.772 | L98: =Inputs!N84/1000 -> 4.772 | M98: =Inputs!O84/1000 -> 4.772 | N98: =Inputs!P84/1000 -> 4.772 | O98: =Inputs!Q84/1000 -> 0 | P98: =Inputs!R84/1000 -> 0 | Q98: =Inputs!S84/1000 -> 0 | R98: =Inputs!T84/1000 -> 0 | S98: =Inputs!U84/1000 -> 0 | ... AJ98: =Inputs!AL84/1000 -> 36.289 | AK98: =AJ98 -> 36.289 | AL98: =AK98 -> 36.289 | AM98: =AL98 -> 36.289 | AN98: =AM98 -> 36.289 | AO98: =AN98 -> 36.289 | AP98: =AO98 -> 36.289 | AQ98: =AP98 -> 36.289 | AR98: =AQ98 -> 36.289 | ... BW98: =BV98 -> 36.289 | BX98: x | BY98: =G98 | BZ98: =K98 -> 4.772 | CA98: =O98 -> 0 | CB98: =S98 -> 0 | CC98: =W98 -> 7.4518056 | CD98: =AA98 -> 18.102 | CE98: =AE98 -> 28.549 | CF98: =AI98 -> 36.289 | CG98: =AM98 -> 36.289 | CH98: =AQ98 -> 36.289 | CI98: =AU98 -> 36.289 | CJ98: =AY98 -> 36.289 | CK98: =BC98 -> 36.289 | CL98: =BG98 -> 36.289 | CM98: =BK98 -> 36.289 | CN98: =BO98 -> 36.289 | CO98: =BS98 -> 36.289 | CP98: =BW98 -> 36.289 | CQ98: x | CX98: =AH98-AG98 -> 0 | CY98: =AI98-AH98 -> 7.74
B99: =Inputs!B85 -> Dividendos propostos | H99: =Inputs!J85/1000 -> 0 | I99: =Inputs!K85/1000 -> 0 | J99: =Inputs!L85/1000 -> 0 | K99: =(Inputs!M85/1000)*-1 -> 0.722 | L99: =Inputs!N85/1000 -> 0.722 | M99: =Inputs!O85/1000 -> 0 | N99: =Inputs!P85/1000 -> 0 | O99: =Inputs!Q85/1000 -> 0 | P99: =Inputs!R85/1000 -> 0 | Q99: =Inputs!S85/1000 -> 0 | R99: =Inputs!T85/1000 -> 0 | S99: =Inputs!U85/1000 -> 0 | ... AJ99: =Inputs!AL85/1000 -> 0 | AK99: =AJ99 -> 0 | AL99: =AK99 -> 0 | AM99: =AL99 -> 0 | AN99: =AM99 -> 0 | AO99: =AN99 -> 0 | AP99: =AO99 -> 0 | AQ99: =AP99 -> 0 | AR99: =AQ99 -> 0 | ... BW99: =BV99 -> 0 | BX99: x | BY99: =G99 | BZ99: =K99 -> 0.722 | CA99: =O99 -> 0 | CB99: =S99 -> 0 | CC99: =W99 -> 0 | CD99: =AA99 -> 0 | CE99: =AE99 -> 0 | CF99: =AI99 -> 0 | CG99: =AM99 -> 0 | CH99: =AQ99 -> 0 | CI99: =AU99 -> 0 | CJ99: =AY99 -> 0 | CK99: =BC99 -> 0 | CL99: =BG99 -> 0 | CM99: =BK99 -> 0 | CN99: =BO99 -> 0 | CO99: =BS99 -> 0 | CP99: =BW99 -> 0 | CQ99: x | CX99: =AH99-AG99 -> 0 | CY99: =AI99-AH99 -> 0
B100: =Inputs!B86 -> Lucros (Prejuízo) acumulados do período | H100: =Inputs!J86/1000 -> 1.154 | I100: =Inputs!K86/1000 -> -2.616 | J100: =Inputs!L86/1000 -> -3.368 | K100: =(Inputs!M86/1000)*-1 -> 0 | L100: =Inputs!N86/1000 -> 0.128 | M100: =Inputs!O86/1000 -> -1.163 | N100: =Inputs!P86/1000 -> -3.155 | O100: =Inputs!Q86/1000 -> -1.337 | P100: =Inputs!R86/1000 -> 2.707 | Q100: =Inputs!S86/1000 -> -13.977 | R100: =Inputs!T86/1000 -> -18.901 | S100: =Inputs!U86/1000 -> -3.473 | ... AJ100: =Inputs!AL86/1000 -> 1.803 | AK100: =AJ100+AK47+AK250 -> 4.0186413 | AL100: =AK100+AL47+AL250 -> 16.581925 | AM100: =AL100+AM47+AM250 -> 29.464423 | AN100: =AM100+AN47+AN250 -> 44.970596 | AO100: =AN100+AO47+AO250 -> 58.670664 | AP100: =AO100+AP47+AP250 -> 73.411888 | AQ100: =AP100+AQ47+AQ250 -> 94.133862 | AR100: =AQ100+AR47+AR250 -> 114.45399 | ... BW100: =BV100+BW47+BW250 -> 1262.4501 | BX100: x | BY100: =G100 | BZ100: =K100 -> 0 | CA100: =O100 -> -1.337 | CB100: =S100 -> -3.473 | CC100: =W100 -> 0 | CD100: =AA100 -> 0 | CE100: =AE100 -> 0 | CF100: =AI100 -> 14.438 | CG100: =AM100 -> 29.464423 | CH100: =AQ100 -> 94.133862 | CI100: =AU100 -> 178.65167 | CJ100: =AY100 -> 283.32818 | CK100: =BC100 -> 402.72411 | CL100: =BG100 -> 537.33856 | CM100: =BK100 -> 688.67326 | CN100: =BO100 -> 858.38912 | CO100: =BS100 -> 1048.5973 | CP100: =BW100 -> 1262.4501 | CQ100: x | CX100: =AH100-AG100 -> 16.585 | CY100: =AI100-AH100 -> 1.281
B101: =Inputs!B89 -> Participações não controladores | G101: 8.156 | H101: =Inputs!J89/1000 -> 7.457 | I101: =Inputs!K89/1000 -> 6.365 | J101: =Inputs!L89/1000 -> 5.925 | K101: =(Inputs!M89/1000)*-1 -> 4.97 | L101: =Inputs!N89/1000 -> 4.337 | M101: =Inputs!O89/1000 -> 3.642 | N101: =Inputs!P89/1000 -> 2.691 | O101: =Inputs!Q89/1000 -> 0.281 | P101: =Inputs!R89/1000 -> -0.493 | Q101: =Inputs!S89/1000 -> -0.926 | R101: =Inputs!T89/1000 -> -1.311 | S101: =Inputs!U89/1000 -> -0.101 | ... AJ101: =Inputs!AL89/1000 -> 16.122 | AK101: =AJ101 -> 16.122 | AL101: =AK101 -> 16.122 | AM101: =AL101 -> 16.122 | AN101: =AM101 -> 16.122 | AO101: =AN101 -> 16.122 | AP101: =AO101 -> 16.122 | AQ101: =AP101 -> 16.122 | AR101: =AQ101 -> 16.122 | ... BW101: =BV101 -> 16.122 | BX101: x | BY101: =G101 -> 8.156 | BZ101: =K101 -> 4.97 | CA101: =O101 -> 0.281 | CB101: =S101 -> -0.101 | CC101: =W101 -> 0 | CD101: =AA101 -> 6.167 | CE101: =AE101 -> 13.969 | CF101: =AI101 -> 13.908 | CG101: =AM101 -> 16.122 | CH101: =AQ101 -> 16.122 | CI101: =AU101 -> 16.122 | CJ101: =AY101 -> 16.122 | CK101: =BC101 -> 16.122 | CL101: =BG101 -> 16.122 | CM101: =BK101 -> 16.122 | CN101: =BO101 -> 16.122 | CO101: =BS101 -> 16.122 | CP101: =BW101 -> 16.122 | CQ101: x | CX101: =AH101-AG101 -> 3.457 | CY101: =AI101-AH101 -> -3.341
B102: Outros | D102: 14.582 | E102: 13.229 | F102: 18.852 | G102: 2.453 | H102: 0 | I102: 0 | J102: 0 | K102: 0 | L102: 0 | M102: 0 | N102: 0 | O102: 0 | P102: 0 | Q102: 0 | R102: 0 | S102: 0 | T102: 0 | U102: 0 | V102: 0 | W102: 0 | X102: 0 | Y102: 0 | Z102: 0 | AA102: 0 | AB102: 0 | AC102: 0 | AD102: 0 | AE102: 0 | AF102: 0 | AG102: 0 | AH102: 0 | AI102: 0 | AJ102: 0 | AK102: =AJ102 -> 0 | AL102: =AK102 -> 0 | AM102: =AL102 -> 0 | AN102: =AM102 -> 0 | AO102: =AN102 -> 0 | AP102: =AO102 -> 0 | AQ102: =AP102 -> 0 | AR102: =AQ102 -> 0 | ... BW102: =BV102 -> 0 | BX102: x | BY102: =G102 -> 2.453 | BZ102: =K102 -> 0 | CA102: =O102 -> 0 | CB102: =S102 -> 0 | CC102: =W102 -> 0 | CD102: =AA102 -> 0 | CE102: =AE102 -> 0 | CF102: =AI102 -> 0 | CG102: =AM102 -> 0 | CH102: =AQ102 -> 0 | CI102: =AU102 -> 0 | CJ102: =AY102 -> 0 | CK102: =BC102 -> 0 | CL102: =BG102 -> 0 | CM102: =BK102 -> 0 | CN102: =BO102 -> 0 | CO102: =BS102 -> 0 | CP102: =BW102 -> 0 | CQ102: x | CX102: =AH102-AG102 -> 0 | CY102: =AI102-AH102 -> 0
BX103: x | CQ103: x
B104: Check | D104: =+D58-D74-D93 -> 0 | E104: =+E58-E74-E93 -> 0 | F104: =+F58-F74-F93 -> 0 | G104: =+G58-G74-G93 -> 0 | H104: =+H58-H74-H93 -> 0 | I104: =+I58-I74-I93 -> 0 | J104: =+J58-J74-J93 -> 0 | K104: =+K58-K74-K93 -> 0 | ... BW104: =+BW58-BW74-BW93 -> 0 | BX104: x | BY104: =BY58-BY74-BY93 -> 0 | BZ104: =BZ58-BZ74-BZ93 -> 0 | CA104: =CA58-CA74-CA93 -> 0 | CB104: =CB58-CB74-CB93 -> 0 | CC104: =CC58-CC74-CC93 -> 0.00019438 | CD104: =CD58-CD74-CD93 -> 0.00018828 | CE104: =CE58-CE74-CE93 -> -9.9999511e-09 | CF104: =CF58-CF74-CF93 -> 0 | ... CP104: =CP58-CP74-CP93 -> 0 | CQ104: x | CX104: =AH104 -> 0 | CY104: =AI104 -> 0
BX105: x | CQ105: x
B106: Dívida Bruta | D106: =D78+D87 -> 12.892 | E106: =E78+E87 -> 34.816 | F106: =F78+F87 -> 48.589 | G106: =G78+G87 -> 65.476 | H106: =H78+H87 -> 67.711 | I106: =I78+I87 -> 60.742 | J106: =J78+J87 -> 62.45 | K106: =K78+K87 -> 67.637 | ... AJ106: =AJ78+AJ87 -> 647.362 | AK106: =+AK233 -> 647.362 | AL106: =+AL233 -> 647.362 | AM106: =+AM233 -> 647.362 | AN106: =+AN233 -> 647.362 | AO106: =+AO233 -> 647.362 | AP106: =+AP233 -> 647.362 | AQ106: =+AQ233 -> 647.362 | AR106: =+AR233 -> 647.362 | ... BW106: =+BW233 -> 647.362 | BX106: x | BY106: =BY78+BY87 -> 65.476 | BZ106: =BZ78+BZ87 -> 67.637 | CA106: =CA78+CA87 -> 77.811 | CB106: =CB78+CB87 -> 56.11 | CC106: =CC78+CC87 -> 60.34 | CD106: =CD78+CD87 -> 136.348 | CE106: =CE78+CE87 -> 348.561 | CF106: =CF78+CF87 -> 463.583 | ... CP106: =CP78+CP87 -> 647.362 | CQ106: x
...

Sheet Build-Up
B7: Valores em R$ (Milhares) | C7: Unidade | D7: 1T17 | E7: 2T17 | F7: 3T17 | G7: 4T17 | H7: 1T18 | I7: 2T18 | J7: 3T18 | K7: 4T18 | L7: 1T19 | M7: 2T19 | N7: 3T19 | O7: 4T19 | P7: 1T20 | Q7: 2T20 | R7: 3T20 | S7: 4T20 | T7: 1T21 | U7: 2T21 | V7: 3T21 | W7: 4T21 | X7: 1T22 | Y7: 2T22 | Z7: 3T22 | AA7: 4T22 | AB7: 1T23 | AC7: 2T23 | AD7: 3T23 | AE7: 4T23 | AF7: 1T24 | AG7: 2T24 | AH7: 3T24 | AI7: 4T24 | AJ7: 1T25 | AK7: 2T25 | AL7: 3T25 | AM7: 4T25 | AN7: 1T26 | AO7: 2T26 | AP7: 3T26 | AQ7: 4T26 | AR7: 1T27 | AS7: 2T27 | AT7: 3T27 | AU7: 4T27 | AV7: 1T28 | AW7: 2T28 | AX7: 3T28 | AY7: 4T28 | AZ7: 1T29 | BA7: 2T29 | BB7: 3T29 | BC7: 4T29 | BD7: 1T30 | BE7: 2T30 | BF7: 3T30 | BG7: 4T30 | BH7: 1T31 | BI7: 2T31 | BJ7: 3T31 | BK7: 4T31 | BL7: 1T32 | BM7: 2T32 | BN7: 3T32 | BO7: 4T32 | BP7: 1T33 | BQ7: 2T33 | BR7: 3T33 | BS7: 4T33 | BT7: 1T34 | BU7: 2T34 | BV7: 3T34 | BW7: 4T34 | BX7: x | BY7: 2017 | BZ7: =BY7+1 -> 2018 | CA7: =BZ7+1 -> 2019 | CB7: =CA7+1 -> 2020 | CC7: =CB7+1 -> 2021 | CD7: =CC7+1 -> 2022 | CE7: =CD7+1 -> 2023 | CF7: =CE7+1 -> 2024 | CG7: =CF7+1 -> 2025 | ... CP7: =CO7+1 -> 2034 | CQ7: x | CR7: CAGR: 17-24 | CS7: CAGR: 19-23 | CT7: CAGR: 22-24 | CU7: CAGR: 23-26 | CV7: CAGR: 24-28 | CW7: CAGR: 25-28
BX8: x | CQ8: x
A9: l | B9: Quebra da Receita Bruta e Líquida | BX9: x | CQ9: x | CR9: =CF35/(1+CF15+CF18) -> 288.66876
BX10: x | CQ10: x
B11: Receita Bruta | C11: [BRL 000] | D11: =Inputs!F344/1000 -> 58.518 | E11: =Inputs!G344/1000 -> 59.783 | F11: =Inputs!H344/1000 -> 67.278 | G11: =Inputs!I344/1000 -> 75.153 | H11: =Inputs!J344/1000 -> 83.716 | I11: =Inputs!K344/1000 -> 92.528 | J11: =Inputs!L344/1000 -> 87.657 | K11: =Inputs!M344/1000 -> 96.578 | ... W11: =Inputs!Y344/1000 -> 130.823 | X11: =Inputs!Z309/1000 -> 141.28999 | Y11: =Inputs!AA309/1000 -> 200.75693 | Z11: =Inputs!AB309/1000 -> 276.42344 | AA11: =Inputs!AC309/1000 -> 266.63214 | AB11: =Inputs!AD309/1000 -> 261.54306 | AC11: =Inputs!AE309/1000 -> 274.60451 | AD11: =Inputs!AF309/1000 -> 293.4205 | AE11: =Inputs!AG309/1000 -> 310.04005 | ... AG11: =Inputs!AI309/1000 -> 227.09262 | AH11: =Inputs!AJ344/1000 -> 432.75508 | AI11: =Inputs!AK344/1000 -> 458.05011 | AJ11: =Inputs!AL344/1000 -> 403.20242 | AK11: =AK20/(1+AK15+AK18) -> 392.24141 | AL11: =AL20/(1+AL15+AL18) -> 408.57771 | AM11: =AM20/(1+AM15+AM18) -> 453.92669 | AN11: =AN20/(1+AN15+AN18) -> 424.32508 | AO11: =AO20/(1+AO15+AO18) -> 426.21414 | AP11: =AP20/(1+AP15+AP18) -> 457.50021 | AQ11: =AQ20/(1+AQ15+AQ18) -> 504.61505 | AR11: =AR20/(1+AR15+AR18) -> 469.38424 | ... BW11: =BW20/(1+BW15+BW18) -> 1025.0819 | BX11: x | BY11: =SUM(D11:G11) -> 260.732 | BZ11: =SUM(H11:K11) -> 360.479 | CA11: =SUM(L11:O11) -> 388.153 | CB11: =SUM(P11:S11) -> 268.803 | CC11: =SUM(T11:W11) -> 472.785 | CD11: =SUM(X11:AA11) -> 885.10249 | CE11: =SUM(AB11:AE11) -> 1139.6081 | CF11: =SUM(AF11:AI11) -> 1356.1719 | CG11: =SUM(AJ11:AM11) -> 1657.9482 | CH11: =SUM(AN11:AQ11) -> 1812.6545 | CI11: =SUM(AR11:AU11) -> 1991.0038 | CJ11: =SUM(AV11:AY11) -> 2175.4388 | CK11: =SUM(AZ11:BC11) -> 2376.9589 | CL11: =SUM(BD11:BG11) -> 2597.1466 | CM11: =SUM(BH11:BK11) -> 2837.7312 | CN11: =SUM(BL11:BO11) -> 3100.6022 | CO11: =SUM(BP11:BS11) -> 3387.8241 | CP11: =SUM(BT11:BW11) -> 3701.6525 | CQ11: x | CR11: =(CF11/BY11)^(1/7)-1 -> 0.26561879 | CS11: =(CE11/CA11)^(1/4)-1 -> 0.30899548 | CT11: =(CF11/CD11)^(1/2)-1 -> 0.23782882 | CU11: =(CH11/CE11)^(1/3)-1 -> 0.16731078 | CV11: =(CJ11/CF11)^(1/4)-1 -> 0.12540291 | CW11: =(CJ11/CG11)^(1/3)-1 -> 0.09477609
B12: a/a % | C12: [%] | H12: =H11/D11-1 -> 0.43060255 | I12: =I11/E11-1 -> 0.54773096 | J12: =J11/F11-1 -> 0.30290734 | K12: =K11/G11-1 -> 0.28508509 | L12: =L11/H11-1 -> 0.088155191 | M12: =M11/I11-1 -> 0.12007176 | N12: =N11/J11-1 -> 0.085070217 | O12: =O11/K11-1 -> 0.017881919 | ... BW12: =BW11/BS11-1 -> 0.09263421 | BX12: x | BZ12: =BZ11/BY11-1 -> 0.38256524 | CA12: =CA11/BZ11-1 -> 0.076770075 | CB12: =CB11/CA11-1 -> -0.30748184 | CC12: =CC11/CB11-1 -> 0.75885314 | CD12: =CD11/CC11-1 -> 0.87210358 | CE12: =CE11/CD11-1 -> 0.28754369 | CF12: =CF11/CE11-1 -> 0.19003355 | CG12: =CG11/CF11-1 -> 0.22252071 | ... CP12: =CP11/CO11-1 -> 0.09263421 | CQ12: x
BX13: x | CQ13: x
B14: Tributos sobre as vendas | D14: -6.178 | E14: -5.694 | F14: -5.811 | G14: -6.139 | H14: -6.872 | I14: -7.462 | J14: -6.975 | K14: -8.066 | L14: -7.455 | M14: -7.941 | N14: -7.564 | O14: -8.348 | P14: -6.136 | Q14: -4.427 | R14: -4.343 | S14: -5.587 | T14: -6.225 | U14: =Inputs!W370/1000 -> -8.837 | V14: =Inputs!X370/1000 -> -10.4 | W14: =Inputs!Y370/1000 -> -9.711 | X14: =Inputs!Z370/1000 -> -10.219 | Y14: =Inputs!AA370/1000 -> -15.45 | Z14: =Inputs!AB370/1000 -> -20.534 | AA14: =Inputs!AC370/1000 -> -18.594 | AB14: =Inputs!AD370/1000 -> -18.887 | ... AG14: =Inputs!AI370/1000 -> -18.617 | AH14: =AH20-AH11+AH17 -> -46.198874 | AI14: =AI20-AI11+AI17 -> -41.653592 | AJ14: =AJ20-AJ11+AJ17 -> -35.886535 | AK14: =AK15*AK$11 -> -32.155859 | AL14: =AL15*AL$11 -> -43.617813 | AM14: =AM15*AM$11 -> -41.278623 | AN14: =AN15*AN$11 -> -37.766531 | AO14: =AO15*AO$11 -> -34.940935 | AP14: =AP15*AP$11 -> -48.840547 | AQ14: =AQ15*AQ$11 -> -45.888057 | AR14: =AR15*AR$11 -> -41.776966 | ... BW14: =BW15*BW$11 -> -93.217623 | BX14: x | BY14: =SUM(D14:G14) -> -23.822 | BZ14: =SUM(H14:K14) -> -29.375 | CA14: =SUM(L14:O14) -> -31.308 | CB14: =SUM(P14:S14) -> -20.493 | CC14: =SUM(T14:W14) -> -35.173 | CD14: =SUM(X14:AA14) -> -64.797 | CE14: =SUM(AB14:AE14) -> -85.332 | CF14: =SUM(AF14:AI14) -> -127.06347 | CG14: =SUM(AJ14:AM14) -> -152.93883 | CH14: =SUM(AN14:AQ14) -> -167.43607 | CI14: =SUM(AR14:AU14) -> -183.87271 | CJ14: =SUM(AV14:AY14) -> -200.90561 | CK14: =SUM(AZ14:BC14) -> -219.51634 | CL14: =SUM(BD14:BG14) -> -239.85107 | CM14: =SUM(BH14:BK14) -> -262.06948 | CN14: =SUM(BL14:BO14) -> -286.34608 | CO14: =SUM(BP14:BS14) -> -312.87152 | CP14: =SUM(BT14:BW14) -> -341.85413 | CQ14: x
B15: % da Receita Bruta | D15: =D14/D$11 -> -0.10557435 | E15: =E14/E$11 -> -0.095244467 | F15: =F14/F$11 -> -0.08637296 | G15: =G14/G$11 -> -0.081686692 | H15: =H14/H$11 -> -0.082087056 | I15: =I14/I$11 -> -0.080645859 | J15: =J14/J$11 -> -0.079571512 | K15: =K14/K$11 -> -0.083517985 | ... AJ15: =AJ14/AJ$11 -> -0.089003768 | AK15: =AG15 -> -0.081979766 | AL15: =AH15 -> -0.10675524 | AM15: =AI15 -> -0.09093676 | AN15: =AJ15 -> -0.089003768 | AO15: =AK15 -> -0.081979766 | AP15: =AL15 -> -0.10675524 | AQ15: =AM15 -> -0.09093676 | AR15: =AN15 -> -0.089003768 | ... BW15: =BS15 -> -0.09093676 | BX15: x | CE15: =CE14/CE11 -> -0.074878371 | CF15: =CF14/CF11 -> -0.093692744 | CG15: =CG14/CG11 -> -0.092245841 | CH15: =CH14/CH11 -> -0.092370649 | CI15: =CI14/CI11 -> -0.092351762 | CJ15: =CJ14/CJ11 -> -0.092351762 | CK15: =CK14/CK11 -> -0.092351762 | CL15: =CL14/CL11 -> -0.092351762 | ... CP15: =CP14/CP11 -> -0.092351762
BX16: x
B17: Cancelamentos | D17: -0.048 | E17: -0.063 | F17: -0.068 | G17: -0.229 | H17: -0.748 | I17: -0.74 | J17: -0.798 | K17: -1.581 | L17: -0.761 | M17: -3.241 | N17: -2.162 | O17: -2.069 | P17: -0.077 | Q17: -2.967 | R17: -2.444 | S17: -0.609 | T17: -0.684 | U17: =Inputs!W371/1000 -> -0.812 | V17: =Inputs!X371/1000 -> -1.456 | W17: =Inputs!Y371/1000 -> -1.519 | X17: =Inputs!Z371/1000 -> -1.783 | Y17: =Inputs!AA371/1000 -> -1.365 | Z17: =Inputs!AB371/1000 -> -1.45 | AA17: =Inputs!AC371/1000 -> -2.213 | AB17: =Inputs!AD371/1000 -> -1.394 | ... AJ17: =Inputs!AL371/1000 -> -1.529 | AK17: =AK18*AK$11 -> -5.5530476 | AL17: =AL18*AL$11 -> -5.7780849 | AM17: =AM18*AM$11 -> -3.2663291 | AN17: =AN18*AN$11 -> -1.6091001 | AO17: =AO18*AO$11 -> -6.0340069 | AP17: =AP18*AP$11 -> -6.4699443 | AQ17: =AQ18*AQ$11 -> -3.6310683 | AR17: =AR18*AR$11 -> -1.7799707 | ... BW17: =BW18*BW$11 -> -7.3762014 | BX17: x | BY17: =SUM(D17:G17) -> -0.408 | BZ17: =SUM(H17:K17) -> -3.867 | CA17: =SUM(L17:O17) -> -8.233 | CB17: =SUM(P17:S17) -> -6.097 | CC17: =SUM(T17:W17) -> -4.471 | CD17: =SUM(X17:AA17) -> -6.811 | CE17: =SUM(AB17:AE17) -> -7.865 | CF17: =SUM(AF17:AI17) -> -13.88 | CG17: =SUM(AJ17:AM17) -> -16.126462 | CH17: =SUM(AN17:AQ17) -> -17.74412 | CI17: =SUM(AR17:AU17) -> -19.475929 | CJ17: =SUM(AV17:AY17) -> -21.280067 | CK17: =SUM(AZ17:BC17) -> -23.251329 | CL17: =SUM(BD17:BG17) -> -25.405197 | CM17: =SUM(BH17:BK17) -> -27.758588 | CN17: =SUM(BL17:BO17) -> -30.329983 | CO17: =SUM(BP17:BS17) -> -33.139577 | CP17: =SUM(BT17:BW17) -> -36.209435 | CQ17: x
B18: % da Receita Bruta | D18: =D17/D$11 -> -0.00082026043 | E18: =E17/E$11 -> -0.0010538113 | F18: =F17/F$11 -> -0.0010107316 | G18: =G17/G$11 -> -0.0030471172 | H18: =H17/H$11 -> -0.0089349706 | I18: =I17/I$11 -> -0.0079975791 | J18: =J17/J$11 -> -0.0091036654 | K18: =K17/K$11 -> -0.016370188 | ... AJ18: =AJ17/AJ$11 -> -0.0037921399 | AK18: =AG18 -> -0.014157219 | AL18: =AH18 -> -0.014141948 | AM18: =AI18 -> -0.0071957193 | AN18: =AJ18 -> -0.0037921399 | AO18: =AK18 -> -0.014157219 | AP18: =AL18 -> -0.014141948 | AQ18: =AM18 -> -0.0071957193 | AR18: =AN18 -> -0.0037921399 | ... BW18: =BS18 -> -0.0071957193 | BX18: x | CE18: =CE17/CE11 -> -0.0069014952 | CF18: =CF17/CF11 -> -0.010234691 | CG18: =CG17/CG11 -> -0.0097267582 | CH18: =CH17/CH11 -> -0.0097890248 | CI18: =CI17/CI11 -> -0.0097819651 | CJ18: =CJ17/CJ11 -> -0.0097819651 | CK18: =CK17/CK11 -> -0.0097819651 | CL18: =CL17/CL11 -> -0.0097819651 | ... CP18: =CP17/CP11 -> -0.0097819651
BX19: x | CQ19: x
B20: Receita Líquida | C20: [BRL 000] | D20: =D11+D14+D17 -> 52.292 | E20: =E11+E14+E17 -> 54.026 | F20: =F11+F14+F17 -> 61.399 | G20: =G11+G14+G17 -> 68.785 | H20: =H11+H14+H17 -> 76.096 | I20: =I11+I14+I17 -> 84.326 | J20: =J11+J14+J17 -> 79.884 | K20: =K11+K14+K17 -> 86.931 | ... AG20: =AG11+AG14+AG17 -> 205.26062 | AH20: =Inputs!AJ314/1000 -> 392.6762 | AI20: =Inputs!AK314/1000 -> 419.69251 | AJ20: =Inputs!AL314/1000 -> 368.84489 | AK20: =AK44*AK47*3/1000 -> 354.5325 | AL20: =AL44*AL47*3/1000 -> 359.18181 | AM20: =AM44*AM47*3/1000 -> 409.38174 | AN20: =AN44*AN47*3/1000 -> 384.94945 | AO20: =AO44*AO47*3/1000 -> 385.23919 | AP20: =AP44*AP47*3/1000 -> 402.18972 | AQ20: =AQ44*AQ47*3/1000 -> 455.09592 | AR20: =AR44*AR47*3/1000 -> 425.82731 | ... BW20: =BW44*BW47*3/1000 -> 924.48804 | BX20: x | BY20: =SUM(D20:G20) -> 236.502 | BZ20: =SUM(H20:K20) -> 327.237 | CA20: =SUM(L20:O20) -> 348.612 | CB20: =SUM(P20:S20) -> 242.213 | CC20: =SUM(T20:W20) -> 433.141 | CD20: =SUM(X20:AA20) -> 813.49449 | CE20: =SUM(AB20:AE20) -> 1046.4111 | CF20: =SUM(AF20:AI20) -> 1234.0604 | CG20: =SUM(AJ20:AM20) -> 1491.9409 | CH20: =SUM(AN20:AQ20) -> 1627.4743 | CI20: =SUM(AR20:AU20) -> 1787.6551 | CJ20: =SUM(AV20:AY20) -> 1953.2532 | CK20: =SUM(AZ20:BC20) -> 2134.1912 | CL20: =SUM(BD20:BG20) -> 2331.8903 | CM20: =SUM(BH20:BK20) -> 2547.9032 | CN20: =SUM(BL20:BO20) -> 2783.9262 | CO20: =SUM(BP20:BS20) -> 3041.813 | CP20: =SUM(BT20:BW20) -> 3323.5889 | CQ20: x | CR20: =(CF20/BY20)^(1/7)-1 -> 0.26619394 | CS20: =(CE20/CA20)^(1/4)-1 -> 0.31625491 | CT20: =(CF20/CD20)^(1/2)-1 -> 0.2316602 | CU20: =(CH20/CE20)^(1/3)-1 -> 0.15860997 | CV20: =(CJ20/CF20)^(1/4)-1 -> 0.12164526 | CW20: =(CJ20/CG20)^(1/3)-1 -> 0.093962163
B21: a/a % | C21: [%] | H21: =H20/D20-1 -> 0.45521303 | I21: =I20/E20-1 -> 0.56084108 | J21: =J20/F20-1 -> 0.30106354 | K21: =K20/G20-1 -> 0.26380752 | L21: =L20/H20-1 -> 0.089150547 | M21: =M20/I20-1 -> 0.096411546 | N21: =N20/J20-1 -> 0.068899905 | O21: =O20/K20-1 -> 0.011008731 | ... BW21: =BW20/BS20-1 -> 0.09263421 | BX21: x | BZ21: =BZ20/BY20-1 -> 0.38365426 | CA21: =CA20/BZ20-1 -> 0.065319631 | CB21: =CB20/CA20-1 -> -0.30520751 | CC21: =CC20/CB20-1 -> 0.78826487 | CD21: =CD20/CC20-1 -> 0.87812858 | CE21: =CE20/CD20-1 -> 0.28631618 | CF21: =CF20/CE20-1 -> 0.17932656 | CG21: =CG20/CF20-1 -> 0.20896911 | ... CP21: =CP20/CO20-1 -> 0.09263421 | CQ21: x
BX22: x | CQ22: x
B23: =Inputs!B315 -> Serviços Industriais | C23: [BRL 000] | X23: =Inputs!Z315/1000 -> 122.98938 | Y23: =Inputs!AA315/1000 -> 153.37301 | Z23: =Inputs!AB315/1000 -> 168.143 | AA23: =Inputs!AC315/1000 -> 175.15283 | AB23: =Inputs!AD315/1000 -> 190.062 | AC23: =Inputs!AE315/1000 -> 198.1976 | AD23: =Inputs!AF315/1000 -> 214.61302 | AE23: =Inputs!AG315/1000 -> 212.85253 | ... AJ23: =Inputs!AL315/1000 -> 197.11955 | AK23: =AK$20*AK25 -> 191.27155 | AL23: =AL$20*AL25 -> 193.77987 | AM23: =AM$20*AM25 -> 220.86292 | AN23: =AN$20*AN25 -> 207.68161 | AO23: =AO$20*AO25 -> 207.83793 | AP23: =AP$20*AP25 -> 216.98279 | AQ23: =AQ$20*AQ25 -> 245.52588 | AR23: =AR$20*AR25 -> 229.73536 | ... BW23: =BW$20*BW25 -> 498.76461 | BX23: x | BY23: =SUM(D23:G23) -> 0 | BZ23: =SUM(H23:K23) -> 0 | CA23: =SUM(L23:O23) -> 0 | CB23: =SUM(P23:S23) -> 0 | CC23: =SUM(T23:W23) -> 0 | CD23: =SUM(X23:AA23) -> 619.65821 | CE23: =SUM(AB23:AE23) -> 815.72515 | CF23: =SUM(AF23:AI23) -> 686.441 | CG23: =SUM(AJ23:AM23) -> 803.0339 | CH23: =SUM(AN23:AQ23) -> 878.02821 | CI23: =SUM(AR23:AU23) -> 964.44636 | CJ23: =SUM(AV23:AY23) -> 1053.7871 | CK23: =SUM(AZ23:BC23) -> 1151.4038 | CL23: =SUM(BD23:BG23) -> 1258.0632 | CM23: =SUM(BH23:BK23) -> 1374.6029 | CN23: =SUM(BL23:BO23) -> 1501.9381 | CO23: =SUM(BP23:BS23) -> 1641.069 | CP23: =SUM(BT23:BW23) -> 1793.0881 | CQ23: x | CT23: =(CF23/CD23)^(1/2)-1 -> 0.052508239 | CU23: =(CH23/CE23)^(1/3)-1 -> 0.02483718 | CV23: =(CJ23/CF23)^(1/4)-1 -> 0.11310828 | CW23: =(CJ23/CG23)^(1/3)-1 -> 0.094812291
B24: a/a % | C24: [%] | AB24: =AB23/X23-1 -> 0.54535298 | AC24: =AC23/Y23-1 -> 0.29225865 | AD24: =AD23/Z23-1 -> 0.27637204 | AE24: =AE23/AA23-1 -> 0.21523889 | AF24: =AF23/AB23-1 -> -0.14510475 | AG24: =AG23/AC23-1 -> -0.27932575 | AH24: =AH23/AD23-1 -> -0.16551298 | AI24: =AI23/AE23-1 -> -0.050844173 | ... BW24: =BW23/BS23-1 -> 0.09263421 | BX24: x | CE24: =CE23/CD23-1 -> 0.31641142 | CF24: =CF23/CE23-1 -> -0.15848983 | CG24: =CG23/CF23-1 -> 0.16985129 | CH24: =CH23/CG23-1 -> 0.093388727 | CI24: =CI23/CH23-1 -> 0.098422971 | CJ24: =CJ23/CI23-1 -> 0.09263421 | CK24: =CK23/CJ23-1 -> 0.09263421 | CL24: =CL23/CK23-1 -> 0.09263421 | ... CP24: =CP23/CO23-1 -> 0.09263421 | CQ24: x
B25: % da Receita Líquida | C25: [%] | AB25: =AB23/AB$20 -> 0.78778238 | AC25: =AC23/AC$20 -> 0.78050674 | AD25: =AD23/AD$20 -> 0.79794696 | AE25: =AE23/AE$20 -> 0.75410613 | AF25: =AF23/AF$20 -> 0.75073824 | AG25: =AG23/AG$20 -> 0.69587584 | AH25: =AH23/AH$20 -> 0.45608005 | AI25: =AI23/AI$20 -> 0.48137674 | AJ25: =AJ23/AJ$20 -> 0.53442397 | AK25: =1-AK29-AK33-AK37 -> 0.53950358 | AL25: =1-AL29-AL33-AL37 -> 0.53950358 | AM25: =1-AM29-AM33-AM37 -> 0.53950358 | AN25: =1-AN29-AN33-AN37 -> 0.53950358 | AO25: =1-AO29-AO33-AO37 -> 0.53950358 | AP25: =1-AP29-AP33-AP37 -> 0.53950358 | AQ25: =1-AQ29-AQ33-AQ37 -> 0.53950358 | AR25: =1-AR29-AR33-AR37 -> 0.53950358 | ... BW25: =1-BW29-BW33-BW37 -> 0.53950358 | BX25: x | CE25: =CE23/CE$20 -> 0.77954556 | CF25: =CF23/CF$20 -> 0.55624586 | CG25: =CG23/CG$20 -> 0.53824778 | CH25: =CH23/CH$20 -> 0.53950358 | CI25: =CI23/CI$20 -> 0.53950358 | CJ25: =CJ23/CJ$20 -> 0.53950358 | CK25: =CK23/CK$20 -> 0.53950358 | CL25: =CL23/CL$20 -> 0.53950358 | ... CP25: =CP23/CP$20 -> 0.53950358 | CQ25: x
BX26: x | CQ26: x
B27: =Inputs!B316 -> Infraestrutura | C27: [BRL 000] | X27: =Inputs!Z316/1000 -> 0.095427 | Y27: =Inputs!AA316/1000 -> 18.902717 | Z27: =Inputs!AB316/1000 -> 73.998 | AA27: =Inputs!AC316/1000 -> 50.129099 | AB27: =Inputs!AD316/1000 -> 33.594 | AC27: =Inputs!AE316/1000 -> 36.303978 | AD27: =Inputs!AF316/1000 -> 34.569031 | AE27: =Inputs!AG316/1000 -> 43.604203 | ... AJ27: =Inputs!AL316/1000 -> 30.477155 | AK27: =AK$20*AK29 -> 35.45325 | AL27: =AL$20*AL29 -> 35.918181 | AM27: =AM$20*AM29 -> 40.938174 | AN27: =AN$20*AN29 -> 38.494945 | AO27: =AO$20*AO29 -> 38.523919 | AP27: =AP$20*AP29 -> 40.218972 | AQ27: =AQ$20*AQ29 -> 45.509592 | AR27: =AR$20*AR29 -> 42.582731 | ... BW27: =BW$20*BW29 -> 92.448804 | BX27: x | BY27: =SUM(D27:G27) -> 0 | BZ27: =SUM(H27:K27) -> 0 | CA27: =SUM(L27:O27) -> 0 | CB27: =SUM(P27:S27) -> 0 | CC27: =SUM(T27:W27) -> 0 | CD27: =SUM(X27:AA27) -> 143.12524 | CE27: =SUM(AB27:AE27) -> 148.07121 | CF27: =SUM(AF27:AI27) -> 157.80389 | CG27: =SUM(AJ27:AM27) -> 142.78676 | CH27: =SUM(AN27:AQ27) -> 162.74743 | CI27: =SUM(AR27:AU27) -> 178.76551 | CJ27: =SUM(AV27:AY27) -> 195.32532 | CK27: =SUM(AZ27:BC27) -> 213.41912 | CL27: =SUM(BD27:BG27) -> 233.18903 | CM27: =SUM(BH27:BK27) -> 254.79032 | CN27: =SUM(BL27:BO27) -> 278.39262 | CO27: =SUM(BP27:BS27) -> 304.1813 | CP27: =SUM(BT27:BW27) -> 332.35889 | CQ27: x | CT27: =(CF27/CD27)^(1/2)-1 -> 0.050027642 | CU27: =(CH27/CE27)^(1/3)-1 -> 0.032003494 | CV27: =(CJ27/CF27)^(1/4)-1 -> 0.054775925 | CW27: =(CJ27/CG27)^(1/3)-1 -> 0.11008661
B28: a/a % | C28: [%] | AB28: =AB27/X27-1 -> 351.03873 | AC28: =AC27/Y27-1 -> 0.9205693 | AD28: =AD27/Z27-1 -> -0.53283831 | AE28: =AE27/AA27-1 -> -0.13016184 | AF28: =AF27/AB27-1 -> -0.093913986 | AG28: =AG27/AC27-1 -> -0.088717095 | AH28: =AH27/AD27-1 -> 0.11818432 | AI28: =AI27/AE27-1 -> 0.27572776 | ... BW28: =BW27/BS27-1 -> 0.09263421 | BX28: x | CE28: =CE27/CD27-1 -> 0.034556931 | CF28: =CF27/CE27-1 -> 0.065729701 | CG28: =CG27/CF27-1 -> -0.095163237 | CH28: =CH27/CG27-1 -> 0.13979355 | CI28: =CI27/CH27-1 -> 0.098422971 | CJ28: =CJ27/CI27-1 -> 0.09263421 | CK28: =CK27/CJ27-1 -> 0.09263421 | CL28: =CL27/CK27-1 -> 0.09263421 | ... CP28: =CP27/CO27-1 -> 0.09263421 | CQ28: x
B29: % da Receita Líquida | C29: [%] | AB29: =AB27/AB$20 -> 0.13924278 | AC29: =AC27/AC$20 -> 0.14296591 | AD29: =AD27/AD$20 -> 0.12853019 | AE29: =AE27/AE$20 -> 0.15448347 | AF29: =AF27/AF$20 -> 0.14064085 | AG29: =AG27/AG$20 -> 0.16117653 | AH29: =AH27/AH$20 -> 0.098438734 | AI29: =AI27/AI$20 -> 0.13254249 | AJ29: =AJ27/AJ$20 -> 0.082628648 | AK29: 0.1 | AL29: 0.1 | AM29: 0.1 | AN29: 0.1 | AO29: 0.1 | AP29: 0.1 | AQ29: 0.1 | AR29: 0.1 | AS29: 0.1 | AT29: 0.1 | AU29: 0.1 | AV29: 0.1 | AW29: 0.1 | AX29: 0.1 | AY29: 0.1 | AZ29: 0.1 | BA29: 0.1 | BB29: 0.1 | BC29: 0.1 | BD29: 0.1 | BE29: 0.1 | BF29: 0.1 | BG29: 0.1 | BH29: 0.1 | BI29: 0.1 | BJ29: 0.1 | BK29: 0.1 | BL29: 0.1 | BM29: 0.1 | BN29: 0.1 | BO29: 0.1 | BP29: 0.1 | BQ29: 0.1 | BR29: 0.1 | BS29: 0.1 | BT29: 0.1 | BU29: 0.1 | BV29: 0.1 | BW29: 0.1 | BX29: x | CE29: =CE27/CE$20 -> 0.14150386 | CF29: =CF27/CF$20 -> 0.12787371 | CG29: =CG27/CG$20 -> 0.09570537 | CH29: =CH27/CH$20 -> 0.1 | CI29: =CI27/CI$20 -> 0.1 | CJ29: =CJ27/CJ$20 -> 0.1 | CK29: =CK27/CK$20 -> 0.1 | CL29: =CL27/CL$20 -> 0.1 | ... CP29: =CP27/CP$20 -> 0.1 | CQ29: x
BX30: x | CQ30: x
B31: =Inputs!B317 -> Engenharia de Integridade e Inspeção | C31: [BRL 000] | X31: =Inputs!Z317/1000 -> 6.203014 | Y31: =Inputs!AA317/1000 -> 11.666569 | Z31: =Inputs!AB317/1000 -> 12.298 | AA31: =Inputs!AC317/1000 -> 20.543072 | AB31: =Inputs!AD317/1000 -> 17.606 | AC31: =Inputs!AE317/1000 -> 19.432719 | AD31: =Inputs!AF317/1000 -> 19.774975 | AE31: =Inputs!AG317/1000 -> 25.800374 | ... AJ31: =Inputs!AL317/1000 -> 43.321189 | AK31: =AK$20*AK33 -> 33.680588 | AL31: =AL$20*AL33 -> 34.122272 | AM31: =AM$20*AM33 -> 38.891266 | AN31: =AN$20*AN33 -> 36.570198 | AO31: =AO$20*AO33 -> 36.597723 | AP31: =AP$20*AP33 -> 38.208023 | AQ31: =AQ$20*AQ33 -> 43.234113 | AR31: =AR$20*AR33 -> 40.453594 | ... BW31: =BW$20*BW33 -> 87.826364 | BX31: x | BY31: =SUM(D31:G31) -> 0 | BZ31: =SUM(H31:K31) -> 0 | CA31: =SUM(L31:O31) -> 0 | CB31: =SUM(P31:S31) -> 0 | CC31: =SUM(T31:W31) -> 0 | CD31: =SUM(X31:AA31) -> 50.710655 | CE31: =SUM(AB31:AE31) -> 82.614068 | CF31: =SUM(AF31:AI31) -> 131.14673 | CG31: =SUM(AJ31:AM31) -> 150.01531 | CH31: =SUM(AN31:AQ31) -> 154.61006 | CI31: =SUM(AR31:AU31) -> 169.82724 | CJ31: =SUM(AV31:AY31) -> 185.55905 | CK31: =SUM(AZ31:BC31) -> 202.74817 | CL31: =SUM(BD31:BG31) -> 221.52958 | CM31: =SUM(BH31:BK31) -> 242.0508 | CN31: =SUM(BL31:BO31) -> 264.47299 | CO31: =SUM(BP31:BS31) -> 288.97223 | CP31: =SUM(BT31:BW31) -> 315.74095 | CQ31: x | CT31: =(CF31/CD31)^(1/2)-1 -> 0.60815952 | CU31: =(CH31/CE31)^(1/3)-1 -> 0.23233253 | CV31: =(CJ31/CF31)^(1/4)-1 -> 0.090639361 | CW31: =(CJ31/CG31)^(1/3)-1 -> 0.073450893
B32: a/a % | C32: [%] | AB32: =AB31/X31-1 -> 1.8382976 | AC32: =AC31/Y31-1 -> 0.66567557 | AD32: =AD31/Z31-1 -> 0.60798301 | AE32: =AE31/AA31-1 -> 0.25591605 | AF32: =AF31/AB31-1 -> 0.33525379 | AG32: =AG31/AC31-1 -> 0.50989333 | AH32: =AH31/AD31-1 -> 1.0962178 | AI32: =AI31/AE31-1 -> 0.42805168 | ... BW32: =BW31/BS31-1 -> 0.09263421 | BX32: x | CE32: =CE31/CD31-1 -> 0.62912642 | CF32: =CF31/CE31-1 -> 0.58746247 | CG32: =CG31/CF31-1 -> 0.14387383 | CH32: =CH31/CG31-1 -> 0.030628491 | CI32: =CI31/CH31-1 -> 0.098422971 | CJ32: =CJ31/CI31-1 -> 0.09263421 | CK32: =CK31/CJ31-1 -> 0.09263421 | CL32: =CL31/CK31-1 -> 0.09263421 | ... CP32: =CP31/CO31-1 -> 0.09263421 | CQ32: x
B33: % da Receita Líquida | C33: [%] | AB33: =AB31/AB$20 -> 0.07297459 | AC33: =AC31/AC$20 -> 0.076526498 | AD33: =AD31/AD$20 -> 0.073524807 | AE33: =AE31/AE$20 -> 0.091407044 | AF33: =AF31/AF$20 -> 0.10861876 | AG33: =AG31/AG$20 -> 0.14294672 | AH33: =AH31/AH$20 -> 0.10556447 | AI33: =AI31/AI$20 -> 0.087788716 | AJ33: =AJ31/AJ$20 -> 0.11745097 | AK33: 0.095 | AL33: 0.095 | AM33: 0.095 | AN33: 0.095 | AO33: 0.095 | AP33: 0.095 | AQ33: 0.095 | AR33: 0.095 | AS33: 0.095 | AT33: 0.095 | AU33: 0.095 | AV33: 0.095 | AW33: 0.095 | AX33: 0.095 | AY33: 0.095 | AZ33: 0.095 | BA33: 0.095 | BB33: 0.095 | BC33: 0.095 | BD33: 0.095 | BE33: 0.095 | BF33: 0.095 | BG33: 0.095 | BH33: 0.095 | BI33: 0.095 | BJ33: 0.095 | BK33: 0.095 | BL33: 0.095 | BM33: 0.095 | BN33: 0.095 | BO33: 0.095 | BP33: 0.095 | BQ33: 0.095 | BR33: 0.095 | BS33: 0.095 | BT33: 0.095 | BU33: 0.095 | BV33: 0.095 | BW33: 0.095 | BX33: x | CE33: =CE31/CE$20 -> 0.078949913 | CF33: =CF31/CF$20 -> 0.10627254 | CG33: =CG31/CG$20 -> 0.10055044 | CH33: =CH31/CH$20 -> 0.095 | CI33: =CI31/CI$20 -> 0.095 | CJ33: =CJ31/CJ$20 -> 0.095 | CK33: =CK31/CK$20 -> 0.095 | CL33: =CL31/CL$20 -> 0.095 | ... CP33: =CP31/CP$20 -> 0.095 | CQ33: x
BX34: x | CQ34: x
B35: Montagem | C35: [BRL 000] | AH35: =Inputs!AJ318/1000 -> 133.47722 | AI35: =Inputs!AK318/1000 -> 125.19094 | AJ35: =Inputs!AL318/1000 -> 97.926996 | AK35: =AK$20*AK37 -> 94.127108 | AL35: =AL$20*AL37 -> 95.361483 | AM35: =AM$20*AM37 -> 108.68939 | AN35: =AN$20*AN37 -> 102.2027 | AO35: =AO$20*AO37 -> 102.27962 | AP35: =AP$20*AP37 -> 106.77993 | AQ35: =AQ$20*AQ37 -> 120.82634 | AR35: =AR$20*AR37 -> 113.05562 | ... BW35: =BW$20*BW37 -> 245.44826 | BX35: x | BY35: =SUM(D35:G35) -> 0 | BZ35: =SUM(H35:K35) -> 0 | CA35: =SUM(L35:O35) -> 0 | CB35: =SUM(P35:S35) -> 0 | CC35: =SUM(T35:W35) -> 0 | CD35: =SUM(X35:AA35) -> 0 | CE35: =SUM(AB35:AE35) -> 0 | CF35: =SUM(AF35:AI35) -> 258.66816 | CG35: =SUM(AJ35:AM35) -> 396.10497 | CH35: =SUM(AN35:AQ35) -> 432.08859 | CI35: =SUM(AR35:AU35) -> 474.61603 | CJ35: =SUM(AV35:AY35) -> 518.58171 | CK35: =SUM(AZ35:BC35) -> 566.62012 | CL35: =SUM(BD35:BG35) -> 619.10853 | CM35: =SUM(BH35:BK35) -> 676.45916 | CN35: =SUM(BL35:BO35) -> 739.12242 | CO35: =SUM(BP35:BS35) -> 807.59044 | CP35: =SUM(BT35:BW35) -> 882.40094 | CQ35: x | CV35: =(CJ35/CF35)^(1/4)-1 -> 0.18992217 | CW35: =(CJ35/CG35)^(1/3)-1 -> 0.093962163
B36: a/a % | C36: [%] | BX36: x | CG36: =CG35/CF35-1 -> 0.53132482 | CH36: =CH35/CG35-1 -> 0.090843637 | CI36: =CI35/CH35-1 -> 0.098422971 | CJ36: =CJ35/CI35-1 -> 0.09263421 | CK36: =CK35/CJ35-1 -> 0.09263421 | CL36: =CL35/CK35-1 -> 0.09263421 | CM36: =CM35/CL35-1 -> 0.09263421 | CN36: =CN35/CM35-1 -> 0.09263421 | ... CP36: =CP35/CO35-1 -> 0.09263421 | CQ36: x
B37: % da Receita Líquida | C37: [%] | AH37: =AH35/AH$20 -> 0.33991675 | AI37: =AI35/AI$20 -> 0.29829205 | AJ37: =AJ35/AJ$20 -> 0.26549642 | AK37: =AJ37 -> 0.26549642 | AL37: =AK37 -> 0.26549642 | AM37: =AL37 -> 0.26549642 | AN37: =AM37 -> 0.26549642 | AO37: =AN37 -> 0.26549642 | AP37: =AO37 -> 0.26549642 | AQ37: =AP37 -> 0.26549642 | AR37: =AQ37 -> 0.26549642 | ... BW37: =BV37 -> 0.26549642 | BX37: x | CE37: =CE35/CE$20 -> 0 | CF37: =CF35/CF$20 -> 0.20960737 | CG37: =CG35/CG$20 -> 0.26549642 | CH37: =CH35/CH$20 -> 0.26549642 | CI37: =CI35/CI$20 -> 0.26549642 | CJ37: =CJ35/CJ$20 -> 0.26549642 | CK37: =CK35/CK$20 -> 0.26549642 | CL37: =CL35/CL$20 -> 0.26549642 | ... CP37: =CP35/CP$20 -> 0.26549642 | CQ37: x
BX38: x | CQ38: x
A39: l | B39: Dados Operacionais | BX39: x | CQ39: x
BX40: x | CQ40: x
B41: =Inputs!B278 -> Quantidade total de colaboradores (final de trimestre) | D41: =Inputs!F278 -> 2023 | E41: =Inputs!G278 -> 2046 | F41: =Inputs!H278 -> 2758 | G41: =Inputs!I278 -> 2598 | H41: =Inputs!J278 -> 3202 | I41: =Inputs!K278 -> 3316 | J41: =Inputs!L278 -> 3177 | K41: =Inputs!M278 -> 3111 | ... AJ41: =Inputs!AL278 -> 6967 | AK41: =6602 -> 6602 | AL41: =AK41*(1+AL42) -> 6701.03 | AM41: =AL41*(1+AM42) -> 6801.5454 | AN41: =AM41*(1+AN42) -> 6903.5686 | AO41: =AN41*(1+AO42) -> 7007.1222 | AP41: =AO41*(1+AP42) -> 7112.229 | AQ41: =AP41*(1+AQ42) -> 7183.3513 | AR41: =AQ41*(1+AR42) -> 7255.1848 | AS41: =AR41*(1+AS42) -> 7327.7366 | ... BW41: =BV41*(1+BW42) -> 9876.6819 | BX41: x | BY41: =G41 -> 2598 | BZ41: =K41 -> 3111 | CA41: =O41 -> 2676 | CB41: =S41 -> 2199 | CC41: =W41 -> 3200 | CD41: =AA41 -> 5256 | CE41: =AE41 -> 5350 | CF41: =AI41 -> 6994 | CG41: =AM41 -> 6801.5454 | CH41: =AQ41 -> 7183.3513 | CI41: =AU41 -> 7475.0242 | CJ41: =AY41 -> 7778.5401 | CK41: =BC41 -> 8094.38 | CL41: =BG41 -> 8423.0443 | CM41: =BK41 -> 8765.0537 | CN41: =BO41 -> 9120.95 | CO41: =BS41 -> 9491.2972 | CP41: =BW41 -> 9876.6819 | CQ41: x
B42: a/a % | H42: =H41/D41-1 -> 0.58279782 | I42: =I41/E41-1 -> 0.62072336 | J42: =J41/F41-1 -> 0.15192168 | K42: =K41/G41-1 -> 0.19745958 | L42: =L41/H41-1 -> 0.064334791 | M42: =M41/I41-1 -> -0.10283474 | N42: =N41/J41-1 -> -0.084985836 | O42: =O41/K41-1 -> -0.13982642 | ... AJ42: =AJ41/AF41-1 -> 0.57838695 | AK42: 0.01 | AL42: 0.015 | AM42: 0.015 | AN42: 0.015 | AO42: 0.015 | AP42: 0.015 | AQ42: 0.01 | AR42: 0.01 | AS42: 0.01 | AT42: 0.01 | AU42: 0.01 | AV42: 0.01 | AW42: 0.01 | AX42: 0.01 | AY42: 0.01 | AZ42: 0.01 | BA42: 0.01 | BB42: 0.01 | BC42: 0.01 | BD42: 0.01 | BE42: 0.01 | BF42: 0.01 | BG42: 0.01 | BH42: 0.01 | BI42: 0.01 | BJ42: 0.01 | BK42: 0.01 | BL42: 0.01 | BM42: 0.01 | BN42: 0.01 | BO42: 0.01 | BP42: 0.01 | BQ42: 0.01 | BR42: 0.01 | BS42: 0.01 | BT42: 0.01 | BU42: 0.01 | BV42: 0.01 | BW42: 0.01 | BX42: x | BZ42: =BZ41/BY41-1 -> 0.19745958 | CA42: =CA41/BZ41-1 -> -0.13982642 | CB42: =CB41/CA41-1 -> -0.17825112 | CC42: =CC41/CB41-1 -> 0.45520691 | CD42: =CD41/CC41-1 -> 0.6425 | CE42: =CE41/CD41-1 -> 0.017884323 | CF42: =CF41/CE41-1 -> 0.30728972 | CG42: =CG41/CF41-1 -> -0.027517093 | ... CP42: =CP41/CO41-1 -> 0.04060401 | CQ42: x
BX43: x | CQ43: x
B44: =Inputs!B279 -> Quantidade total de colaboradores (média mensal do trimestre) | D44: =Inputs!F279 -> 2023 | E44: =Inputs!G279 -> 2034.5 | F44: =Inputs!H279 -> 2402 | G44: =Inputs!I279 -> 2678 | H44: =Inputs!J279 -> 2900 | I44: =Inputs!K279 -> 3259 | J44: =Inputs!L279 -> 3246.5 | K44: =Inputs!M279 -> 3144 | ... X44: =Inputs!Z279 -> 3558.3333 | Y44: =Inputs!AA280 -> 3995.5 | Z44: =Inputs!AB280 -> 4345.5 | AA44: =Inputs!AC280 -> 4907 | AB44: =Inputs!AD279 -> 5745.6667 | AC44: =Inputs!AE279 -> 5776.6667 | AD44: =Inputs!AF279 -> 5832.3333 | AE44: =Inputs!AG279 -> 5567.3333 | AF44: =Inputs!AH279 -> 4281.3333 | AG44: =Inputs!AI279 -> 4632.6667 | AH44: =Inputs!AJ279 -> 7276 | AI44: =Inputs!AK279 -> 7302 | AJ44: =Inputs!AL279 -> 6927 | AK44: =6753 -> 6753 | AL44: =(AL41+AK41)/2 -> 6651.515 | AM44: =(AM41+AL41)/2 -> 6751.2877 | AN44: =(AN41+AM41)/2 -> 6852.557 | AO44: =(AO41+AN41)/2 -> 6955.3454 | AP44: =(AP41+AO41)/2 -> 7059.6756 | AQ44: =(AQ41+AP41)/2 -> 7147.7901 | AR44: =(AR41+AQ41)/2 -> 7219.268 | AS44: =(AS41+AR41)/2 -> 7291.4607 | ... BW44: =(BW41+BV41)/2 -> 9827.7874 | BX44: x | BY44: =AVERAGE(G44,D44) -> 2350.5 | BZ44: =AVERAGE(H44:K44) -> 3137.375 | CA44: =AVERAGE(L44:O44) -> 3045.875 | CB44: =AVERAGE(P44:S44) -> 2044.0833 | CC44: =AVERAGE(T44:W44) -> 2962.1667 | CD44: =AVERAGE(X44:AA44) -> 4201.5833 | CE44: =AVERAGE(AB44:AE44) -> 5730.5 | CF44: =AI44 -> 7302 | CG44: =AM44 -> 6751.2877 | CH44: =AQ44 -> 7147.7901 | CI44: =AU44 -> 7438.0191 | CJ44: =AY44 -> 7740.0325 | CK44: =BC44 -> 8054.3088 | CL44: =BG44 -> 8381.3461 | CM44: =BK44 -> 8721.6623 | CN44: =BO44 -> 9075.7968 | CO44: =BS44 -> 9444.3105 | CP44: =BW44 -> 9827.7874 | CQ44: x
B45: a/a % | H45: =H44/D44-1 -> 0.43351458 | I45: =I44/E44-1 -> 0.60186778 | J45: =J44/F44-1 -> 0.35158202 | K45: =K44/G44-1 -> 0.17401046 | L45: =L44/H44-1 -> 0.12396552 | M45: =M44/I44-1 -> -0.020711875 | N45: =N44/J44-1 -> -0.09410134 | O45: =O44/K44-1 -> -0.11211832 | ... BW45: =BW44/BS44-1 -> 0.04060401 | BX45: x | BZ45: =BZ44/BY44-1 -> 0.3347692 | CA45: =CA44/BZ44-1 -> -0.029164509 | CB45: =CB44/CA44-1 -> -0.32890111 | CC45: =CC44/CB44-1 -> 0.44914183 | CD45: =CD44/CC44-1 -> 0.41841557 | CE45: =CE44/CD44-1 -> 0.3638906 | CF45: =CF44/CE44-1 -> 0.27423436 | CG45: =CG44/CF44-1 -> -0.075419375 | ... CP45: =CP44/CO44-1 -> 0.04060401 | CQ45: x
BX46: x | CQ46: x
B47: =Inputs!B281 -> Receita Líquida per capita (R$ mil mensal per capita) | D47: =(D20/D44)*1000/3 -> 8.6162465 | E47: =(E20/E44)*1000/3 -> 8.8516425 | F47: =(F20/F44)*1000/3 -> 8.5205384 | G47: =(G20/G44)*1000/3 -> 8.5617376 | H47: =(H20/H44)*1000/3 -> 8.7466667 | I47: =(I20/I44)*1000/3 -> 8.6249361 | J47: =(J20/J44)*1000/3 -> 8.2020638 | K47: =(K20/K44)*1000/3 -> 9.2166031 | ... X47: =(X20/X44)*1000/3 -> 12.111287 | Y47: =Inputs!AA282/1000 -> 14.22736 | Z47: =Inputs!AB282/1000 -> 14.67251 | AA47: =Inputs!AC282/1000 -> 14.922966 | AB47: =(AB20/AB44)*1000/3 -> 13.996755 | AC47: =(AC20/AC44)*1000/3 -> 14.652886 | AD47: =(AD20/AD44)*1000/3 -> 15.371578 | AE47: =(AE20/AE44)*1000/3 -> 16.899656 | AF47: =(AF20/AF44)*1000/3 -> 16.850755 | AG47: =(AG20/AG44)*1000/3 -> 14.769076 | AH47: =(AH20/AH44)*1000/3 -> 17.989564 | AI47: =(AI20/AI44)*1000/3 -> 19.158793 | AJ47: =(AJ20/AJ44)*1000/3 -> 17.749141 | AK47: 17.5 | AL47: 18 | AM47: =AI47*(1+AM48) -> 20.212526 | AN47: =AJ47*(1+AN48) -> 18.725343 | AO47: =AK47*(1+AO48) -> 18.4625 | AP47: =AL47*(1+AP48) -> 18.99 | AQ47: =AM47*(1+AQ48) -> 21.223153 | AR47: =AN47*(1+AR48) -> 19.66161 | AS47: =AO47*(1+AS48) -> 19.385625 | AT47: =AP47*(1+AT48) -> 19.9395 | ... BW47: =BS47*(1+BW48) -> 31.356262 | BX47: x | BY47: =AVERAGE(D47:G47) -> 8.6375413 | BZ47: =AVERAGE(H47:K47) -> 8.6975674 | CA47: =AVERAGE(L47:O47) -> 9.5762061 | CB47: =AVERAGE(P47:S47) -> 9.929012 | CC47: =AVERAGE(T47:W47) -> 12.098749 | CD47: =AVERAGE(X47:AA47) -> 13.983531 | CE47: =AVERAGE(AB47:AE47) -> 15.230219 | CF47: =AVERAGE(AF47:AI47) -> 17.192047 | CG47: =AVERAGE(AJ47:AM47) -> 18.365417 | CH47: =AVERAGE(AN47:AQ47) -> 19.350249 | CI47: =AVERAGE(AR47:AU47) -> 20.317761 | CJ47: =AVERAGE(AV47:AY47) -> 21.33365 | CK47: =AVERAGE(AZ47:BC47) -> 22.400332 | CL47: =AVERAGE(BD47:BG47) -> 23.520349 | CM47: =AVERAGE(BH47:BK47) -> 24.696366 | CN47: =AVERAGE(BL47:BO47) -> 25.931184 | CO47: =AVERAGE(BP47:BS47) -> 27.227744 | CP47: =AVERAGE(BT47:BW47) -> 28.589131 | CQ47: x
B48: a/a % | H48: =H47/D47-1 -> 0.015136541 | I48: =I47/E47-1 -> -0.025611792 | J48: =J47/F47-1 -> -0.037377295 | K48: =K47/G47-1 -> 0.076487445 | L48: =L47/H47-1 -> -0.030975123 | M48: =M47/I47-1 -> 0.11960057 | N48: =N47/J47-1 -> 0.1799332 | O48: =O47/K47-1 -> 0.13867507 | ... AL48: =AL47/AH47-1 -> 0.00058010969 | AM48: 0.055 | AN48: 0.055 | AO48: 0.055 | AP48: 0.055 | AQ48: 0.05 | AR48: 0.05 | AS48: 0.05 | AT48: 0.05 | AU48: 0.05 | AV48: 0.05 | AW48: 0.05 | AX48: 0.05 | AY48: 0.05 | AZ48: 0.05 | BA48: 0.05 | BB48: 0.05 | BC48: 0.05 | BD48: 0.05 | BE48: 0.05 | BF48: 0.05 | BG48: 0.05 | BH48: 0.05 | BI48: 0.05 | BJ48: 0.05 | BK48: 0.05 | BL48: 0.05 | BM48: 0.05 | BN48: 0.05 | BO48: 0.05 | BP48: 0.05 | BQ48: 0.05 | BR48: 0.05 | BS48: 0.05 | BT48: 0.05 | BU48: 0.05 | BV48: 0.05 | BW48: 0.05 | BX48: x | BZ48: =BZ47/BY47-1 -> 0.0069494459 | CA48: =CA47/BZ47-1 -> 0.1010212 | CB48: =CB47/CA47-1 -> 0.03684193 | CC48: =CC47/CB47-1 -> 0.21852497 | CD48: =CD47/CC47-1 -> 0.1557832 | CE48: =CE47/CD47-1 -> 0.089153998 | CF48: =CF47/CE47-1 -> 0.12881157 | CG48: =CG47/CF47-1 -> 0.068250729 | ... CP48: =CP47/CO47-1 -> 0.05 | CQ48: x
BX49: x | CQ49: x
B50: =Inputs!B319 -> Custo dos serviços prestados | D50: =Inputs!F142/1000 -> -39.486 | E50: =Inputs!G142/1000 -> -44.543 | F50: =Inputs!H142/1000 -> -57.243 | G50: =Inputs!I142/1000 -> -61.827 | H50: =Inputs!J142/1000 -> -65.521 | I50: =Inputs!K142/1000 -> -77.319 | J50: =Inputs!L142/1000 -> -70.948 | K50: =Inputs!M142/1000 -> -68.426 | ... W50: =Inputs!Y142/1000 -> -103.182 | X50: =+X56+X60+X64+X68 -> -103.76556 | Y50: =+Y56+Y60+Y64+Y68 -> -144.53664 | Z50: =+Z56+Z60+Z64+Z68 -> -176.368 | AA50: =+AA56+AA60+AA64+AA68 -> -190.2423 | AB50: =+AB56+AB60+AB64+AB68 -> -191.671 | AC50: =+AC56+AC60+AC64+AC68 -> -199.08161 | AD50: =+AD56+AD60+AD64+AD68 -> -217.44521 | AE50: =+AE56+AE60+AE64+AE68 -> -222.64139 | ... AJ50: =+AJ56+AJ60+AJ64+AJ68 -> -295.00508 | AK50: =AK56+AK60+AK64+AK68 -> -279.49002 | AL50: =AL56+AL60+AL64+AL68 -> -280.44507 | AM50: =AM56+AM60+AM64+AM68 -> -321.04799 | AN50: =AN56+AN60+AN64+AN68 -> -302.16683 | AO50: =AO56+AO60+AO64+AO68 -> -302.54252 | AP50: =AP56+AP60+AP64+AP68 -> -312.84841 | AQ50: =AQ56+AQ60+AQ64+AQ68 -> -355.33199 | AR50: =AR56+AR60+AR64+AR68 -> -333.26288 | ... BW50: =BW56+BW60+BW64+BW68 -> -720.599 | BX50: x | BY50: =SUM(D50:G50) -> -203.099 | BZ50: =SUM(H50:K50) -> -282.214 | CA50: =SUM(L50:O50) -> -299.585 | CB50: =SUM(P50:S50) -> -215.064 | CC50: =SUM(T50:W50) -> -362.687 | CD50: =SUM(X50:AA50) -> -614.9125 | CE50: =SUM(AB50:AE50) -> -830.83921 | CF50: =SUM(AF50:AI50) -> -960.46513 | CG50: =SUM(AJ50:AM50) -> -1175.9881 | CH50: =SUM(AN50:AQ50) -> -1272.8898 | CI50: =SUM(AR50:AU50) -> -1394.9603 | CJ50: =SUM(AV50:AY50) -> -1524.1814 | CK50: =SUM(AZ50:BC50) -> -1665.3727 | CL50: =SUM(BD50:BG50) -> -1819.6432 | CM50: =SUM(BH50:BK50) -> -1988.2044 | CN50: =SUM(BL50:BO50) -> -2172.3802 | CO50: =SUM(BP50:BS50) -> -2373.6169 | CP50: =SUM(BT50:BW50) -> -2593.495 | CQ50: x
B51: a/a % | H51: =H50/D50-1 -> 0.65934762 | I51: =I50/E50-1 -> 0.7358283 | J51: =J50/F50-1 -> 0.23941792 | K51: =K50/G50-1 -> 0.1067333 | L51: =L50/H50-1 -> 0.10422613 | M51: =M50/I50-1 -> 0.031686907 | N51: =N50/J50-1 -> 0.052122681 | O51: =O50/K50-1 -> 0.064215357 | ... BW51: =BW50/BS50-1 -> 0.09263421 | BX51: x | BZ51: =BZ50/BY50-1 -> 0.38953909 | CA51: =CA50/BZ50-1 -> 0.061552581 | CB51: =CB50/CA50-1 -> -0.28212694 | CC51: =CC50/CB50-1 -> 0.68641428 | CD51: =CD50/CC50-1 -> 0.69543574 | CE51: =CE50/CD50-1 -> 0.35115029 | CF51: =CF50/CE50-1 -> 0.15601806 | CG51: =CG50/CF50-1 -> 0.22439442 | ... CP51: =CP50/CO50-1 -> 0.09263421 | CQ51: x
BX52: x | CQ52: x
B53: =Inputs!B283 -> CPV per capita (R$ mil mensal per capita) | E53: =(E50/E44)*1000/3 -> -7.2979438 | F53: =(F50/F44)*1000/3 -> -7.9437968 | G53: =(G50/G44)*1000/3 -> -7.6956684 | H53: =(H50/H44)*1000/3 -> -7.5311494 | I53: =(I50/I44)*1000/3 -> -7.9082541 | J53: =(J50/J44)*1000/3 -> -7.2845629 | K53: =(K50/K44)*1000/3 -> -7.254665 | L53: =(L50/L44)*1000/3 -> -7.3988853 | ... X53: =(X50/X44)*1000/3 -> -9.7204274 | Y53: =Inputs!AA284/1000 -> -11.435577 | Z53: =Inputs!AB284/1000 -> -11.158763 | AA53: =Inputs!AC284/1000 -> -11.644168 | AB53: =(AB50/AB44)*1000/3 -> -11.119742 | AC53: =(AC50/AC44)*1000/3 -> -11.487686 | AD53: =(AD50/AD44)*1000/3 -> -12.427571 | AE53: =(AE50/AE44)*1000/3 -> -13.330223 | AF53: =(AF50/AF44)*1000/3 -> -13.462793 | AG53: =(AG50/AG44)*1000/3 -> -11.963731 | AH53: =(AH50/AH44)*1000/3 -> -13.919033 | AI53: =(AI50/AI44)*1000/3 -> -14.491575 | AJ53: =(AJ50/AJ44)*1000/3 -> -14.195904 | BX53: x | BY53: =AVERAGE(D53:G53) -> -7.645803 | BZ53: =AVERAGE(H53:K53) -> -7.4946578 | CA53: =AVERAGE(L53:O53) -> -8.2215296 | CB53: =AVERAGE(P53:S53) -> -8.8891676 | CC53: =AVERAGE(T53:W53) -> -10.13382 | CD53: =AVERAGE(X53:AA53) -> -10.989734 | CE53: =AVERAGE(AB53:AE53) -> -12.091306 | CF53: =AVERAGE(AF53:AI53) -> -13.459283 | CQ53: x
B54: a/a % | I54: =I53/E53-1 -> 0.083627701 | J54: =J53/F53-1 -> -0.082987265 | K54: =K53/G53-1 -> -0.057305411 | L54: =L53/H53-1 -> -0.017562275 | M54: =M53/I53-1 -> 0.053507013 | N54: =N53/J53-1 -> 0.16141322 | O54: =O53/K53-1 -> 0.19860042 | P54: =P53/L53-1 -> 0.066092302 | ... AJ54: =AJ53/AF53-1 -> 0.054454617 | BX54: x | BZ54: =BZ53/BY53-1 -> -0.019768386 | CA54: =CA53/BZ53-1 -> 0.096985323 | CB54: =CB53/CA53-1 -> 0.081206052 | CC54: =CC53/CB53-1 -> 0.14001896 | CD54: =CD53/CC53-1 -> 0.084461156 | CE54: =CE53/CD53-1 -> 0.10023647 | CF54: =CF53/CE53-1 -> 0.11313724 | CQ54: x
BX55: x | CQ55: x
B56: =B23 -> Serviços Industriais | C56: =C23 -> [BRL 000] | X56: =Inputs!Z320/1000 -> -98.305986 | Y56: =Inputs!AA320/1000 -> -125.96173 | Z56: =Inputs!AB320/1000 -> -131.703 | AA56: =Inputs!AC320/1000 -> -143.03996 | AB56: =Inputs!AD320/1000 -> -152.657 | AC56: =Inputs!AE320/1000 -> -160.61093 | AD56: =Inputs!AF320/1000 -> -179.04839 | AE56: =Inputs!AG320/1000 -> -175.07869 | ... AJ56: =Inputs!AL320/1000 -> -156.71901 | AK56: =AK23*(AK82-1) -> -155.88632 | AL56: =AL23*(AL82-1) -> -156.9617 | AM56: =AM23*(AM82-1) -> -178.89896 | AN56: =AN23*(AN82-1) -> -165.11633 | AO56: =AO23*(AO82-1) -> -169.38791 | AP56: =AP23*(AP82-1) -> -175.75606 | AQ56: =AQ23*(AQ82-1) -> -198.87596 | AR56: =AR23*(AR82-1) -> -182.65006 | ... BW56: =BW23*(BW82-1) -> -403.99934 | BX56: x | BY56: =SUM(D56:G56) -> 0 | BZ56: =SUM(H56:K56) -> 0 | CA56: =SUM(L56:O56) -> 0 | CB56: =SUM(P56:S56) -> 0 | CC56: =SUM(T56:W56) -> 0 | CD56: =SUM(X56:AA56) -> -499.01068 | CE56: =SUM(AB56:AE56) -> -667.395 | CF56: =SUM(AF56:AI56) -> -555.47106 | CG56: =SUM(AJ56:AM56) -> -648.46599 | CH56: =SUM(AN56:AQ56) -> -709.13626 | CI56: =SUM(AR56:AU56) -> -778.90985 | CJ56: =SUM(AV56:AY56) -> -851.06355 | CK56: =SUM(AZ56:BC56) -> -929.90115 | CL56: =SUM(BD56:BG56) -> -1016.0418 | CM56: =SUM(BH56:BK56) -> -1110.162 | CN56: =SUM(BL56:BO56) -> -1213.001 | CO56: =SUM(BP56:BS56) -> -1325.3664 | CP56: =SUM(BT56:BW56) -> -1448.1407 | CQ56: x
B57: =B24 -> a/a % | C57: =C24 -> [%] | AB57: =AB56/X56-1 -> 0.55287594 | AC57: =AC56/Y56-1 -> 0.27507717 | AD57: =AD56/Z56-1 -> 0.35948602 | AE57: =AE56/AA56-1 -> 0.22398444 | AF57: =AF56/AB56-1 -> -0.14301149 | AG57: =AG56/AC56-1 -> -0.2836457 | AH57: =AH56/AD56-1 -> -0.19405658 | AI57: =AI56/AE56-1 -> -0.055918428 | ... BW57: =BW56/BS56-1 -> 0.09263421 | BX57: x | CE57: =CE56/CD56-1 -> 0.33743631 | CF57: =CF56/CE56-1 -> -0.1677027 | CG57: =CG56/CF56-1 -> 0.16741634 | CH57: =CH56/CG56-1 -> 0.093559688 | CI57: =CI56/CH56-1 -> 0.098392351 | CJ57: =CJ56/CI56-1 -> 0.09263421 | CK57: =CK56/CJ56-1 -> 0.09263421 | CL57: =CL56/CK56-1 -> 0.09263421 | ... CP57: =CP56/CO56-1 -> 0.09263421 | CQ57: x
B58: % do CPV | C58: =C25 -> [%] | X58: =X56/X$50 -> 0.94738546 | Y58: =Y56/Y$50 -> 0.87148651 | Z58: =Z56/Z$50 -> 0.74675111 | AA58: =AA56/AA$50 -> 0.75188306 | AB58: =AB56/AB$50 -> 0.7964533 | AC58: =AC56/AC$50 -> 0.80675927 | AD58: =AD56/AD$50 -> 0.82341839 | AE58: =AE56/AE$50 -> 0.7863708 | ... BW58: =BW56/BW$50 -> 0.56064377 | BX58: x | CE58: =CE56/CE$50 -> 0.80327818 | CF58: =CF56/CF$50 -> 0.57833547 | CG58: =CG56/CG$50 -> 0.55142221 | CH58: =CH56/CH$50 -> 0.55710737 | CI58: =CI56/CI$50 -> 0.5583742 | CJ58: =CJ56/CJ$50 -> 0.5583742 | CK58: =CK56/CK$50 -> 0.5583742 | CL58: =CL56/CL$50 -> 0.5583742 | ... CP58: =CP56/CP$50 -> 0.5583742 | CQ58: x
BX59: x | CQ59: x
B60: =B27 -> Infraestrutura | C60: =C27 -> [BRL 000] | X60: =Inputs!Z321/1000 -> -0.500588 | Y60: =Inputs!AA321/1000 -> -10.710703 | Z60: =Inputs!AB321/1000 -> -36.028 | AA60: =Inputs!AC321/1000 -> -33.140624 | AB60: =Inputs!AD321/1000 -> -26.731 | AC60: =Inputs!AE321/1000 -> -24.322592 | AD60: =Inputs!AF321/1000 -> -23.844529 | AE60: =Inputs!AG321/1000 -> -28.544506 | ... AJ60: =Inputs!AL321/1000 -> -22.162878 | AK60: =AK27*(AK87-1) -> -24.584064 | AL60: =AL27*(AL87-1) -> -24.162479 | AM60: =AM27*(AM87-1) -> -26.931852 | AN60: =AN27*(AN87-1) -> -28.871209 | AO60: =AO27*(AO87-1) -> -26.581504 | AP60: =AP27*(AP87-1) -> -26.946711 | AQ60: =AQ27*(AQ87-1) -> -29.581235 | AR60: =AR27*(AR87-1) -> -31.511221 | ... BW60: =BW27*(BW87-1) -> -60.091723 | BX60: x | BY60: =SUM(D60:G60) -> 0 | BZ60: =SUM(H60:K60) -> 0 | CA60: =SUM(L60:O60) -> 0 | CB60: =SUM(P60:S60) -> 0 | CC60: =SUM(T60:W60) -> 0 | CD60: =SUM(X60:AA60) -> -80.379915 | CE60: =SUM(AB60:AE60) -> -103.44263 | CF60: =SUM(AF60:AI60) -> -102.90447 | CG60: =SUM(AJ60:AM60) -> -97.841272 | CH60: =SUM(AN60:AQ60) -> -111.98066 | CI60: =SUM(AR60:AU60) -> -122.17499 | CJ60: =SUM(AV60:AY60) -> -133.49257 | CK60: =SUM(AZ60:BC60) -> -145.85855 | CL60: =SUM(BD60:BG60) -> -159.37004 | CM60: =SUM(BH60:BK60) -> -174.13316 | CN60: =SUM(BL60:BO60) -> -190.26385 | CO60: =SUM(BP60:BS60) -> -207.88879 | CP60: =SUM(BT60:BW60) -> -227.1464 | CQ60: x
B61: =B28 -> a/a % | C61: =C28 -> [%] | AB61: =AB60/X60-1 -> 52.399203 | AC61: =AC60/Y60-1 -> 1.2708679 | AD61: =AD60/Z60-1 -> -0.33816674 | AE61: =AE60/AA60-1 -> -0.13868531 | AF61: =AF60/AB60-1 -> -0.073960645 | AG61: =AG60/AC60-1 -> 0.14755057 | AH61: =AH60/AD60-1 -> 0.062882677 | AI61: =AI60/AE60-1 -> -0.12784736 | ... BW61: =BW60/BS60-1 -> 0.09263421 | BX61: x | CE61: =CE60/CD60-1 -> 0.28692132 | CF61: =CF60/CE60-1 -> -0.0052025141 | CG61: =CG60/CF60-1 -> -0.049202847 | CH61: =CH60/CG60-1 -> 0.14451352 | CI61: =CI60/CH60-1 -> 0.09103652 | CJ61: =CJ60/CI60-1 -> 0.09263421 | CK61: =CK60/CJ60-1 -> 0.09263421 | CL61: =CL60/CK60-1 -> 0.09263421 | ... CP61: =CP60/CO60-1 -> 0.09263421 | CQ61: x
B62: % do CPV | C62: =C29 -> [%] | X62: =X60/X$50 -> 0.0048242209 | Y62: =Y60/Y$50 -> 0.074103721 | Z62: =Z60/Z$50 -> 0.20427742 | AA62: =AA60/AA$50 -> 0.17420219 | AB62: =AB60/AB$50 -> 0.13946293 | AC62: =AC60/AC$50 -> 0.12217398 | AD62: =AD60/AD$50 -> 0.10965764 | AE62: =AE60/AE$50 -> 0.12820845 | ... BW62: =BW60/BW$50 -> 0.083391349 | BX62: x | CE62: =CE60/CE$50 -> 0.12450379 | CF62: =CF60/CF$50 -> 0.10714024 | CG62: =CG60/CG$50 -> 0.083199199 | CH62: =CH60/CH$50 -> 0.087973573 | CI62: =CI60/CI$50 -> 0.087583128 | CJ62: =CJ60/CJ$50 -> 0.087583128 | CK62: =CK60/CK$50 -> 0.087583128 | CL62: =CL60/CL$50 -> 0.087583128 | ... CP62: =CP60/CP$50 -> 0.087583128 | CQ62: x
BX63: x | CQ63: x
B64: =B31 -> Engenharia de Integridade e Inspeção | C64: =C31 -> [BRL 000] | X64: =Inputs!Z322/1000 -> -4.958989 | Y64: =Inputs!AA322/1000 -> -7.864206 | Z64: =Inputs!AB322/1000 -> -8.637 | AA64: =Inputs!AC322/1000 -> -14.061713 | AB64: =Inputs!AD322/1000 -> -12.283 | AC64: =Inputs!AE322/1000 -> -14.148084 | AD64: =Inputs!AF322/1000 -> -14.552297 | AE64: =Inputs!AG322/1000 -> -19.018196 | ... AJ64: =Inputs!AL322/1000 -> -33.71523 | AK64: =AK31*(AK93-1) -> -24.65922 | AL64: =AL31*(AL93-1) -> -23.985323 | AM64: =AM31*(AM93-1) -> -29.352558 | AN64: =AN31*(AN93-1) -> -28.46119 | AO64: =AO31*(AO93-1) -> -26.794999 | AP64: =AP31*(AP93-1) -> -26.857291 | AQ64: =AQ31*(AQ93-1) -> -32.630252 | AR64: =AR31*(AR93-1) -> -31.48349 | ... BW64: =BW31*(BW93-1) -> -66.285537 | BX64: x | BY64: =SUM(D64:G64) -> 0 | BZ64: =SUM(H64:K64) -> 0 | CA64: =SUM(L64:O64) -> 0 | CB64: =SUM(P64:S64) -> 0 | CC64: =SUM(T64:W64) -> 0 | CD64: =SUM(X64:AA64) -> -35.521908 | CE64: =SUM(AB64:AE64) -> -60.001576 | CF64: =SUM(AF64:AI64) -> -99.483753 | CG64: =SUM(AJ64:AM64) -> -111.71233 | CH64: =SUM(AN64:AQ64) -> -114.74373 | CI64: =SUM(AR64:AU64) -> -126.04806 | CJ64: =SUM(AV64:AY64) -> -137.72443 | CK64: =SUM(AZ64:BC64) -> -150.48242 | CL64: =SUM(BD64:BG64) -> -164.42224 | CM64: =SUM(BH64:BK64) -> -179.65336 | CN64: =SUM(BL64:BO64) -> -196.29541 | CO64: =SUM(BP64:BS64) -> -214.47908 | CP64: =SUM(BT64:BW64) -> -234.34718 | CQ64: x
B65: =B32 -> a/a % | C65: =C32 -> [%] | AB65: =AB64/X64-1 -> 1.4769162 | AC65: =AC64/Y64-1 -> 0.79904797 | AD65: =AD64/Z64-1 -> 0.68487861 | AE65: =AE64/AA64-1 -> 0.3524807 | AF65: =AF64/AB64-1 -> 0.41145111 | AG65: =AG64/AC64-1 -> 0.64730406 | AH65: =AH64/AD64-1 -> 0.91012315 | AI65: =AI64/AE64-1 -> 0.63233279 | ... BW65: =BW64/BS64-1 -> 0.09263421 | BX65: x | CE65: =CE64/CD64-1 -> 0.68914282 | CF65: =CF64/CE64-1 -> 0.65801899 | CG65: =CG64/CF64-1 -> 0.12292035 | CH65: =CH64/CG64-1 -> 0.027135783 | CI65: =CI64/CH64-1 -> 0.098518075 | CJ65: =CJ64/CI64-1 -> 0.09263421 | CK65: =CK64/CJ64-1 -> 0.09263421 | CL65: =CL64/CK64-1 -> 0.09263421 | ... CP65: =CP64/CO64-1 -> 0.09263421 | CQ65: x
B66: % do CPV | C66: =C33 -> [%] | X66: =X64/X$50 -> 0.047790316 | Y66: =Y64/Y$50 -> 0.054409773 | Z66: =Z64/Z$50 -> 0.048971469 | AA66: =AA64/AA$50 -> 0.073914756 | AB66: =AB64/AB$50 -> 0.064083769 | AC66: =AC64/AC$50 -> 0.071066755 | AD66: =AD64/AD$50 -> 0.066923969 | AE66: =AE64/AE$50 -> 0.085420755 | ... BW66: =BW64/BW$50 -> 0.091986718 | BX66: x | CE66: =CE64/CE$50 -> 0.072218036 | CF66: =CF64/CF$50 -> 0.10357872 | CG66: =CG64/CG$50 -> 0.094994435 | CH66: =CH64/CH$50 -> 0.090144281 | CI66: =CI64/CI$50 -> 0.090359604 | CJ66: =CJ64/CJ$50 -> 0.090359604 | CK66: =CK64/CK$50 -> 0.090359604 | CL66: =CL64/CL$50 -> 0.090359604 | ... CP66: =CP64/CP$50 -> 0.090359604 | CQ66: x
BX67: x | CQ67: x
B68: =B35 -> Montagem | C68: =C35 -> [BRL 000] | AH68: =Inputs!AJ323/1000 -> -106.38116 | AI68: =Inputs!AK323/1000 -> -96.224695 | AJ68: =Inputs!AL323/1000 -> -82.407957 | AK68: =AK35*(AK98-1) -> -74.360415 | AL68: =AL35*(AL98-1) -> -75.335572 | AM68: =AM35*(AM98-1) -> -85.864614 | AN68: =AN35*(AN98-1) -> -79.718105 | AO68: =AO35*(AO98-1) -> -79.778107 | AP68: =AP35*(AP98-1) -> -83.288344 | AQ68: =AQ35*(AQ98-1) -> -94.244542 | AR68: =AR35*(AR98-1) -> -87.618108 | ... BW68: =BW35*(BW98-1) -> -190.2224 | BX68: x | BY68: =SUM(D68:G68) -> 0 | BZ68: =SUM(H68:K68) -> 0 | CA68: =SUM(L68:O68) -> 0 | CB68: =SUM(P68:S68) -> 0 | CC68: =SUM(T68:W68) -> 0 | CD68: =SUM(X68:AA68) -> 0 | CE68: =SUM(AB68:AE68) -> 0 | CF68: =SUM(AF68:AI68) -> -202.60586 | CG68: =SUM(AJ68:AM68) -> -317.96856 | CH68: =SUM(AN68:AQ68) -> -337.0291 | CI68: =SUM(AR68:AU68) -> -367.82742 | CJ68: =SUM(AV68:AY68) -> -401.90083 | CK68: =SUM(AZ68:BC68) -> -439.13059 | CL68: =SUM(BD68:BG68) -> -479.80911 | CM68: =SUM(BH68:BK68) -> -524.25585 | CN68: =SUM(BL68:BO68) -> -572.81987 | CO68: =SUM(BP68:BS68) -> -625.88259 | CP68: =SUM(BT68:BW68) -> -683.86073 | CQ68: x
B69: =B36 -> a/a % | C69: =C36 -> [%] | AL69: =AL68/AH68-1 -> -0.29183353 | AM69: =AM68/AI68-1 -> -0.10766551 | AN69: =AN68/AJ68-1 -> -0.032640682 | AO69: =AO68/AK68-1 -> 0.072857207 | AP69: =AP68/AL68-1 -> 0.10556464 | AQ69: =AQ68/AM68-1 -> 0.097594662 | AR69: =AR68/AN68-1 -> 0.099099237 | AS69: =AS68/AO68-1 -> 0.093684955 | ... BW69: =BW68/BS68-1 -> 0.09263421 | BX69: x | CG69: =CG68/CF68-1 -> 0.5693947 | CH69: =CH68/CG68-1 -> 0.059944734 | CI69: =CI68/CH68-1 -> 0.091381799 | CJ69: =CJ68/CI68-1 -> 0.09263421 | CK69: =CK68/CJ68-1 -> 0.09263421 | CL69: =CL68/CK68-1 -> 0.09263421 | CM69: =CM68/CL68-1 -> 0.09263421 | CN69: =CN68/CM68-1 -> 0.09263421 | ... CP69: =CP68/CO68-1 -> 0.09263421 | CQ69: x
B70: % do CPV | C70: =C37 -> [%] | AH70: =AH68/AH$50 -> 0.35014 | AI70: =AI68/AI$50 -> 0.3031153 | AJ70: =AJ68/AJ$50 -> 0.2793442 | AK70: =AK68/AK$50 -> 0.2660575 | AL70: =AL68/AL$50 -> 0.26862862 | AM70: =AM68/AM$50 -> 0.26745103 | AN70: =AN68/AN$50 -> 0.26382149 | AO70: =AO68/AO$50 -> 0.26369222 | ... BW70: =BW68/BW$50 -> 0.26397817 | BX70: x | CF70: =CF68/CF$50 -> 0.21094556 | CG70: =CG68/CG$50 -> 0.27038415 | CH70: =CH68/CH$50 -> 0.26477478 | CI70: =CI68/CI$50 -> 0.26368307 | CJ70: =CJ68/CJ$50 -> 0.26368307 | CK70: =CK68/CK$50 -> 0.26368307 | CL70: =CL68/CL$50 -> 0.26368307 | CM70: =CM68/CM$50 -> 0.26368307 | ... CP70: =CP68/CP$50 -> 0.26368307 | CQ70: x
BX71: x | CQ71: x
B72: =Inputs!B324 -> Lucro Bruto contábil consolidado | D72: =Inputs!F144/1000 -> 12.806 | E72: =Inputs!G144/1000 -> 9.483 | F72: =Inputs!H144/1000 -> 4.156 | G72: =Inputs!I144/1000 -> 6.958 | H72: =Inputs!J144/1000 -> 10.575 | I72: =Inputs!K144/1000 -> 7.007 | J72: =Inputs!L144/1000 -> 8.936 | K72: =Inputs!M144/1000 -> 18.505 | ... W72: =Inputs!Y144/1000 -> 16.411 | X72: =+X79+X84+X90+X95 -> 25.522255 | Y72: =+Y79+Y84+Y90+Y95 -> 39.405652 | Z72: =+Z79+Z84+Z90+Z95 -> 78.071 | AA72: =+AA79+AA84+AA90+AA95 -> 55.5827 | AB72: =+AB79+AB84+AB90+AB95 -> 49.591 | AC72: =+AC79+AC84+AC90+AC95 -> 54.852689 | AD72: =+AD79+AD84+AD90+AD95 -> 51.511818 | AE72: =+AE79+AE84+AE90+AE95 -> 59.615715 | ... AJ72: =+AJ79+AJ84+AJ90+AJ95 -> 73.839815 | AK72: =AK20+AK50 -> 75.042484 | AL72: =AL20+AL50 -> 78.736739 | AM72: =AM20+AM50 -> 88.333756 | AN72: =AN20+AN50 -> 82.782618 | AO72: =AO20+AO50 -> 82.696673 | AP72: =AP20+AP50 -> 89.341308 | AQ72: =AQ20+AQ50 -> 99.76393 | AR72: =AR20+AR50 -> 92.564426 | ... BW72: =BW20+BW50 -> 203.88904 | BX72: x | BY72: =SUM(D72:G72) -> 33.403 | BZ72: =SUM(H72:K72) -> 45.023 | CA72: =SUM(L72:O72) -> 49.027 | CB72: =SUM(P72:S72) -> 27.149 | CC72: =SUM(T72:W72) -> 70.454 | CD72: =SUM(X72:AA72) -> 198.58161 | CE72: =SUM(AB72:AE72) -> 215.57122 | CF72: =SUM(AF72:AI72) -> 273.59465 | CG72: =SUM(AJ72:AM72) -> 315.95279 | CH72: =SUM(AN72:AQ72) -> 354.58453 | CI72: =SUM(AR72:AU72) -> 392.69481 | CJ72: =SUM(AV72:AY72) -> 429.07179 | CK72: =SUM(AZ72:BC72) -> 468.81852 | CL72: =SUM(BD72:BG72) -> 512.24715 | CM72: =SUM(BH72:BK72) -> 559.69876 | CN72: =SUM(BL72:BO72) -> 611.54601 | CO72: =SUM(BP72:BS72) -> 668.19609 | CP72: =SUM(BT72:BW72) -> 730.09391 | CQ72: x | CR72: =(CF72/BY72)^(1/7)-1 -> 0.35043781 | CS72: =(CE72/CA72)^(1/4)-1 -> 0.4480677 | CT72: =(CF72/CD72)^(1/2)-1 -> 0.17377348 | CU72: =(CH72/CE72)^(1/3)-1 -> 0.18043751 | CV72: =(CJ72/CF72)^(1/4)-1 -> 0.11906571 | CW72: =(CJ72/CG72)^(1/3)-1 -> 0.10739507 | CY72: =(CF72/BY72)^(1/7)-1 -> 0.35043781
B73: a/a % | H73: =H72/D72-1 -> -0.17421521 | I73: =I72/E72-1 -> -0.26109881 | J73: =J72/F72-1 -> 1.1501444 | K73: =K72/G72-1 -> 1.6595286 | L73: =L72/H72-1 -> -0.0042553191 | M73: =M72/I72-1 -> 0.81061795 | N73: =N72/J72-1 -> 0.20210385 | O73: =O72/K72-1 -> -0.18573359 | ... BW73: =BW72/BS72-1 -> 0.09263421 | BX73: x | BZ73: =BZ72/BY72-1 -> 0.34787295 | CA73: =CA72/BZ72-1 -> 0.088932323 | CB73: =CB72/CA72-1 -> -0.44624391 | CC73: =CC72/CB72-1 -> 1.5950864 | CD73: =CD72/CC72-1 -> 1.8185995 | CE73: =CE72/CD72-1 -> 0.085554822 | CF73: =CF72/CE72-1 -> 0.26916131 | CG73: =CG72/CF72-1 -> 0.15482079 | ... CP73: =CP72/CO72-1 -> 0.09263421 | CQ73: x
B74: Margem Bruta Consolidada | D74: =D72/D$20 -> 0.24489406 | E74: =E72/E$20 -> 0.1755266 | F74: =F72/F$20 -> 0.067688399 | G74: =G72/G$20 -> 0.10115578 | H74: =H72/H$20 -> 0.1389692 | I74: =I72/I$20 -> 0.083094182 | J74: =J72/J$20 -> 0.1118622 | K74: =K72/K$20 -> 0.21286998 | ... BW74: =BW72/BW$20 -> 0.22054265 | BX74: x | BY74: =BY72/BY$20 -> 0.14123771 | BZ74: =BZ72/BZ$20 -> 0.1375853 | CA74: =CA72/CA$20 -> 0.14063486 | CB74: =CB72/CB$20 -> 0.1120873 | CC74: =CC72/CC$20 -> 0.16265835 | CD74: =CD72/CD$20 -> 0.24410934 | CE74: =CE72/CE$20 -> 0.20601006 | CF74: =CF72/CF$20 -> 0.2217028 | ... CP74: =CP72/CP$20 -> 0.21967034 | CQ74: x
BX75: x | CQ75: x
B76: =Inputs!B285 -> Lucro Bruto per capita (R$ mil mensal per capita) | E76: =(E72/E44)*1000/3 -> 1.5536987 | F76: =(F72/F44)*1000/3 -> 0.5767416 | G76: =(G72/G44)*1000/3 -> 0.86606921 | H76: =(H72/H44)*1000/3 -> 1.2155172 | I76: =(I72/I44)*1000/3 -> 0.71668201 | J76: =(J72/J44)*1000/3 -> 0.9175009 | K76: =(K72/K44)*1000/3 -> 1.9619381 | L76: =(L72/L44)*1000/3 -> 1.0768523 | ... X76: =(X72/X44)*1000/3 -> 2.3908436 | Y76: =Inputs!AA286/1000 -> 2.791783 | Z76: =Inputs!AB286/1000 -> 3.5137477 | AA76: =Inputs!AC286/1000 -> 3.2787987 | AB76: =(AB72/AB44)*1000/3 -> 2.8770088 | AC76: =(AC72/AC44)*1000/3 -> 3.1651869 | AD76: =(AD72/AD44)*1000/3 -> 2.9440371 | AE76: =(AE72/AE44)*1000/3 -> 3.5693758 | AF76: =(AF72/AF44)*1000/3 -> 3.3879264 | AG76: =(AG72/AG44)*1000/3 -> 2.8053319 | AH76: =(AH72/AH44)*1000/3 -> 4.0705314 | AI76: =(AI72/AI44)*1000/3 -> 4.6672175 | AJ76: =(AJ72/AJ44)*1000/3 -> 3.5532368 | AK76: =(AK72/7258)*1000/3 -> 3.4464262 | AL76: =(AL72/7258)*1000/3 -> 3.6160898 | AM76: =(AM72/7258)*1000/3 -> 4.0568456 | AN76: =(AN72/7258)*1000/3 -> 3.8019022 | AO76: =(AO72/7258)*1000/3 -> 3.797955 | AP76: =(AP72/7258)*1000/3 -> 4.1031188 | AQ76: =(AQ72/7258)*1000/3 -> 4.5817916 | AR76: =(AR72/7258)*1000/3 -> 4.2511448 | ... BW76: =(BW72/7258)*1000/3 -> 9.3638764 | BX76: x | BY76: =AVERAGE(D76:G76) -> 0.9988365 | BZ76: =AVERAGE(H76:K76) -> 1.2029096 | CA76: =AVERAGE(L76:O76) -> 1.3546765 | CB76: =AVERAGE(P76:S76) -> 1.0398444 | CC76: =AVERAGE(T76:W76) -> 1.9649295 | CD76: =AVERAGE(X76:AA76) -> 2.9937932 | CE76: =AVERAGE(AB76:AE76) -> 3.1389021 | CF76: =AVERAGE(AF76:AI76) -> 3.7327518 | CG76: =AVERAGE(AJ76:AM76) -> 3.6681496 | CH76: =AVERAGE(AN76:AQ76) -> 4.0711919 | CI76: =AVERAGE(AR76:AU76) -> 4.5087583 | CJ76: =AVERAGE(AV76:AY76) -> 4.9264236 | CK76: =AVERAGE(AZ76:BC76) -> 5.3827789 | CL76: =AVERAGE(BD76:BG76) -> 5.8814084 | CM76: =AVERAGE(BH76:BK76) -> 6.4262281 | CN76: =AVERAGE(BL76:BO76) -> 7.0215166 | CO76: =AVERAGE(BP76:BS76) -> 7.6719493 | CP76: =AVERAGE(BT76:BW76) -> 8.3826342 | CQ76: x
B77: a/a % | I77: =I76/E76-1 -> -0.53872523 | J77: =J76/F76-1 -> 0.59083529 | K77: =K76/G76-1 -> 1.2653364 | L77: =L76/H76-1 -> -0.11407898 | M77: =M76/I76-1 -> 0.8489124 | N77: =N76/J76-1 -> 0.32697387 | O77: =O76/K76-1 -> -0.082911121 | P77: =P76/L76-1 -> 0.1176115 | ... BW77: =BW76/BS76-1 -> 0.09263421 | BX77: x | BZ77: =BZ76/BY76-1 -> 0.20431077 | CA77: =CA76/BZ76-1 -> 0.12616651 | CB77: =CB76/CA76-1 -> -0.23240386 | CC77: =CC76/CB76-1 -> 0.88963793 | CD77: =CD76/CC76-1 -> 0.5236136 | CE77: =CE76/CD76-1 -> 0.048469914 | CF77: =CF76/CE76-1 -> 0.18919023 | CG77: =CG76/CF76-1 -> -0.017306848 | ... CP77: =CP76/CO76-1 -> 0.09263421 | CQ77: x
BX78: x | CQ78: x
B79: =B56 -> Serviços Industriais | C79: =C56 -> [BRL 000] | X79: =Inputs!Z325/1000 -> 24.683391 | Y79: =Inputs!AA325/1000 -> 27.411275 | Z79: =Inputs!AB325/1000 -> 36.44 | AA79: =Inputs!AC325/1000 -> 32.112866 | AB79: =Inputs!AD325/1000 -> 37.405 | AC79: =Inputs!AE325/1000 -> 37.586667 | AD79: =Inputs!AF325/1000 -> 35.564637 | AE79: =Inputs!AG325/1000 -> 37.77384 | ... AJ79: =Inputs!AL325/1000 -> 40.40054 | AK79: =AK23*AK82 -> 35.385238 | AL79: =AL23*AL82 -> 36.818176 | AM79: =AM23*AM82 -> 41.963954 | AN79: =AN23*AN82 -> 42.565281 | AO79: =AO23*AO82 -> 38.450016 | AP79: =AP23*AP82 -> 41.226731 | AQ79: =AQ23*AQ82 -> 46.649918 | AR79: =AR23*AR82 -> 47.085297 | ... BW79: =BW23*BW82 -> 94.765277 | BX79: x | BY79: =SUM(D79:G79) -> 0 | BZ79: =SUM(H79:K79) -> 0 | CA79: =SUM(L79:O79) -> 0 | CB79: =SUM(P79:S79) -> 0 | CC79: =SUM(T79:W79) -> 0 | CD79: =SUM(X79:AA79) -> 120.64753 | CE79: =SUM(AB79:AE79) -> 148.33014 | CF79: =SUM(AF79:AI79) -> 130.96995 | CG79: =SUM(AJ79:AM79) -> 154.56791 | CH79: =SUM(AN79:AQ79) -> 168.89195 | CI79: =SUM(AR79:AU79) -> 185.53651 | CJ79: =SUM(AV79:AY79) -> 202.72354 | CK79: =SUM(AZ79:BC79) -> 221.50267 | CL79: =SUM(BD79:BG79) -> 242.02139 | CM79: =SUM(BH79:BK79) -> 264.44086 | CN79: =SUM(BL79:BO79) -> 288.93713 | CO79: =SUM(BP79:BS79) -> 315.70259 | CP79: =SUM(BT79:BW79) -> 344.94745 | CQ79: x
B80: =B57 -> a/a % | C80: =C57 -> [%] | AB80: =AB79/X79-1 -> 0.51539146 | AC80: =AC79/Y79-1 -> 0.37121192 | AD80: =AD79/Z79-1 -> -0.024022043 | AE80: =AE79/AA79-1 -> 0.17628367 | AF80: =AF79/AB79-1 -> -0.15364776 | AG80: =AG79/AC79-1 -> -0.26086624 | AH80: =AH79/AD79-1 -> -0.021811664 | AI80: =AI79/AE79-1 -> -0.027325416 | ... BW80: =BW79/BS79-1 -> 0.09263421 | BX80: x | CE80: =CE79/CD79-1 -> 0.22945029 | CF80: =CF79/CE79-1 -> -0.11703755 | CG80: =CG79/CF79-1 -> 0.18017844 | CH80: =CH79/CG79-1 -> 0.092671488 | CI80: =CI79/CH79-1 -> 0.098551541 | CJ80: =CJ79/CI79-1 -> 0.09263421 | CK80: =CK79/CJ79-1 -> 0.09263421 | CL80: =CL79/CK79-1 -> 0.09263421 | ... CP80: =CP79/CO79-1 -> 0.09263421 | CQ80: x
B81: % da Receita Líquida | C81: =C58 -> [%] | X81: =X79/X$20 -> 0.1909179 | Y81: =Y79/Y$20 -> 0.14902135 | Z81: =Z79/Z$20 -> 0.14321679 | AA81: =AA79/AA$20 -> 0.13063296 | AB81: =AB79/AB$20 -> 0.15503888 | AC81: =AC79/AC$20 -> 0.14801717 | AD81: =AD79/AD$20 -> 0.13223193 | AE81: =AE79/AE$20 -> 0.13382733 | ... BW81: =BW79/BW$20 -> 0.10250568 | BX81: x | CE81: =CE79/CE$20 -> 0.14175131 | CF81: =CF79/CF$20 -> 0.10612928 | CG81: =CG79/CG$20 -> 0.10360189 | CH81: =CH79/CH$20 -> 0.10377549 | CI81: =CI79/CI$20 -> 0.10378764 | CJ81: =CJ79/CJ$20 -> 0.10378764 | CK81: =CK79/CK$20 -> 0.10378764 | CL81: =CL79/CL$20 -> 0.10378764 | ... CP81: =CP79/CP$20 -> 0.10378764 | CQ81: x
B82: Margem Bruta | C82: =C81 -> [%] | X82: =X79/X23 -> 0.20069531 | Y82: =Y79/Y23 -> 0.17872294 | Z82: =Z79/Z23 -> 0.21672029 | AA82: =AA79/AA23 -> 0.18334198 | AB82: =AB79/AB23 -> 0.1968042 | AC82: =AC79/AC23 -> 0.18964239 | AD82: =AD79/AD23 -> 0.16571518 | AE82: =AE79/AE23 -> 0.17746484 | ... AJ82: =AJ79/AJ23 -> 0.2049545 | AK82: 0.185 | AL82: 0.19 | AM82: 0.19 | AN82: =AJ82 -> 0.2049545 | AO82: =AK82 -> 0.185 | AP82: =AL82 -> 0.19 | AQ82: =AM82 -> 0.19 | AR82: =AN82 -> 0.2049545 | AS82: =AO82 -> 0.185 | AT82: =AP82 -> 0.19 | AU82: =AQ82 -> 0.19 | ... BW82: =BS82 -> 0.19 | BX82: x | CE82: =CE79/CE23 -> 0.18183839 | CF82: =CF79/CF23 -> 0.19079563 | CG82: =CG79/CG23 -> 0.19247993 | CH82: =CH79/CH23 -> 0.19235367 | CI82: =CI79/CI23 -> 0.19237618 | CJ82: =CJ79/CJ23 -> 0.19237618 | CK82: =CK79/CK23 -> 0.19237618 | CL82: =CL79/CL23 -> 0.19237618 | ... CP82: =CP79/CP23 -> 0.19237618 | CQ82: x
BX83: x | CQ83: x
B84: =B60 -> Infraestrutura | C84: =C60 -> [BRL 000] | X84: =Inputs!Z326/1000 -> -0.405161 | Y84: =Inputs!AA326/1000 -> 8.192014 | Z84: =Inputs!AB326/1000 -> 37.97 | AA84: =Inputs!AC326/1000 -> 16.988475 | AB84: =Inputs!AD326/1000 -> 6.863 | AC84: =Inputs!AE326/1000 -> 11.981386 | AD84: =Inputs!AF326/1000 -> 10.724502 | AE84: =Inputs!AG326/1000 -> 15.059697 | ... AJ84: =Inputs!AL326/1000 -> 8.3142764 | AK84: =AK$27*AK87 -> 10.869186 | AL84: =AL$27*AL87 -> 11.755702 | AM84: =AM$27*AM87 -> 14.006322 | AN84: =AN$27*AN87 -> 9.6237362 | AO84: =AO$27*AO87 -> 11.942415 | AP84: =AP$27*AP87 -> 13.272261 | AQ84: =AQ$27*AQ87 -> 15.928357 | AR84: =AR$27*AR87 -> 11.07151 | ... BW84: =BW$27*BW87 -> 32.357082 | BX84: x | BY84: =SUM(D84:G84) -> 0 | BZ84: =SUM(H84:K84) -> 0 | CA84: =SUM(L84:O84) -> 0 | CB84: =SUM(P84:S84) -> 0 | CC84: =SUM(T84:W84) -> 0 | CD84: =SUM(X84:AA84) -> 62.745328 | CE84: =SUM(AB84:AE84) -> 44.628585 | CF84: =SUM(AF84:AI84) -> 54.899425 | CG84: =SUM(AJ84:AM84) -> 44.945488 | CH84: =SUM(AN84:AQ84) -> 50.766769 | CI84: =SUM(AR84:AU84) -> 56.590525 | CJ84: =SUM(AV84:AY84) -> 61.832744 | CK84: =SUM(AZ84:BC84) -> 67.560571 | CL84: =SUM(BD84:BG84) -> 73.818991 | CM84: =SUM(BH84:BK84) -> 80.657155 | CN84: =SUM(BL84:BO84) -> 88.128767 | CO84: =SUM(BP84:BS84) -> 96.292506 | CP84: =SUM(BT84:BW84) -> 105.21249 | CQ84: x
B85: =B61 -> a/a % | C85: =C61 -> [%] | AB85: =AB84/X84-1 -> -17.938945 | AC85: =AC84/Y84-1 -> 0.46256908 | AD85: =AD84/Z84-1 -> -0.71755327 | AE85: =AE84/AA84-1 -> -0.11353452 | AF85: =AF84/AB84-1 -> -0.17163106 | AG85: =AG84/AC84-1 -> -0.56834787 | AH85: =AH84/AD84-1 -> 0.24114029 | AI85: =AI84/AE84-1 -> 1.0406736 | ... BW85: =BW84/BS84-1 -> 0.09263421 | BX85: x | CE85: =CE84/CD84-1 -> -0.28873453 | CF85: =CF84/CE84-1 -> 0.23014037 | CG85: =CG84/CF84-1 -> -0.18131223 | CH85: =CH84/CG84-1 -> 0.12951871 | CI85: =CI84/CH84-1 -> 0.11471591 | CJ85: =CJ84/CI84-1 -> 0.09263421 | CK85: =CK84/CJ84-1 -> 0.09263421 | CL85: =CL84/CK84-1 -> 0.09263421 | ... CP85: =CP84/CO84-1 -> 0.09263421 | CQ85: x
B86: % da Receita Líquida | C86: =C62 -> [%] | X86: =X84/X$20 -> -0.0031337869 | Y86: =Y84/Y$20 -> 0.044535871 | Z86: =Z84/Z$20 -> 0.14923001 | AA86: =AA84/AA$20 -> 0.069107965 | AB86: =AB84/AB$20 -> 0.028446246 | AC86: =AC84/AC$20 -> 0.047182977 | AD86: =AD84/AD$20 -> 0.039874486 | AE86: =AE84/AE$20 -> 0.053354357 | ... BW86: =BW84/BW$20 -> 0.035 | BX86: x | CE86: =CE84/CE$20 -> 0.042649189 | CF86: =CF84/CF$20 -> 0.04448682 | CG86: =CG84/CG$20 -> 0.030125514 | CH86: =CH84/CH$20 -> 0.031193592 | CI86: =CI84/CI$20 -> 0.031656288 | CJ86: =CJ84/CJ$20 -> 0.031656288 | CK86: =CK84/CK$20 -> 0.031656288 | CL86: =CL84/CL$20 -> 0.031656288 | ... CP86: =CP84/CP$20 -> 0.031656288 | CQ86: x
B87: Margem Bruta | C87: =C86 -> [%] | X87: =X84/X27 -> -4.245769 | Y87: =Y84/Y27 -> 0.43337759 | Z87: =Z84/Z27 -> 0.51312198 | AA87: =AA84/AA27 -> 0.33889448 | AB87: =AB84/AB27 -> 0.20429243 | AC87: =AC84/AC27 -> 0.33002957 | AD87: =AD84/AD27 -> 0.31023439 | AE87: =AE84/AE27 -> 0.34537259 | ... AJ87: =AJ84/AJ27 -> 0.27280356 | AK87: =AVERAGE(AG87,AC87,Y87) -> 0.306578 | AL87: =AVERAGE(AH87,AD87) -> 0.32729114 | AM87: =AVERAGE(AE87,AA87) -> 0.34213354 | AN87: 0.25 | AO87: 0.31 | AP87: 0.33 | AQ87: 0.35 | AR87: 0.26 | AS87: 0.315 | AT87: 0.335 | AU87: 0.35 | AV87: =AR87 -> 0.26 | AW87: =AS87 -> 0.315 | AX87: =AT87 -> 0.335 | AY87: =AU87 -> 0.35 | AZ87: =AV87 -> 0.26 | BA87: =AW87 -> 0.315 | BB87: =AX87 -> 0.335 | BC87: =AY87 -> 0.35 | ... BW87: =BS87 -> 0.35 | BX87: x | CE87: =CE84/CE27 -> 0.30139947 | CF87: =CF84/CF27 -> 0.34789653 | CG87: =CG84/CG27 -> 0.3147735 | CH87: =CH84/CH27 -> 0.31193592 | CI87: =CI84/CI27 -> 0.31656288 | CJ87: =CJ84/CJ27 -> 0.31656288 | CK87: =CK84/CK27 -> 0.31656288 | CL87: =CL84/CL27 -> 0.31656288 | ... CP87: =CP84/CP27 -> 0.31656288 | CQ87: x
B88: Diferença | AC88: =(AC87-Y87)*100 -> -10.334802 | AD88: =(AD87-Z87)*100 -> -20.288758 | AE88: =(AE87-AA87)*100 -> 0.64781117 | AF88: =(AF87-AB87)*100 -> -1.7522631 | AG88: =(AG87-AC87)*100 -> -17.370274 | AH88: =(AH87-AD87)*100 -> 3.411349 | AI88: =(AI87-AE87)*100 -> 20.709068 | AJ88: =(AJ87-AF87)*100 -> 8.6033761
BX89: x | CQ89: x
B90: =B64 -> Engenharia de Integridade e Inspeção | C90: =C64 -> [BRL 000] | X90: =Inputs!Z327/1000 -> 1.244025 | Y90: =Inputs!AA327/1000 -> 3.802363 | Z90: =Inputs!AB327/1000 -> 3.661 | AA90: =Inputs!AC327/1000 -> 6.481359 | AB90: =Inputs!AD327/1000 -> 5.323 | AC90: =Inputs!AE327/1000 -> 5.2846352 | AD90: =Inputs!AF327/1000 -> 5.2226784 | AE90: =Inputs!AG327/1000 -> 6.7821783 | ... AJ90: =Inputs!AL327/1000 -> 9.6059595 | AK90: =AK$31*AK93 -> 9.0213677 | AL90: =AL$31*AL93 -> 10.136949 | AM90: =AM$31*AM93 -> 9.5387079 | AN90: =AN$31*AN93 -> 8.1090072 | AO90: =AO$31*AO93 -> 9.8027245 | AP90: =AP$31*AP93 -> 11.350733 | AQ90: =AQ$31*AQ93 -> 10.603861 | AR90: =AR$31*AR93 -> 8.9701043 | ... BW90: =BW$31*BW93 -> 21.540827 | BX90: x | BY90: =SUM(D90:G90) -> 0 | BZ90: =SUM(H90:K90) -> 0 | CA90: =SUM(L90:O90) -> 0 | CB90: =SUM(P90:S90) -> 0 | CC90: =SUM(T90:W90) -> 0 | CD90: =SUM(X90:AA90) -> 15.188747 | CE90: =SUM(AB90:AE90) -> 22.612492 | CF90: =SUM(AF90:AI90) -> 31.66298 | CG90: =SUM(AJ90:AM90) -> 38.302984 | CH90: =SUM(AN90:AQ90) -> 39.866325 | CI90: =SUM(AR90:AU90) -> 43.779175 | CJ90: =SUM(AV90:AY90) -> 47.834624 | CK90: =SUM(AZ90:BC90) -> 52.265747 | CL90: =SUM(BD90:BG90) -> 57.107343 | CM90: =SUM(BH90:BK90) -> 62.397437 | CN90: =SUM(BL90:BO90) -> 68.177574 | CO90: =SUM(BP90:BS90) -> 74.49315 | CP90: =SUM(BT90:BW90) -> 81.393764 | CQ90: x
B91: =B65 -> a/a % | C91: =C65 -> [%] | AB91: =AB90/X90-1 -> 3.2788529 | AC91: =AC90/Y90-1 -> 0.38982921 | AD91: =AD90/Z90-1 -> 0.42657155 | AE91: =AE90/AA90-1 -> 0.046413 | AF91: =AF90/AB90-1 -> 0.15942598 | AG91: =AG90/AC90-1 -> 0.14201581 | AH91: =AH90/AD90-1 -> 1.6147456 | AI91: =AI90/AE90-1 -> -0.1447817 | ... BW91: =BW90/BS90-1 -> 0.09263421 | BX91: x | CE91: =CE90/CD90-1 -> 0.48876612 | CF91: =CF90/CE90-1 -> 0.40024283 | CG91: =CG90/CF90-1 -> 0.20970877 | CH91: =CH90/CG90-1 -> 0.040815126 | CI91: =CI90/CH90-1 -> 0.098149243 | CJ91: =CJ90/CI90-1 -> 0.09263421 | CK91: =CK90/CJ90-1 -> 0.09263421 | CL91: =CL90/CK90-1 -> 0.09263421 | ... CP91: =CP90/CO90-1 -> 0.09263421 | CQ91: x
B92: % da Receita Líquida | C92: =C66 -> [%] | X92: =X90/X$20 -> 0.0096221238 | Y92: =Y90/Y$20 -> 0.02067154 | Z92: =Z90/Z$20 -> 0.014388493 | AA92: =AA90/AA$20 -> 0.026365729 | AB92: =AB90/AB$20 -> 0.022063146 | AC92: =AC90/AC$20 -> 0.020811016 | AD92: =AD90/AD$20 -> 0.019418301 | AE92: =AE90/AE$20 -> 0.02402829 | ... BW92: =BW90/BW$20 -> 0.023300277 | BX92: x | CE92: =CE90/CE$20 -> 0.021609568 | CF92: =CF90/CF$20 -> 0.02565756 | CG92: =CG90/CG$20 -> 0.025673258 | CH92: =CH90/CH$20 -> 0.024495825 | CI92: =CI90/CI$20 -> 0.024489721 | CJ92: =CJ90/CJ$20 -> 0.024489721 | CK92: =CK90/CK$20 -> 0.024489721 | CL92: =CL90/CL$20 -> 0.024489721 | ... CP92: =CP90/CP$20 -> 0.024489721 | CQ92: x
B93: Margem Bruta | C93: =C92 -> [%] | X93: =X90/X31 -> 0.2005517 | Y93: =Y90/Y31 -> 0.32591956 | Z93: =Z90/Z31 -> 0.29769068 | AA93: =AA90/AA31 -> 0.31550096 | AB93: =AB90/AB31 -> 0.30234011 | AC93: =AC90/AC31 -> 0.27194523 | AD93: =AD90/AD31 -> 0.26410544 | AE93: =AE90/AE31 -> 0.26287132 | ... AJ93: =AJ90/AJ31 -> 0.22173813 | AK93: =AVERAGE(AG93,AC93,Y93) -> 0.26785066 | AL93: =AVERAGE(AH93,AD93,Z93) -> 0.2970772 | AM93: =AVERAGE(AI93,AE93,AA93) -> 0.24526607 | AN93: =AJ93 -> 0.22173813 | AO93: =AK93 -> 0.26785066 | AP93: =AL93 -> 0.2970772 | AQ93: =AM93 -> 0.24526607 | AR93: =AN93 -> 0.22173813 | AS93: =AO93 -> 0.26785066 | AT93: =AP93 -> 0.2970772 | AU93: =AQ93 -> 0.24526607 | ... BW93: =BS93 -> 0.24526607 | BX93: x | CE93: =CE90/CE31 -> 0.27371237 | CF93: =CF90/CF31 -> 0.24143171 | CG93: =CG90/CG31 -> 0.25532716 | CH93: =CH90/CH31 -> 0.25785079 | CI93: =CI90/CI31 -> 0.25778653 | CJ93: =CJ90/CJ31 -> 0.25778653 | CK93: =CK90/CK31 -> 0.25778653 | CL93: =CL90/CL31 -> 0.25778653 | ... CP93: =CP90/CP31 -> 0.25778653 | CQ93: x
BX94: x | CQ94: x
B95: =B68 -> Montagem | C95: =C68 -> [BRL 000] | AH95: =Inputs!AJ328/1000 -> 27.096059 | AI95: =Inputs!AK328/1000 -> 28.966243 | AJ95: =Inputs!AL328/1000 -> 15.519039 | AK95: =AK$35*AK98 -> 19.766693 | AL95: =AL$35*AL98 -> 20.025911 | AM95: =AM$35*AM98 -> 22.824771 | AN95: =AN$35*AN98 -> 22.484594 | AO95: =AO$35*AO98 -> 22.501517 | AP95: =AP$35*AP98 -> 23.491584 | AQ95: =AQ$35*AQ98 -> 26.581794 | AR95: =AR$35*AR98 -> 25.437515 | ... BW95: =BW$35*BW98 -> 55.225859 | BX95: x | BY95: =SUM(D95:G95) -> 0 | BZ95: =SUM(H95:K95) -> 0 | CA95: =SUM(L95:O95) -> 0 | CB95: =SUM(P95:S95) -> 0 | CC95: =SUM(T95:W95) -> 0 | CD95: =SUM(X95:AA95) -> 0 | CE95: =SUM(AB95:AE95) -> 0 | CF95: =SUM(AF95:AI95) -> 56.062302 | CG95: =SUM(AJ95:AM95) -> 78.136414 | CH95: =SUM(AN95:AQ95) -> 95.059489 | CI95: =SUM(AR95:AU95) -> 106.78861 | CJ95: =SUM(AV95:AY95) -> 116.68089 | CK95: =SUM(AZ95:BC95) -> 127.48953 | CL95: =SUM(BD95:BG95) -> 139.29942 | CM95: =SUM(BH95:BK95) -> 152.20331 | CN95: =SUM(BL95:BO95) -> 166.30254 | CO95: =SUM(BP95:BS95) -> 181.70785 | CP95: =SUM(BT95:BW95) -> 198.54021 | CQ95: x
B96: =B69 -> a/a % | C96: =C69 -> [%] | BX96: x | CG96: =CG95/CF95-1 -> 0.39374252 | CH96: =CH95/CG95-1 -> 0.21658372 | CI96: =CI95/CH95-1 -> 0.12338713 | CJ96: =CJ95/CI95-1 -> 0.09263421 | CK96: =CK95/CJ95-1 -> 0.09263421 | CL96: =CL95/CK95-1 -> 0.09263421 | CM96: =CM95/CL95-1 -> 0.09263421 | CN96: =CN95/CM95-1 -> 0.09263421 | ... CP96: =CP95/CO95-1 -> 0.09263421 | CQ96: x
B97: % da Receita Líquida | C97: =C70 -> [%] | AH97: =AH95/AH$20 -> 0.069003567 | AI97: =AI95/AI$20 -> 0.069017775 | AJ97: =AJ95/AJ$20 -> 0.042074703 | AK97: =AK95/AK$20 -> 0.055754247 | AL97: =AL95/AL$20 -> 0.055754247 | AM97: =AM95/AM$20 -> 0.055754247 | AN97: =AN95/AN$20 -> 0.058409211 | AO97: =AO95/AO$20 -> 0.058409211 | ... BW97: =BW95/BW$20 -> 0.059736693 | BX97: x | CF97: =CF95/CF$20 -> 0.045429138 | CG97: =CG95/CG$20 -> 0.052372324 | CH97: =CH95/CH$20 -> 0.058409211 | CI97: =CI95/CI$20 -> 0.059736693 | CJ97: =CJ95/CJ$20 -> 0.059736693 | CK97: =CK95/CK$20 -> 0.059736693 | CL97: =CL95/CL$20 -> 0.059736693 | CM97: =CM95/CM$20 -> 0.059736693 | ... CP97: =CP95/CP$20 -> 0.059736693 | CQ97: x
B98: Margem Bruta | C98: =C97 -> [%] | AH98: =AH95/AH35 -> 0.20300137 | AI98: =AI95/AI35 -> 0.23137652 | AJ98: =AJ95/AJ35 -> 0.1584756 | AK98: 0.21 | AL98: 0.21 | AM98: 0.21 | AN98: 0.22 | AO98: 0.22 | AP98: 0.22 | AQ98: 0.22 | AR98: 0.225 | AS98: 0.225 | AT98: 0.225 | AU98: 0.225 | AV98: 0.225 | AW98: 0.225 | AX98: 0.225 | AY98: 0.225 | AZ98: 0.225 | BA98: 0.225 | BB98: 0.225 | BC98: 0.225 | BD98: 0.225 | BE98: 0.225 | BF98: 0.225 | BG98: 0.225 | BH98: 0.225 | BI98: 0.225 | BJ98: 0.225 | BK98: 0.225 | BL98: 0.225 | BM98: 0.225 | BN98: 0.225 | BO98: 0.225 | BP98: 0.225 | BQ98: 0.225 | BR98: 0.225 | BS98: 0.225 | BT98: 0.225 | BU98: 0.225 | BV98: 0.225 | BW98: 0.225 | BX98: x | CF98: =CF95/CF35 -> 0.21673445 | CG98: =CG95/CG35 -> 0.19726189 | CH98: =CH95/CH35 -> 0.22 | CI98: =CI95/CI35 -> 0.225 | CJ98: =CJ95/CJ35 -> 0.225 | CK98: =CK95/CK35 -> 0.225 | CL98: =CL95/CL35 -> 0.225 | CM98: =CM95/CM35 -> 0.225 | ... CP98: =CP95/CP35 -> 0.225 | CQ98: x
BX99: x | CQ99: x
B100: =Inputs!B146 -> Despesas operacionais, gerais e administrativas | C100: =C95 -> [BRL 000] | D100: =Inputs!F147/1000 -> -9.014 | E100: =Inputs!G147/1000 -> -10.452 | F100: =Inputs!H147/1000 -> -8.349 | G100: =Inputs!I147/1000 -> -13.301 | H100: =Inputs!J147/1000 -> -8.349 | I100: =Inputs!K147/1000 -> -4.123 | J100: =Inputs!L147/1000 -> -5.844 | K100: =Inputs!M147/1000 -> -12.059 | ... AJ100: =Inputs!AL147/1000 -> -52.195 | AK100: =AK104*(AK44/1000)*3 -> -50.883909 | AL100: =AL104*(AL44/1000)*3 -> -40.035246 | AM100: =AM104*(AM44/1000)*3 -> -52.137101 | AN100: =AN102*AN20 -> -42.344439 | AO100: =AO102*AO20 -> -42.376311 | AP100: =AP102*AP20 -> -44.240869 | AQ100: =AQ102*AQ20 -> -50.060552 | AR100: =AR102*AR20 -> -44.711867 | AS100: =AS102*AS20 -> -44.5251 | AT100: =AT102*AT20 -> -46.255218 | AU100: =AU102*AU20 -> -52.211604 | ... BW100: =BW102*BW20 -> -92.448804 | BX100: x | BY100: =SUM(D100:G100) -> -41.116 | BZ100: =SUM(H100:K100) -> -30.375 | CA100: =SUM(L100:O100) -> -42.064 | CB100: =SUM(P100:S100) -> -31.998 | CC100: =SUM(T100:W100) -> -49.962 | CD100: =SUM(X100:AA100) -> -94.124 | CE100: =SUM(AB100:AE100) -> -128.172 | CF100: =SUM(AF100:AI100) -> -162.113 | CG100: =SUM(AJ100:AM100) -> -195.25126 | CH100: =SUM(AN100:AQ100) -> -179.02217 | CI100: =SUM(AR100:AU100) -> -187.70379 | CJ100: =SUM(AV100:AY100) -> -195.32532 | CK100: =SUM(AZ100:BC100) -> -213.41912 | CL100: =SUM(BD100:BG100) -> -233.18903 | CM100: =SUM(BH100:BK100) -> -254.79032 | CN100: =SUM(BL100:BO100) -> -278.39262 | CO100: =SUM(BP100:BS100) -> -304.1813 | CP100: =SUM(BT100:BW100) -> -332.35889 | CQ100: x
B101: =B96 -> a/a % | C101: =C96 -> [%] | H101: =H100/D100-1 -> -0.073774129 | I101: =I100/E100-1 -> -0.60553004 | J101: =J100/F100-1 -> -0.30003593 | K101: =K100/G100-1 -> -0.093376438 | L101: =L100/H100-1 -> 0.13067433 | M101: =M100/I100-1 -> 1.643706 | N101: =N100/J100-1 -> 0.92060233 | O101: =O100/K100-1 -> -0.12928103 | ... BW101: =BW100/BS100-1 -> 0.09263421 | BX101: x | CE101: =CE100/CD100-1 -> 0.36173558 | CF101: =CF100/CE100-1 -> 0.26480823 | CG101: =CG100/CF100-1 -> 0.20441455 | CH101: =CH100/CG100-1 -> -0.083118977 | CI101: =CI100/CH100-1 -> 0.048494655 | CJ101: =CJ100/CI100-1 -> 0.04060401 | CK101: =CK100/CJ100-1 -> 0.09263421 | CL101: =CL100/CK100-1 -> 0.09263421 | ... CP101: =CP100/CO100-1 -> 0.09263421 | CQ101: x
B102: =B92 -> % da Receita Líquida | C102: =C92 -> [%] | D102: =D100/D$20 -> -0.17237818 | E102: =E100/E$20 -> -0.19346241 | F102: =F100/F$20 -> -0.13597941 | G102: =G100/G$20 -> -0.19337065 | H102: =H100/H$20 -> -0.10971667 | I102: =I100/I$20 -> -0.04889358 | J102: =J100/J$20 -> -0.073156076 | K102: =K100/K$20 -> -0.13871921 | ... AM102: =AM100/AM$20 -> -0.12735571 | AN102: -0.11 | AO102: -0.11 | AP102: -0.11 | AQ102: -0.11 | AR102: -0.105 | AS102: -0.105 | AT102: -0.105 | AU102: -0.105 | AV102: -0.1 | AW102: -0.1 | AX102: -0.1 | AY102: -0.1 | AZ102: -0.1 | BA102: -0.1 | BB102: -0.1 | BC102: -0.1 | BD102: -0.1 | BE102: -0.1 | BF102: -0.1 | BG102: -0.1 | BH102: -0.1 | BI102: -0.1 | BJ102: -0.1 | BK102: -0.1 | BL102: -0.1 | BM102: -0.1 | BN102: -0.1 | BO102: -0.1 | BP102: -0.1 | BQ102: -0.1 | BR102: -0.1 | BS102: -0.1 | BT102: -0.1 | BU102: -0.1 | BV102: -0.1 | BW102: -0.1 | BX102: x | CE102: =CE100/CE$20 -> -0.12248723 | CF102: =CF100/CF$20 -> -0.13136553 | CG102: =CG100/CG$20 -> -0.13087063 | CH102: =CH100/CH$20 -> -0.11 | CI102: =CI100/CI$20 -> -0.105 | CJ102: =CJ100/CJ$20 -> -0.1 | CK102: =CK100/CK$20 -> -0.1 | CL102: =CL100/CL$20 -> -0.1 | ... CP102: =CP100/CP$20 -> -0.1 | CQ102: x
BX103: x | CQ103: x
B104: Despesa per capita (R$ mil mensal per capita) | C104: =C100 -> [BRL 000] | E104: =(E100/E44)*1000/3 -> -1.7124601 | F104: =(F100/F44)*1000/3 -> -1.1586178 | G104: =(G100/G44)*1000/3 -> -1.6555887 | H104: =(H100/H44)*1000/3 -> -0.95965517 | I104: =(I100/I44)*1000/3 -> -0.421704 | J104: =(J100/J44)*1000/3 -> -0.6000308 | K104: =(K100/K44)*1000/3 -> -1.2785199 | L104: =(L100/L44)*1000/3 -> -0.96538324 | ... AJ104: =(AJ100/AJ44)*1000/3 -> -2.5116693 | AK104: =AJ104 -> -2.5116693 | AL104: =AH104*(1+AL105) -> -2.0063222 | AM104: =AI104*(1+AM105) -> -2.5741806 | AN104: =AJ104*(1+AN105) -> -2.6372528 | AO104: =AK104*(1+AO105) -> -2.6372528 | AP104: =AL104*(1+AP105) -> -2.1066383 | AQ104: =AM104*(1+AQ105) -> -2.7028896 | AR104: =AN104*(1+AR105) -> -2.9009781 | AS104: =AO104*(1+AS105) -> -2.9009781 | ... BW104: =BS104*(1+BW105) -> -5.4350868 | BX104: x | BY104: =AVERAGE(D104:G104) -> -1.5088889 | BZ104: =AVERAGE(H104:K104) -> -0.81497748 | CA104: =AVERAGE(L104:O104) -> -1.1574399 | CB104: =AVERAGE(P104:S104) -> -1.4778591 | CC104: =AVERAGE(T104:W104) -> -1.4097577 | CD104: =AVERAGE(X104:AA104) -> -1.8327231 | CE104: =AVERAGE(AB104:AE104) -> -1.8690583 | CF104: =AVERAGE(AF104:AI104) -> -2.3027044 | CG104: =AVERAGE(AJ104:AM104) -> -2.4009603 | CH104: =AVERAGE(AN104:AQ104) -> -2.5210084 | CI104: =AVERAGE(AR104:AU104) -> -2.7731092 | CJ104: =AVERAGE(AV104:AY104) -> -3.022689 | CK104: =AVERAGE(AZ104:BC104) -> -3.294731 | CL104: =AVERAGE(BD104:BG104) -> -3.5912568 | CM104: =AVERAGE(BH104:BK104) -> -3.9144699 | CN104: =AVERAGE(BL104:BO104) -> -4.2667722 | CO104: =AVERAGE(BP104:BS104) -> -4.6507817 | CP104: =AVERAGE(BT104:BW104) -> -5.0693521 | CQ104: x
B105: =B101 -> a/a % | C105: =C102 -> [%] | I105: =I104/E104-1 -> -0.75374375 | J105: =J104/F104-1 -> -0.48211499 | K105: =K104/G104-1 -> -0.22775512 | L105: =L104/H104-1 -> 0.0059688797 | M105: =M104/I104-1 -> 1.6996202 | N105: =N104/J104-1 -> 1.1201073 | O105: =O104/K104-1 -> -0.019329957 | P105: =P104/L104-1 -> -1.1514792 | ... AK105: =AK104/AG104-1 -> 0.077348851 | AL105: 0 | AM105: 0 | AN105: 0.05 | AO105: 0.05 | AP105: 0.05 | AQ105: 0.05 | AR105: 0.1 | AS105: =AR105 -> 0.1 | AT105: =AS105 -> 0.1 | AU105: =AT105 -> 0.1 | AV105: 0.09 | AW105: =AV105 -> 0.09 | AX105: =AW105 -> 0.09 | AY105: =AX105 -> 0.09 | AZ105: =AY105 -> 0.09 | BA105: =AZ105 -> 0.09 | BB105: =BA105 -> 0.09 | BC105: =BB105 -> 0.09 | BD105: =BC105 -> 0.09 | ... BW105: =BV105 -> 0.09 | BX105: x | BZ105: =BZ104/BY104-1 -> -0.45988238 | CA105: =CA104/BZ104-1 -> 0.42021095 | CB105: =CB104/CA104-1 -> 0.27683439 | CC105: =CC104/CB104-1 -> -0.046081138 | CD105: =CD104/CC104-1 -> 0.30002702 | CE105: =CE104/CD104-1 -> 0.019825791 | CF105: =CF104/CE104-1 -> 0.23201318 | CG105: =CG104/CF104-1 -> 0.042669795 | ... CP105: =CP104/CO104-1 -> 0.09 | CQ105: x
BX106: x | CQ106: x
...

Sheet Valuation
B7: Valores em R$ (Milhares) | C7: Unidade | BA7: =Modelo!BY7 -> 2017 | BB7: =Modelo!BZ7 -> 2018 | BC7: =Modelo!CA7 -> 2019 | BD7: =Modelo!CB7 -> 2020 | BE7: =Modelo!CC7 -> 2021 | BF7: =Modelo!CD7 -> 2022 | BG7: =Modelo!CE7 -> 2023 | BH7: =Modelo!CF7 -> 2024 | ... BR7: =Modelo!CP7 -> 2034 | BS7: Perpetuidade | BU7: =Modelo!CQ7 -> x
BU8: =Modelo!CQ8 -> x
A9: l | B9: Fluxos de Caixa Livre | BU9: =Modelo!CQ9 -> x
BU10: =Modelo!CQ10 -> x
BH11: 45657 | BI11: 46022 | BJ11: 46387 | BK11: 46752 | BL11: 47118 | BM11: 47483 | BN11: 47848 | BO11: 48213 | BP11: 48579 | BQ11: 48944 | BR11: 49309 | BU11: =Modelo!CQ11 -> x
B12: FCO | C12: [BRL 000] | BH12: =+BH13+BH14+BH15+BH16 -> 145.95633 | BI12: =+BI13+BI14+BI15+BI16 -> 248.54217 | BJ12: =+BJ13+BJ14+BJ15+BJ16 -> 260.61273 | BK12: =+BK13+BK14+BK15+BK16 -> 268.10472 | BL12: =+BL13+BL14+BL15+BL16 -> 287.34494 | BM12: =+BM13+BM14+BM15+BM16 -> 307.88508 | BN12: =+BN13+BN14+BN15+BN16 -> 332.2228 | BO12: =+BO13+BO14+BO15+BO16 -> 359.22093 | ... BR12: =+BR13+BR14+BR15+BR16 -> 455.7975 | BU12: =Modelo!CQ12 -> x
B13: (+) EBITDA | BH13: =Modelo!CF52 -> 160.61833 | BI13: =Modelo!CG52 -> 193.94655 | BJ13: =Modelo!CH52 -> 250.90167 | BK13: =Modelo!CI52 -> 284.04885 | BL13: =Modelo!CJ52 -> 316.80139 | BM13: =Modelo!CK52 -> 343.34172 | BN13: =Modelo!CL52 -> 372.73552 | BO13: =Modelo!CM52 -> 405.13546 | ... BR13: =Modelo!CP52 -> 517.8069 | BU13: =Modelo!CQ13 -> x
B14: (-) Imposto | BH14: =Modelo!CF42 -> -17.147 | BI14: =Modelo!CG42 -> -18.632059 | BJ14: =Modelo!CH42 -> -39.281412 | BK14: =Modelo!CI42 -> -51.337677 | BL14: =Modelo!CJ42 -> -63.582446 | BM14: =Modelo!CK42 -> -72.523293 | BN14: =Modelo!CL42 -> -81.767304 | BO14: =Modelo!CM42 -> -91.923493 | ... BR14: =Modelo!CP42 -> -129.89816 | BU14: =Modelo!CQ14 -> x
B15: (-) ∆ Capital de Giro | BH15: =Modelo!CF140 -> -20.891 | BI15: =Modelo!CG140 -> 27.112751 | BJ15: =Modelo!CH140 -> -8.2527546 | BK15: =Modelo!CI140 -> -15.568925 | BL15: =Modelo!CJ140 -> -16.684434 | BM15: =Modelo!CK140 -> -18.229983 | BN15: =Modelo!CL140 -> -19.918703 | BO15: =Modelo!CM140 -> -21.763856 | ... BR15: =Modelo!CP140 -> -28.389663 | BU15: =Modelo!CQ15 -> x
B16: (+) Receitas Financeiras | BH16: =Modelo!CF35 -> 23.376 | BI16: =Modelo!CG35 -> 46.114931 | BJ16: =Modelo!CH35 -> 57.245224 | BK16: =Modelo!CI35 -> 50.962464 | BL16: =Modelo!CJ35 -> 50.810426 | BM16: =Modelo!CK35 -> 55.296637 | BN16: =Modelo!CL35 -> 61.173289 | BO16: =Modelo!CM35 -> 67.772816 | ... BR16: =Modelo!CP35 -> 96.278428 | BU16: =Modelo!CQ16 -> x
B17: FCI | BH17: =+BH18 -> -93.599 | BI17: =+BI18 -> -85.623622 | BJ17: =+BJ18 -> -97.648457 | BK17: =+BK18 -> -107.25931 | BL17: =+BL18 -> -117.19519 | BM17: =+BM18 -> -128.05147 | BN17: =+BN18 -> -139.91342 | BO17: =+BO18 -> -152.87419 | ... BR17: =+BR18 -> -166.17945 | BU17: =Modelo!CQ17 -> x
B18: (-) CAPEX | BH18: =Modelo!CF144+Modelo!CF145 -> -93.599 | BI18: =Modelo!CG144+Modelo!CG145 -> -85.623622 | BJ18: =Modelo!CH144+Modelo!CH145 -> -97.648457 | BK18: =Modelo!CI144+Modelo!CI145 -> -107.25931 | BL18: =Modelo!CJ144+Modelo!CJ145 -> -117.19519 | BM18: =Modelo!CK144+Modelo!CK145 -> -128.05147 | BN18: =Modelo!CL144+Modelo!CL145 -> -139.91342 | BO18: =Modelo!CM144+Modelo!CM145 -> -152.87419 | ... BR18: =Modelo!CP144+Modelo!CP145 -> -166.17945 | BU18: =Modelo!CQ18 -> x
B19: FCF | BH19: =+BH20+BH21+BH22 -> 39.855 | BI19: =+BI20+BI21+BI22 -> 47.954302 | BJ19: =+BJ20+BJ21+BJ22 -> -107.30025 | BK19: =+BK20+BK21+BK22 -> -91.925404 | BL19: =+BL20+BL21+BL22 -> -81.405772 | BM19: =+BM20+BM21+BM22 -> -78.978164 | BN19: =+BN20+BN21+BN22 -> -78.978164 | BO19: =+BO20+BO21+BO22 -> -78.978164 | ... BR19: =+BR20+BR21+BR22 -> -78.978164 | BU19: =Modelo!CQ19 -> x
B20: (-) Despesas Financeiras | BH20: =Modelo!CF36 -> -75.456 | BI20: =Modelo!CG36 -> -107.2857 | BJ20: =Modelo!CH36 -> -107.30025 | BK20: =Modelo!CI36 -> -91.925404 | BL20: =Modelo!CJ36 -> -81.405772 | BM20: =Modelo!CK36 -> -78.978164 | BN20: =Modelo!CL36 -> -78.978164 | BO20: =Modelo!CM36 -> -78.978164 | ... BR20: =Modelo!CP36 -> -78.978164 | BU20: =Modelo!CQ20 -> x
B21: (+/-) Delta Equity | BH21: =Modelo!CF149 -> 84.603 | BI21: =Modelo!CG149 -> 0 | BJ21: =Modelo!CH149 -> 0 | BK21: =Modelo!CI149 -> 0 | BL21: =Modelo!CJ149 -> 0 | BM21: =Modelo!CK149 -> 0 | BN21: =Modelo!CL149 -> 0 | BO21: =Modelo!CM149 -> 0 | ... BR21: =Modelo!CP149 -> 0 | BU21: =Modelo!CQ21 -> x
B22: (+/-) Delta Debt | BH22: =+Modelo!CF150+Modelo!CF151 -> 30.708 | BI22: =+Modelo!CG150+Modelo!CG151 -> 155.24 | BJ22: =+Modelo!CH150+Modelo!CH151 -> 0 | BK22: =+Modelo!CI150+Modelo!CI151 -> 0 | BL22: =+Modelo!CJ150+Modelo!CJ151 -> 0 | BM22: =+Modelo!CK150+Modelo!CK151 -> 0 | BN22: =+Modelo!CL150+Modelo!CL151 -> 0 | BO22: =+Modelo!CM150+Modelo!CM151 -> 0 | ... BR22: =+Modelo!CP150+Modelo!CP151 -> 0 | BU22: =Modelo!CQ22 -> x
B23: Fluxo de caixa livre | BH23: =+BH12+BH17+BH19 -> 92.212333 | BI23: =+BI12+BI17+BI19 -> 210.87285 | BJ23: =+BJ12+BJ17+BJ19 -> 55.664022 | BK23: =+BK12+BK17+BK19 -> 68.920003 | BL23: =+BL12+BL17+BL19 -> 88.743978 | BM23: =+BM12+BM17+BM19 -> 100.85544 | BN23: =+BN12+BN17+BN19 -> 113.33121 | BO23: =+BO12+BO17+BO19 -> 127.36857 | ... BR23: =+BR12+BR17+BR19 -> 210.63989 | BS23: =BR23*(1+$C$29)/(C58-C29) -> 2086.338 | BU23: =Modelo!CQ23 -> x
BU24: =Modelo!CQ24 -> x
B25: Desconto | C25: Unidade | BI25: 1 | BJ25: =BI25+1 -> 2 | BK25: =BJ25+1 -> 3 | BL25: =BK25+1 -> 4 | BM25: =BL25+1 -> 5 | BN25: =BM25+1 -> 6 | BO25: =BN25+1 -> 7 | BP25: =BO25+1 -> 8 | BQ25: =BP25+1 -> 9 | BR25: =BQ25+1 -> 10 | BU25: =Modelo!CQ25 -> x
B26: Fluxo de caixa livre | C26: [BRL 000] | BI26: =BI23/(1+$C$58)^BI25 -> 184.16843 | BJ26: =BJ23/(1+$C$58)^BJ25 -> 42.458399 | BK26: =BK23/(1+$C$58)^BK25 -> 45.912277 | BL26: =BL23/(1+$C$58)^BL25 -> 51.631762 | BM26: =BM23/(1+$C$58)^BM25 -> 51.247407 | BN26: =BN23/(1+$C$58)^BN25 -> 50.294051 | BO26: =BO23/(1+$C$58)^BO25 -> 49.365538 | BP26: =BP23/(1+$C$58)^BP25 -> 48.451493 | ... BR26: =BR23/(1+$C$58)^BR25 -> 54.38583 | BS26: =BS23/(1+$C$58)^BR25 -> 538.67869 | BU26: =Modelo!CQ22 -> x
BU27: =Modelo!CQ23 -> x
BU28: =Modelo!CQ24 -> x
B29: Crescimento na Perpetuidade (g) | C29: 0.04 | BU29: =Modelo!CQ25 -> x
BU30: =Modelo!CQ26 -> x
A31: l | B31: Premissas | BU31: =Modelo!CQ27 -> x
BU32: =Modelo!CQ28 -> x
B33: PRNR3 | BU33: =Modelo!CQ29 -> x
B34: Preço da ação no último fechamento | C34: 15 | BU34: =Modelo!CQ30 -> x
B35: Data do último fechamento | C35: 45700 | BU35: =Modelo!CQ31 -> x
B36: 52 Week Price (Low) | BU36: =Modelo!CQ32 -> x
B37: 52 Week Price (High) | BU37: =Modelo!CQ33 -> x
B38: Quantidade de ações | C38: 46.7 | BU38: =Modelo!CQ34 -> x
B39: Market Cap | C39: =C38*C34 -> 700.5 | BU39: =Modelo!CQ35 -> x
BU40: =Modelo!CQ36 -> x
A41: l | B41: Valuation | BU41: =Modelo!CQ37 -> x
BU42: =Modelo!CQ38 -> x
B43: Fluxo de caixa livre | BU43: =Modelo!CQ39 -> x
B44: Valor Presente dos fluxos de caixa estágio 1 | C44: =SUM(BI26:BR26) -> 634.12125 | BU44: =Modelo!CQ40 -> x
B45: Valor Presente da Perpetuidade | C45: =BS26 -> 538.67869 | BU45: =Modelo!CQ41 -> x
B46: Equity value | C46: =SUM(C44,C45) -> 1172.7999 | BU46: =Modelo!CQ42 -> x
B47: Preço por ação | C47: =C46/C38 -> 25.113489
B48: Upside/Downside | C48: =C47/C34-1 -> 0.67423262
BU49: =Modelo!CQ57 -> x
A50: l | B50: WACC | BU50: =Modelo!CQ58 -> x
BU51: =Modelo!CQ59 -> x
B52: Cost of Equity (Ke) | BU52: =Modelo!CQ60 -> x
B53: Beta | C53: 1 | BU53: =Modelo!CQ61 -> x
B54: Risk Free Rate (10 Year Treasury Bond) | C54: 0.045 | BU54: =Modelo!CQ62 -> x
B55: Equity Risk Premium (ERP) | C55: 0.1 | BU55: =Modelo!CQ63 -> x
B56: Country Risk Premium (CRP) | C56: 0.044 | BU56: =Modelo!CQ64 -> x
B57: Devaluation Risk | C57: 1 | BU57: =Modelo!CQ65 -> x
B58: Ke | C58: =(1+(C54+C53*(C55-C56)+C56))*C57-1 -> 0.145 | BK58: Ke = 21% = IPCA de 5% + 16% | BU58: =Modelo!CQ66 -> x
BU59: =Modelo!CQ67 -> x
B60: Cost of Debt | BU60: =Modelo!CQ36 -> x
B61: Dívida 1 | BU61: =Modelo!CQ10 -> x
B62: Montante | C62: 247.548 | BU62: =Modelo!CQ11 -> x
B63: CDI+ | C63: 0.022 | BU63: =Modelo!CQ12 -> x
B64: Taxa | C64: =C63+Macro!$BH$10 -> 0.1367 | BU64: =Modelo!CQ13 -> x
B65: % da dívida | C65: =C62/C81 -> 0.65219213 | BU65: =Modelo!CQ14 -> x
B66: Dívida 2 | BU66: =Modelo!CQ15 -> x
B67: Montante | C67: 78.937 | BU67: =Modelo!CQ16 -> x
B68: CDI+ | C68: 0.022 | BU68: =Modelo!CQ17 -> x
B69: Taxa | C69: =C68+Macro!$BI$10 -> 0.172 | BU69: =Modelo!CQ18 -> x
B70: % da dívida | C70: =C67/C81 -> 0.20796811 | BU70: =Modelo!CQ19 -> x
B71: Dívida 3 | BU71: =Modelo!CQ20 -> x
B72: Montante | C72: 38.012 | BU72: =Modelo!CQ21 -> x
B73: CDI+ | C73: 0.022 | BU73: =Modelo!CQ22 -> x
B74: Taxa | C74: =C73+Macro!$BI$10 -> 0.172 | BU74: =Modelo!CQ23 -> x
B75: % da dívida | C75: =C72/C81 -> 0.10014675 | BU75: =Modelo!CQ24 -> x
B76: Dívida 4 | BU76: =Modelo!CQ25 -> x
B77: Montante | C77: 15.066 | BU77: =Modelo!CQ26 -> x
B78: CDI+ | C78: 0.022 | BU78: =Modelo!CQ27 -> x
B79: Taxa | C79: =C78+Macro!$BI$10 -> 0.172 | BU79: =Modelo!CQ28 -> x
B80: % da dívida | C80: =C77/C81 -> 0.039693015 | BU80: =Modelo!CQ29 -> x
B81: Dívida Bruta | C81: =SUM(C72,C67,C62,C77) -> 379.563 | BU81: =Modelo!CQ30 -> x
B82: Kd | C82: =(C64*C65)+(C69*C70)+(C74*C75)+(C79*C80) -> 0.14897762 | BU82: =Modelo!CQ31 -> x
B83: Kd | C83: =C82*(1-Modelo!CF43) -> 0.10597369 | BU83: =Modelo!CQ32 -> x
BU84: =Modelo!CQ33 -> x
B85: Weighted Avarage Cost of Captial (WACC) | BU85: =Modelo!CQ33 -> x
B86: Ke | C86: =C58 -> 0.145 | BU86: =Modelo!CQ34 -> x
B87: Kd depois de impostos | C87: =C83 -> 0.10597369 | BU87: =Modelo!CQ35 -> x
B88: D | C88: =C81 -> 379.563 | BU88: =Modelo!CQ36 -> x
B89: E | C89: =C39 -> 700.5 | BU89: =Modelo!CQ37 -> x
B90: WACC | C90: =C86*(C89/(C89+C88))+C87*(C88/(C88+C89))*(1-Modelo!CF43) -> 0.12053483 | BU90: =Modelo!CQ38 -> x
BU91: =Modelo!CQ39 -> x
B92: EV/EBITDA | C92: =C39+Modelo!CG108+150 -> 1046.5136 | BH92: =$C$92/BH13 -> 6.5155304 | BI92: =$C$92/BI13 -> 5.3958869 | BJ92: =$C$92/BJ13 -> 4.1710109 | BK92: =$C$92/BK13 -> 3.6842734 | BL92: =$C$92/BL13 -> 3.3033744 | BM92: =$C$92/BM13 -> 3.0480235 | BN92: =$C$92/BN13 -> 2.8076574 | BO92: =$C$92/BO13 -> 2.5831203 | ... BR92: =$C$92/BR13 -> 2.02105 | BU92: =Modelo!CQ40 -> x
B93: P/E | C93: =C39 -> 700.5 | BH93: =$C$93/Modelo!CF47 -> 16.57792 | BI93: =$C$93/Modelo!CG47 -> 17.127601 | BJ93: =$C$93/Modelo!CH47 -> 8.1240073 | BK93: =$C$93/Modelo!CI47 -> 6.2161457 | BL93: =$C$93/Modelo!CJ47 -> 5.0190343 | BM93: =$C$93/Modelo!CK47 -> 4.4002756 | BN93: =$C$93/Modelo!CL47 -> 3.9028128 | BO93: =$C$93/Modelo!CM47 -> 3.4716096 | ... BR93: =$C$93/Modelo!CP47 -> 2.4567128 | BU93: =Modelo!CQ41 -> x
BU94: =Modelo!CQ42 -> x
BU95: =Modelo!CQ43 -> x
B96: TIR | BU96: =Modelo!CQ44 -> x
BI97: 1 | BJ97: =BI97+1 -> 2 | BK97: =BJ97+1 -> 3 | BL97: =BK97+1 -> 4 | BM97: =BL97+1 -> 5 | BN97: =BM97+1 -> 6 | BO97: =BN97+1 -> 7 | BP97: =BO97+1 -> 8 | BQ97: =BP97+1 -> 9 | BR97: =BQ97+1 -> 10 | BU97: =Modelo!CQ45 -> x
B98: Fluxo de Caixa Livre | BI98: =BI23 -> 210.87285 | BJ98: =BJ23 -> 55.664022 | BK98: =BK23 -> 68.920003 | BL98: =BL23 -> 88.743978 | BM98: =BM23 -> 100.85544 | BN98: =BN23 -> 113.33121 | BO98: =BO23 -> 127.36857 | BP98: =BP23 -> 143.13672 | ... BS98: =BS23 -> 2086.338 | BU98: =Modelo!CQ46 -> x
BU99: =Modelo!CQ47 -> x
C100: 2025 | BI100: =BI98/(1+$C$90)^BI97 -> 188.18946 | BJ100: =BJ98/(1+$C$90)^BJ97 -> 44.332668 | BK100: =BK98/(1+$C$90)^BK97 -> 48.985688 | BL100: =BL98/(1+$C$90)^BL97 -> 56.290804 | BM100: =BM98/(1+$C$90)^BM97 -> 57.091641 | BN100: =BN98/(1+$C$90)^BN97 -> 57.252886 | BO100: =BO98/(1+$C$90)^BO97 -> 57.422853 | BP100: =BP98/(1+$C$90)^BP97 -> 57.590145 | ... BR100: =BR98/(1+$C$90)^BR97 -> 67.497397 | BS100: =BS98/(1+$C$90)^BR97 -> 668.54565 | BU100: =Modelo!CQ48 -> x
C101: 2026 | BJ101: =BJ98/(1+$C$90)^BI97 -> 49.676298 | BK101: =BK98/(1+$C$90)^BJ97 -> 54.890169 | BL101: =BL98/(1+$C$90)^BK97 -> 63.075807 | BM101: =BM98/(1+$C$90)^BL97 -> 63.973173 | BN101: =BN98/(1+$C$90)^BM97 -> 64.153852 | BO101: =BO98/(1+$C$90)^BN97 -> 64.344306 | BP101: =BP98/(1+$C$90)^BO97 -> 64.531764 | BQ101: =BQ98/(1+$C$90)^BP97 -> 76.494414 | BR101: =BR98/(1+$C$90)^BQ97 -> 75.633184 | BS101: =BS98/(1+$C$90)^BQ97 -> 749.12868 | BU101: =Modelo!CQ49 -> x
C102: 2027 | BK102: =BK98/(1+$C$90)^BI97 -> 61.506346 | BL102: =BL98/(1+$C$90)^BJ97 -> 70.678638 | BM102: =BM98/(1+$C$90)^BK97 -> 71.684168 | BN102: =BN98/(1+$C$90)^BL97 -> 71.886626 | BO102: =BO98/(1+$C$90)^BM97 -> 72.100036 | BP102: =BP98/(1+$C$90)^BN97 -> 72.310089 | BQ102: =BQ98/(1+$C$90)^BO97 -> 85.714655 | BR102: =BR98/(1+$C$90)^BP97 -> 84.749617 | BS102: =BS98/(1+$C$90)^BP97 -> 839.42478 | BU102: =Modelo!CQ50 -> x
C103: 2028 | BL103: =BL98/(1+$C$90)^BI97 -> 79.197876 | BM103: =BM98/(1+$C$90)^BJ97 -> 80.324607 | BN103: =BN98/(1+$C$90)^BK97 -> 80.551468 | BO103: =BO98/(1+$C$90)^BL97 -> 80.790602 | BP103: =BP98/(1+$C$90)^BM97 -> 81.025973 | BQ103: =BQ98/(1+$C$90)^BN97 -> 96.046256 | BR103: =BR98/(1+$C$90)^BO97 -> 94.964898 | BS103: =BS98/(1+$C$90)^BO97 -> 940.6047 | BU103: =Modelo!CQ51 -> x
C104: 2029 | BM104: =BM98/(1+$C$90)^BI97 -> 90.00652 | BN104: =BN98/(1+$C$90)^BJ97 -> 90.260726 | BO104: =BO98/(1+$C$90)^BK97 -> 90.528683 | BP104: =BP98/(1+$C$90)^BL97 -> 90.792425 | BQ104: =BQ98/(1+$C$90)^BM97 -> 107.62318 | BR104: =BR98/(1+$C$90)^BN97 -> 106.41148 | BS104: =BS98/(1+$C$90)^BN97 -> 1053.9803 | BU104: =Modelo!CQ52 -> x
C105: 2030 | BN105: =BN98/(1+$C$90)^BI97 -> 101.14029 | BO105: =BO98/(1+$C$90)^BJ97 -> 101.44054 | BP105: =BP98/(1+$C$90)^BK97 -> 101.73607 | BQ105: =BQ98/(1+$C$90)^BL97 -> 120.59552 | BR105: =BR98/(1+$C$90)^BM97 -> 119.23776 | BS105: =BS98/(1+$C$90)^BM97 -> 1181.0217 | BU105: =Modelo!CQ53 -> x
C106: 2031 | BO106: =BO98/(1+$C$90)^BI97 -> 113.66766 | BP106: =BP98/(1+$C$90)^BJ97 -> 113.99881 | BQ106: =BQ98/(1+$C$90)^BK97 -> 135.13148 | BR106: =BR98/(1+$C$90)^BL97 -> 133.61007 | BS106: =BS98/(1+$C$90)^BL97 -> 1323.3759 | BU106: =Modelo!CQ54 -> x
...

Sheet Inputs
E1: ='[40]Balance Sheet'!E3 -> #REF! | F1: ='[40]Balance Sheet'!F3 -> #REF! | G1: ='[40]Balance Sheet'!G3 -> #REF! | H1: ='[40]Balance Sheet'!H3 -> #REF! | I1: ='[40]Balance Sheet'!I3 -> #REF! | J1: ='[40]Balance Sheet'!J3 -> #REF! | K1: ='[40]Balance Sheet'!K3 -> #REF! | L1: ='[40]Balance Sheet'!L3 -> #REF! | ... AI1: ='[40]Balance Sheet'!AI3 -> #REF! | AJ1: 3Q24 | AK1: 4Q24 | AL1: 1Q25 | AN1: =Modelo!BY7 -> 2017 | AO1: =Modelo!BZ7 -> 2018 | AP1: =Modelo!CA7 -> 2019 | AQ1: =Modelo!CB7 -> 2020 | AR1: =Modelo!CC7 -> 2021 | AS1: =Modelo!CD7 -> 2022 | AT1: =Modelo!CE7 -> 2023 | AU1: UDM
B2: Balanço Patrimonial
B3: ATIVO
B5: CIRCULANTE
B6: Caixa e equivalentes de caixa | J6: 2367 | K6: 4754 | L6: 5101 | M6: -3400 | N6: 4641 | O6: 12260 | P6: 13296 | Q6: 34157 | R6: 7730 | S6: 27646 | T6: 47445 | U6: 52035 | V6: 43367 | W6: 50134 | X6: 50628 | Y6: 66038 | Z6: 53723 | AA6: 44656 | AB6: 91538 | AC6: 105039 | AD6: 180380 | AE6: 67826 | AF6: 82151 | AG6: 125891 | AH6: 174881 | AI6: 179772 | AJ6: 182138 | AK6: 232537 | AL6: 349281
B7: Títulos e valores mobiliários | J7: 41 | K7: 542 | L7: 6 | M7: -28 | N7: 463 | O7: 13 | P7: 3573 | Q7: 3616 | R7: 138324 | S7: 120331 | T7: 87133 | U7: 57794 | V7: 35197 | W7: 20423 | X7: 20482 | Y7: 10611 | Z7: 12684 | AA7: 12792 | AB7: 12482 | AC7: 10848 | AD7: 10857 | AE7: 11038 | AF7: 10858 | AG7: 11011 | AH7: 10960 | AI7: 11774 | AJ7: 10977 | AK7: 11202 | AL7: 11180
B8: Depósitos bancários vinculados | J8: 0 | K8: 0 | L8: 0 | M8: 0 | N8: 0 | O8: 14637 | P8: 9800 | Q8: 6755 | R8: 1398 | S8: 1130 | T8: 863 | U8: 593 | V8: 0 | W8: 0 | X8: 0 | Y8: 0 | Z8: 0 | AA8: 0 | AB8: 0 | AC8: 0 | AD8: 0 | AE8: 0 | AF8: 0 | AG8: 0 | AH8: 0 | AI8: 0 | AJ8: 0 | AK8: 0 | AL8: 0
B9: Contas a receber | J9: 76972 | K9: 70422 | L9: 66556 | M9: -69815 | N9: 71528 | O9: 65509 | P9: 59853 | Q9: 52607 | R9: 69489 | S9: 51624 | T9: 54726 | U9: 63078 | V9: 79141 | W9: 103303 | X9: 105848 | Y9: 108811 | Z9: 122120 | AA9: 159082 | AB9: 205139 | AC9: 205273 | AD9: 226922 | AE9: 271795 | AF9: 232718 | AG9: 276728 | AH9: 239120 | AI9: 223508 | AJ9: 344358 | AK9: 298446 | AL9: 375586
B10: Contas a receber - partes relacionadas | J10: 1 | K10: 0 | L10: 0 | M10: 0 | N10: 0 | O10: 0 | P10: 0 | Q10: 0 | R10: 3 | S10: 0 | T10: 0 | U10: 0 | V10: 0 | W10: 0 | X10: 0 | Y10: 0 | Z10: 0 | AA10: 0 | AB10: 0 | AC10: 0 | AD10: 0 | AE10: 0 | AF10: 0 | AG10: 0 | AH10: 126 | AI10: 22 | AJ10: 11850 | AK10: 21087 | AL10: 4654
B11: Mútuo a receber - partes relacionadas | J11: 0 | K11: 0 | L11: 0 | M11: 0 | N11: 0 | O11: 0 | P11: 272 | Q11: 0 | R11: 0 | S11: 0 | T11: 0 | U11: 0 | V11: 0 | W11: 0 | X11: 0 | Y11: 0 | Z11: 0 | AA11: 0 | AB11: 0 | AC11: 0 | AD11: 0 | AE11: 0 | AF11: 0 | AG11: 0 | AH11: 0 | AI11: 0 | AJ11: 0 | AK11: 0 | AL11: 0
B12: Estoques | J12: 67 | K12: 1469 | L12: 1529 | M12: -1052 | N12: 1336 | O12: 684 | P12: 1442 | Q12: 692 | R12: 924 | S12: 639 | T12: 1172 | U12: 1282 | V12: 2619 | W12: 2954 | X12: 3483 | Y12: 3628 | Z12: 3529 | AA12: 4308 | AB12: 5660 | AC12: 5361 | AD12: 4729 | AE12: 4796 | AF12: 5988 | AG12: 4609 | AH12: 4431 | AI12: 5692 | AJ12: 5732 | AK12: 5778 | AL12: 6781
B13: Créditos com funcionários | J13: 1192 | K13: 1793 | L13: 1356 | M13: -1189 | N13: 1140 | O13: 1511 | P13: 1518 | Q13: 1090 | R13: 1183 | S13: 1191 | T13: 1524 | U13: 1248 | V13: 1516 | W13: 1952 | X13: 2549 | Y13: 2299 | Z13: 2360 | AA13: 2890 | AB13: 3195 | AC13: 0 | AD13: 0 | AE13: 0 | AF13: 0 | AG13: 0 | AH13: 0 | AI13: 0 | AJ13: 0 | AK13: 0 | AL13: 0
B14: Tributos a recuperar | J14: 12686 | K14: 14387 | L14: 18521 | M14: -23011 | N14: 24610 | O14: 25535 | P14: 25518 | Q14: 25022 | R14: 25696 | S14: 27577 | T14: 27586 | U14: 22788 | V14: 20244 | W14: 18391 | X14: 13698 | Y14: 12693 | Z14: 12075 | AA14: 14482 | AB14: 16359 | AC14: 12392 | AD14: 13637 | AE14: 17981 | AF14: 19928 | AG14: 15428 | AH14: 21558 | AI14: 27110 | AJ14: 25967 | AK14: 20037 | AL14: 27294
B15: Dividendos a receber | J15: 0 | K15: 0 | L15: 0 | M15: 0 | N15: 0 | O15: 0 | P15: 0 | Q15: 0 | R15: 0 | S15: 0 | T15: 0 | U15: 0 | V15: 0 | W15: 0 | X15: 0 | Y15: 0 | Z15: 0 | AA15: 0 | AB15: 0 | AC15: 0 | AD15: 0 | AE15: 0 | AF15: 0 | AG15: 0 | AH15: 0 | AI15: 0 | AJ15: 0 | AK15: 0 | AL15: 0
B16: Dididendos antecipados | K16: 0 | L16: 0 | M16: 0 | N16: 0 | O16: 0 | P16: 0 | Q16: 0 | R16: 0 | S16: 0 | T16: 0 | U16: 0 | V16: 0 | W16: 0 | X16: 0 | Y16: 0 | Z16: 0 | AA16: 10908 | AB16: 10908 | AC16: 0 | AD16: 949 | AE16: 0 | AF16: 0 | AG16: 0 | AH16: 0 | AI16: 0 | AJ16: 0 | AK16: 0 | AL16: 0
B17: Despesas antecipadas | J17: 2814 | K17: 1664 | L17: 1889 | M17: -3682 | N17: 3569 | O17: 2809 | P17: 2196 | Q17: 3043 | R17: 3623 | S17: 2113 | T17: 1612 | U17: 5485 | V17: 5745 | W17: 5255 | X17: 4646 | Y17: 7174 | Z17: 5135 | AA17: 7736 | AB17: 6669 | AC17: 0 | AD17: 0 | AE17: 0 | AF17: 0 | AG17: 0 | AH17: 0 | AI17: 0 | AJ17: 0 | AK17: 0 | AL17: 0
B18: Instrumentos Financeiros Derivativos | K18: 0 | L18: 0 | M18: 0 | N18: 0 | O18: 0 | P18: 0 | Q18: 0 | R18: 12218 | S18: 12218 | T18: 0 | U18: 0 | V18: 0 | W18: 0 | X18: 0 | Y18: 0 | Z18: 0 | AA18: 0 | AB18: 0 | AC18: 0 | AD18: 0 | AE18: 0 | AF18: 0 | AG18: 0 | AH18: 0 | AI18: 0 | AJ18: 0 | AK18: 0 | AL18: 0
B19: Instrumento derivativo financeiro (Swap) | J19: 0 | K19: 1844 | L19: 2906 | M19: -2163 | N19: 1197 | O19: 538 | P19: 266 | Q19: 132 | R19: 108 | S19: 1899 | T19: 59 | U19: 0 | V19: 0 | W19: 0 | X19: 0 | Y19: 0 | Z19: 0 | AA19: 6 | AB19: 24 | AC19: 0 | AD19: 288 | AE19: 259 | AF19: 598 | AG19: 0 | AH19: 0 | AI19: 0 | AJ19: 0 | AK19: 2685 | AL19: 4321
B20: Outros créditos a receber | J20: 2656 | K20: 0 | L20: 0 | M20: 0 | N20: 0 | O20: 0 | P20: 0 | Q20: 0 | R20: 0 | S20: 0 | T20: 0 | U20: 0 | V20: 0 | W20: 0 | X20: 0 | Y20: 0 | Z20: 0 | AA20: 0 | AB20: 0 | AC20: 0 | AD20: 0 | AE20: 0 | AF20: 0 | AG20: 0 | AH20: 0 | AI20: 0 | AJ20: 0 | AK20: 0 | AL20: 0
B21: Outros ativos circulantes | J21: 402 | K21: 1460 | L21: 1891 | M21: -976 | N21: 1002 | O21: 1448 | P21: 1314 | Q21: 748 | R21: 1618 | S21: 469 | T21: 331 | U21: 544 | V21: 612 | W21: 763 | X21: 833 | Y21: 850 | Z21: 1179 | AA21: 1498 | AB21: 1883 | AC21: 14975 | AD21: 16082 | AE21: 20221 | AF21: 15569 | AG21: 11560 | AH21: 10882 | AI21: 15623 | AJ21: 36951 | AK21: 17992 | AL21: 16132
J22: 99198 | K22: 98335 | L22: 99755 | M22: -105316 | N22: 109486 | O22: 124944 | P22: 119048 | Q22: 127862 | R22: 262314 | S22: 246837 | T22: 222451 | U22: 204847 | V22: 188441 | W22: 203175 | X22: 202167 | Y22: 212104 | Z22: 212805 | AA22: 258358 | AB22: 353857 | AC22: 353888 | AD22: 453844 | AE22: 393916 | AF22: 367810 | AG22: 445227 | AH22: 461958 | AI22: 463501 | AJ22: =SUM(AJ6:AJ21) -> 617973 | AK22: =SUM(AK6:AK21) -> 609764 | AL22: 795229
B23: NÃO CIRCULANTE | K23: 0 | L23: 0 | M23: 0 | N23: 0 | O23: 0 | P23: 0 | Q23: 0 | R23: 0 | S23: 0 | T23: 0 | U23: 0 | V23: 0 | W23: 0 | X23: 0 | Y23: 0 | Z23: 0 | AA23: 0 | AB23: 0 | AC23: 0 | AD23: 0 | AE23: 0 | AF23: 0 | AG23: 0 | AH23: 0 | AI23: 0
B24: Contas a receber | J24: 334 | K24: 177 | L24: 0 | M24: 0 | N24: 0 | O24: 0 | P24: 0 | Q24: 0 | R24: 0 | S24: 0 | T24: 0 | U24: 0 | V24: 0 | W24: 0 | X24: 0 | Y24: 0 | Z24: 0 | AA24: 0 | AB24: 0 | AC24: 0 | AD24: 0 | AE24: 0 | AF24: 0 | AG24: 0 | AH24: 0 | AI24: 0 | AJ24: 0 | AK24: 0 | AL24: 0
B25: Notas promissórias e confissão de dívida a receber | J25: 0 | K25: 0 | L25: 0 | M25: 0 | N25: 0 | O25: 0 | P25: 997 | Q25: 997 | R25: 4251 | S25: 4251 | T25: 4251 | U25: 4251 | V25: 4251 | W25: 4251 | X25: 4251 | Y25: 4251 | Z25: 4251 | AA25: 4251 | AB25: 4251 | AC25: 4251.1883 | AD25: 4251 | AE25: 4805 | AF25: 4805 | AG25: 4805 | AH25: 4804.6894 | AI25: 4805 | AJ25: 5452 | AK25: 5100 | AL25: 5123
B26: Títulos e valores mobiliários | J26: 0 | K26: 0 | L26: 16 | M26: -46 | N26: 76 | O26: 106 | P26: 137 | Q26: 0 | R26: 0 | S26: 0 | T26: 0 | U26: 0 | V26: 0 | W26: 0 | X26: 1317 | Y26: 1317 | Z26: 1317 | AA26: 1317 | AB26: 1317 | AC26: 1317 | AD26: 1317 | AE26: 1317 | AF26: 1371 | AG26: 1371 | AH26: 1317 | AI26: 2013 | AJ26: 2767 | AK26: 2812 | AL26: 2839
B27: Mútuo a receber - partes relacionadas | J27: 0 | K27: 0 | L27: 0 | M27: -245 | N27: 254 | O27: 263 | P27: 0 | Q27: 0 | R27: 0 | S27: 0 | T27: 0 | U27: 0 | V27: 0 | W27: 0 | X27: 0 | Y27: 0 | Z27: 0 | AA27: 0 | AB27: 0 | AC27: 0 | AD27: 0 | AE27: 0 | AF27: 0 | AG27: 0 | AH27: 0 | AI27: 0 | AJ27: 0 | AK27: 0 | AL27: 0
B28: Créditos com funcionários | J28: 0 | K28: 4 | L28: 2 | M28: 0 | N28: 0 | O28: 0 | P28: 0 | Q28: 0 | R28: 313 | S28: 202 | T28: 163 | U28: 171 | V28: 153 | W28: 207 | X28: 154 | Y28: 154 | Z28: 21 | AA28: 8 | AB28: 5 | AC28: 3 | AD28: 0 | AE28: 0 | AF28: 0 | AG28: 0 | AH28: 0 | AI28: 0 | AJ28: 0 | AK28: 0 | AL28: 0
B29: Outros créditos a receber | J29: 23 | K29: 2656 | L29: 2656 | M29: -2656 | N29: 2656 | O29: 2656 | P29: 2656 | Q29: 2656 | R29: 2656 | S29: 2656 | T29: 2656 | U29: 2656 | V29: 2656 | W29: 2656 | X29: 2656 | Y29: 2656 | Z29: 2656 | AA29: 2655.6197 | AB29: 2656 | AC29: 0 | AD29: 0 | AE29: 0 | AF29: 0 | AG29: 0 | AH29: 0 | AI29: 0 | AJ29: 0
B30: Outros ativos não circulantes | K30: 0 | L30: 0 | M30: 0 | N30: 0 | O30: 0 | P30: 0 | Q30: 0 | R30: 0 | S30: 0 | T30: 51 | U30: 52 | V30: 52 | W30: 52 | X30: 52 | Y30: 52 | Z30: 64 | AA30: 64 | AB30: 74 | AC30: 1935 | AD30: 2038 | AE30: 2059 | AF30: 2074 | AG30: 339 | AH30: 414 | AI30: 524 | AJ30: 578 | AK30: 1091 | AL30: 1347
B31: Despesas antecipadas | J31: 68 | K31: 53 | L31: 39 | M31: -24 | N31: 10 | O31: 0 | P31: 0 | Q31: 0 | R31: 0 | S31: 0 | T31: 0 | U31: 0 | V31: 0 | W31: 0 | X31: 0 | Y31: 0 | Z31: 0 | AA31: 144 | AB31: 133 | AC31: 0 | AD31: 0 | AE31: 0 | AF31: 0 | AG31: 0 | AH31: 0 | AI31: 0 | AJ31: 0
B32: Instrumentos Financeiros Derivativos | J32: 2377 | K32: 5525 | L32: 5861 | M32: -5820 | N32: 5689 | O32: 4866 | P32: 4193 | Q32: 4455 | R32: 0 | S32: 0 | T32: 0 | U32: 0 | V32: 0 | W32: 0 | X32: 0 | Y32: 0 | Z32: 0 | AA32: 0 | AB32: 3613 | AC32: 0 | AD32: 0 | AE32: 0 | AF32: 0 | AG32: 0 | AH32: 0 | AI32: 0 | AJ32: 0 | AK32: 0 | AL32: 0
B33: Tributos a recuperar | J33: 315 | K33: 315 | L33: 315 | M33: -315 | N33: 315 | O33: 303 | P33: 1126 | Q33: 1149 | R33: 1030 | S33: 1030 | T33: 929 | U33: 854 | V33: 854 | W33: 67 | X33: 67 | Y33: 854 | Z33: 668 | AA33: 639 | AB33: 419 | AC33: 327 | AD33: 307 | AE33: 242 | AF33: 228 | AG33: 602 | AH33: 602 | AI33: 567 | AJ33: 567 | AK33: 0 | AL33: 0
B34: Tributos diferidos | J34: 12783 | K34: 14839 | L34: 13511 | M34: -16813 | N34: 19263 | O34: 20598 | P34: 23668 | Q34: 18047 | R34: 14699 | S34: 13739 | T34: 18187 | U34: 34592 | V34: 35603 | W34: 36604 | X34: 37741 | Y34: 41378 | Z34: 41597 | AA34: 41914 | AB34: 42898 | AC34: 48007 | AD34: 49970 | AE34: 51621 | AF34: 53745 | AG34: 64509 | AH34: 71481 | AI34: 77689 | AJ34: 82182 | AK34: 71891 | AL34: 81200
B35: Depósitos judiciais | J35: 547 | K35: 607 | L35: 645 | M35: -711 | N35: 915 | O35: 938 | P35: 1066 | Q35: 1067 | R35: 1068 | S35: 1219 | T35: 3828 | U35: 3834 | V35: 3894 | W35: 4028 | X35: 4130 | Y35: 3962 | Z35: 3945 | AA35: 4031 | AB35: 4250 | AC35: 4426 | AD35: 4302 | AE35: 4575 | AF35: 4782 | AG35: 4910 | AH35: 7440 | AI35: 5620 | AJ35: 5470 | AK35: 5689 | AL35: 5921
B36: Investimentos | J36: 1854 | K36: 2292 | L36: 2408 | M36: -1696 | N36: 1533 | O36: 1821 | P36: 1565 | Q36: 1728 | R36: 1945 | S36: 0 | T36: 0 | U36: 0 | V36: 0 | W36: 0 | X36: 0 | Y36: 0 | Z36: 0 | AA36: 0 | AB36: 0 | AC36: -1e-05 | AD36: 0 | AE36: 5.9371814e-12 | AF36: 2.7939677e-11 | AG36: -9.9999559e-06 | AH36: -9.9999559e-06 | AI36: 0 | AJ36: 0 | AK36: 0 | AL36: 0
B37: Imobilizado e ativo de direito de uso | J37: 67664 | K37: 68049 | L37: 66735 | M37: -67964 | N37: 78724 | O37: 80360 | P37: 80430 | Q37: 77024 | R37: 74242 | S37: 70589 | T37: 71121 | U37: 75485 | V37: 91928 | W37: 91680 | X37: 97135 | Y37: 99594 | Z37: 117618 | AA37: 132806 | AB37: 151750 | AC37: 174189 | AD37: 192045 | AE37: 211083 | AF37: 230886 | AG37: 255291 | AH37: 263546 | AI37: 272059 | AJ37: 294753 | AK37: 301842 | AL37: 295894
B38: Intangível | J38: 7589 | K38: 7172 | L38: 6763 | M38: -6380 | N38: 5943 | O38: 5461 | P38: 5017 | Q38: 4556 | R38: 4123 | S38: 5134 | T38: 4863 | U38: 9888 | V38: 9553 | W38: 9177 | X38: 8783 | Y38: 8055 | Z38: 25498 | AA38: 28871 | AB38: 33035 | AC38: 31596 | AD38: 54677 | AE38: 56645 | AF38: 58360 | AG38: 59950 | AH38: 60638 | AI38: 88221 | AJ38: 197634 | AK38: 245411 | AL38: 225826
J39: 93554 | K39: 101689 | L39: 98951 | M39: -102670 | N39: 115378 | O39: 117372 | P39: 120855 | Q39: 111679 | R39: 104327 | S39: 98820 | T39: 106049 | U39: 131783 | V39: 148944 | W39: 148722 | X39: 156286 | Y39: 162273 | Z39: 197635 | AA39: 216700.62 | AB39: 244401 | AC39: 266051.19 | AD39: 308907 | AE39: 332347 | AF39: 356251 | AG39: 391777 | AH39: 410242.69 | AI39: 451498 | AJ39: =SUM(AJ24:AJ38) -> 589403 | AK39: =SUM(AK24:AK38) -> 633836 | AL39: 618150
K40: 0 | L40: 0 | M40: 0 | N40: 0 | O40: 0 | P40: 0 | Q40: 0 | R40: 0 | S40: 0 | T40: 0 | U40: 0 | V40: 0 | W40: 0 | X40: 0 | Y40: 0 | Z40: 0 | AA40: 0 | AB40: 0 | AC40: 0 | AD40: 0 | AE40: 0 | AF40: 0 | AG40: 0 | AH40: 0 | AI40: 0
B41: TOTAL DO ATIVO | J41: 192752 | K41: 200024 | L41: 198706 | M41: -207986 | N41: 224864 | O41: 242316 | P41: 239903 | Q41: 239541 | R41: 366641 | S41: 345657 | T41: 328500 | U41: 336630 | V41: 337385 | W41: 351897 | X41: 358453 | Y41: 374377 | Z41: 410440 | AA41: 475058.62 | AB41: 598258 | AC41: 619939.19 | AD41: 762751 | AE41: 726263 | AF41: 724061 | AG41: 837004 | AH41: 872200.69 | AI41: 914999 | AJ41: =SUM(AJ22+AJ39) -> 1207376 | AK41: =SUM(AK22+AK39) -> 1243600 | AL41: 1413379
K42: 0 | L42: 0 | M42: 0 | N42: 0 | O42: 0 | P42: 0 | Q42: 0 | R42: 0 | S42: 0 | T42: 0 | U42: 0 | V42: 0 | W42: 0 | X42: 0 | Y42: 0 | Z42: 0 | AA42: 0 | AB42: 0 | AC42: 0 | AD42: 0 | AE42: 0 | AF42: 0 | AG42: 0 | AH42: 0 | AI42: 0
B43: PASSIVO E PATRIMÔNIO LÍQUIDO | K43: 0 | L43: 0 | M43: 0 | N43: 0 | O43: 0 | P43: 0 | Q43: 0 | R43: 0 | S43: 0 | T43: 0 | U43: 0 | V43: 0 | W43: 0 | X43: 0 | Y43: 0 | Z43: 0 | AA43: 0 | AB43: 0 | AC43: 0 | AD43: 0 | AE43: 0 | AF43: 0 | AG43: 0 | AH43: 0 | AI43: 0
K44: 0 | L44: 0 | M44: 0 | N44: 0 | O44: 0 | P44: 0 | Q44: 0 | R44: 0 | S44: 0 | T44: 0 | U44: 0 | V44: 0 | W44: 0 | X44: 0 | Y44: 0 | Z44: 0 | AA44: 0 | AB44: 0 | AC44: 0 | AD44: 0 | AE44: 0 | AF44: 0 | AG44: 0 | AH44: 0 | AI44: 0
B45: CIRCULANTE | K45: 0 | L45: 0 | M45: 0 | N45: 0 | O45: 0 | P45: 0 | Q45: 0 | R45: 0 | S45: 0 | T45: 0 | U45: 0 | V45: 0 | W45: 0 | X45: 0 | Y45: 0 | Z45: 0 | AA45: 0 | AB45: 0 | AC45: 0 | AD45: 0 | AE45: 0 | AF45: 0 | AG45: 0 | AH45: 0 | AI45: 0
B46: Fornecedores | J46: 11524 | K46: 8844 | L46: 9590 | M46: -12846 | N46: 14878 | O46: 12560 | P46: 11768 | Q46: 9419 | R46: 8461 | S46: 6606 | T46: 7124 | U46: 11478 | V46: 12157 | W46: 12457 | X46: 13559 | Y46: 17250 | Z46: 18095 | AA46: 26499 | AB46: 29798 | AC46: 33383 | AD46: 36383 | AE46: 33689 | AF46: 29052 | AG46: 38577 | AH46: 20957 | AI46: 21204 | AJ46: 59339 | AK46: 42428 | AL46: 37327
B47: Fornecedores - partes relacionadas | J47: 13 | K47: 741 | L47: 298 | M47: -400 | N47: 75 | O47: 153 | P47: 996 | Q47: 342 | R47: 220 | S47: 0 | T47: 0 | U47: 0 | V47: 0 | W47: 0 | X47: 0 | Y47: 0 | Z47: 1e-05 | AA47: -5e-05 | AB47: 4e-05 | AC47: 6e-05 | AD47: 0 | AE47: 0 | AF47: 0 | AG47: 0 | AH47: 0 | AI47: 0 | AJ47: 700 | AK47: 2139 | AL47: 1188
B48: Operações de risco sacado | J48: 0 | K48: 0 | L48: 0 | M48: 0 | N48: 0 | O48: 2505 | P48: 7945 | Q48: 5347 | R48: 0 | S48: 0 | T48: 0 | U48: 0 | V48: 0 | W48: 0 | X48: 0 | Y48: 0 | Z48: 0 | AA48: 2939 | AB48: 6941 | AC48: 19790 | AD48: 25736 | AE48: 11003 | AF48: 0 | AG48: 0 | AH48: 0 | AI48: 0 | AJ48: 0 | AK48: 0 | AL48: 0
B49: Empréstimos e financiamentos | J49: 53759 | K49: 43836 | L49: 46112 | M49: -53735 | N49: 56805 | O49: 11932 | P49: 8334 | Q49: 8854 | R49: 4515 | S49: 5134 | T49: 2164 | U49: 929 | V49: 656 | W49: 4350 | X49: 4727 | Y49: 32864 | Z49: 31904 | AA49: 37855 | AB49: 40282 | AC49: 35653 | AD49: 40687 | AE49: 48643 | AF49: 60453 | AG49: 77019 | AH49: 91419 | AI49: 95471 | AJ49: 97974 | AK49: 267358 | AL49: 127847
B50: Debêntures não conversíveis em ações | J50: 0 | K50: 0 | L50: 0 | M50: 0 | N50: 0 | O50: 629 | P50: 3981 | Q50: 11513 | R50: 17790 | S50: 22764 | T50: 24430 | U50: 24410 | V50: 24449 | W50: 24463 | X50: 24484 | Y50: 0 | Z50: 0 | AA50: 0 | AB50: 0 | AC50: 0 | AD50: 0 | AE50: 0 | AF50: 0 | AG50: 0 | AH50: 0 | AI50: 0 | AJ50: 0 | AK50: 0 | AL50: 0
B51: Duplicatas descontadas a pagar | J51: 0 | K51: 0 | L51: 0 | M51: 0 | N51: 0 | O51: 0 | P51: 0 | Q51: 0 | R51: 0 | S51: 0 | T51: 0 | U51: 0 | V51: 0 | W51: 0 | X51: 0 | Y51: 0 | Z51: 0 | AA51: 0 | AB51: 0 | AC51: 7691 | AD51: 2100 | AE51: 20 | AF51: 0 | AG51: 0 | AH51: 0 | AI51: 0 | AJ51: 0 | AK51: 0 | AL51: 0
B52: Arrendamento financeiro a pagar - Direitos de uso CPC 06 | J52: 0 | K52: 0 | L52: 0 | M52: 0 | N52: 1517 | O52: 1847 | P52: 1500 | Q52: 1601 | R52: 1639 | S52: 1731 | T52: 1811 | U52: 2085 | V52: 2103 | W52: 2184 | X52: 2331 | Y52: 2343 | Z52: 4013 | AA52: 4361 | AB52: 4588 | AC52: 4555 | AD52: 4438 | AE52: 4941 | AF52: 5031 | AG52: 5127 | AH52: 4531 | AI52: 4043 | AJ52: 5432 | AK52: 5817 | AL52: 5889
B53: Salários e Encargos Sociais | J53: 26582 | K53: 36642 | L53: 34914 | M53: -28385 | N53: 31788 | O53: 35377 | P53: 34811 | Q53: 24967 | R53: 21521 | S53: 21683 | T53: 21661 | U53: 17778 | V53: 23144 | W53: 33303 | X53: 41306 | Y53: 32982 | Z53: 40932 | AA53: 55515 | AB53: 71069 | AC53: 69116 | AD53: 74887 | AE53: 82899 | AF53: 97465 | AG53: 78670 | AH53: 75311 | AI53: 77802 | AJ53: 119224 | AK53: 100936 | AL53: 110759
B54: Imposto de renda e contribuição social | J54: 901 | K54: 1010 | L54: 999 | M54: -1685 | N54: 1736 | O54: 1411 | P54: 1622 | Q54: 1667 | R54: 1546 | S54: 2815 | T54: 1164 | U54: 1417 | V54: 1585 | W54: 1858 | X54: 1935 | Y54: 1850 | Z54: 3843 | AA54: 4778 | AB54: 7171 | AC54: 7608 | AD54: 5559 | AE54: 5981 | AF54: 4340 | AG54: 6743 | AH54: 0 | AI54: 0 | AJ54: 0 | AK54: 0 | AL54: 0
B55: Tributos a Pagar | J55: 3617 | K55: 2959 | L55: 2501 | M55: -2596 | N55: 3007 | O55: 3142 | P55: 2844 | Q55: 2948 | R55: 3039 | S55: 3857 | T55: 2942 | U55: 2904 | V55: 2835 | W55: 2895 | X55: 3043 | Y55: 2730 | Z55: 4000 | AA55: 7863 | AB55: 10740 | AC55: 8608 | AD55: 9305 | AE55: 9312 | AF55: 9594 | AG55: 10264 | AH55: 9752 | AI55: 13350 | AJ55: 27543 | AK55: 16443 | AL55: 14651
B56: Juros sobre capital próprio e dividendos a pagar | J56: 1996 | K56: 1996 | L56: 1996 | M56: -1996 | N56: 1692 | O56: 2111 | P56: 1808 | Q56: 1808 | R56: 0 | S56: 0 | T56: 0 | U56: 0 | V56: 0 | W56: 0 | X56: 0 | Y56: 3443 | Z56: 1507 | AA56: 7e-05 | AB56: 7e-05 | AC56: 41386 | AD56: 41386 | AE56: 0 | AF56: 1000 | AG56: 11756 | AH56: 11756 | AI56: 4400 | AJ56: 0 | AK56: 13590 | AL56: 13590
B57: Contas a pagar por aquisição societária | J57: 5860 | K57: 983 | L57: 6526 | M57: -6525 | N57: 6543 | O57: 6585 | P57: 8139 | Q57: 7864 | R57: 4087 | S57: 0 | T57: 3312 | U57: 1097 | V57: 1282 | W57: 1454 | X57: 1961 | Y57: 1017 | Z57: 8303 | AA57: 14815 | AB57: 9992 | AC57: 14473 | AD57: 16752 | AE57: 15241 | AF57: 17093 | AG57: 16298 | AH57: 14961 | AI57: 24710 | AJ57: 60100 | AK57: 67038 | AL57: 62990
... B63: Outros Passivos | J63: 573 | K63: 780 | L63: 448 | M63: -793 | N63: 482 | O63: 1727 | P63: 2491 | Q63: 2008 | R63: 303 | S63: 265 | T63: 224 | U63: 255 | V63: 184 | W63: 209 | X63: 166 | Y63: 1659 | Z63: 1800 | AA63: 3374 | AB63: 9087 | AC63: 1174 | AD63: 12945 | AE63: 6876 | AF63: 1270 | AG63: 1461 | AH63: 751 | AI63: 1145 | AJ63: 1173 | AK63: 1174 | AL63: 2132
J64: 106524 | K64: 101471 | L64: 108174 | M64: -114810 | N64: 131132 | O64: 92451 | P64: 101252 | Q64: 95180 | R64: 70044 | S64: 69380 | T64: 68301 | U64: 66608 | V64: 74266 | W64: 91576 | X64: 104317 | Y64: 106361 | Z64: 127042 | AA64: 170646 | AB64: 202843 | AC64: 259122 | AD64: 289881 | AE64: 238720 | AF64: 247400 | AG64: 277072 | AH64: 257940 | AI64: 264726 | AJ64: =SUM(AJ46:AJ63) -> 395917 | AK64: =SUM(AK46:AK63) -> 546806 | AL64: 406194
B65: NÃO CIRCULANTE | K65: 0 | L65: 0 | M65: 0 | N65: 0 | O65: 0 | P65: 0 | Q65: 0 | R65: 0 | S65: 0 | T65: 0 | U65: 0 | V65: 0 | W65: 0 | X65: 0 | Y65: 0 | Z65: 0 | AA65: 0 | AB65: 0 | AC65: 0 | AD65: 0 | AE65: 0 | AF65: 0 | AG65: 0 | AH65: 0 | AI65: 0
B66: Fornecedores | J66: 0 | K66: 0 | L66: 0 | M66: 0 | N66: 0 | O66: 0 | P66: 144 | Q66: 144 | R66: 144 | S66: 144 | T66: 144 | U66: 0 | V66: 0 | W66: 0 | X66: 0 | Y66: 0 | Z66: 0 | AA66: 0 | AB66: 0 | AC66: 0 | AD66: 0 | AE66: 0 | AF66: 16 | AG66: 0 | AH66: 0 | AI66: 0 | AJ66: 0 | AK66: 0
B67: Empréstimos e financiamentos | J67: 13952 | K67: 16906 | L67: 16338 | M67: -13902 | N67: 10296 | O67: 5713 | P67: 4419 | Q67: 3226 | R67: 1367 | S67: 1321 | T67: 1307 | U67: 1149 | V67: 985 | W67: 820 | X67: 652 | Y67: 27476 | Z67: 26195 | AA67: 25503 | AB67: 76085 | AC67: 100695 | AD67: 197867 | AE67: 205869 | AF67: 190960 | AG67: 271542 | AH67: 245981 | AI67: 284092 | AJ67: 330276 | AK67: 196225 | AL67: 519515
B68: Debêntures não conversíveis em ações | J68: 0 | K68: 0 | L68: 0 | M68: 0 | N68: 0 | O68: 64869 | P68: 61654 | Q68: 54218 | R68: 48084 | S68: 41873 | T68: 35769 | U68: 29622 | V68: 23558 | W68: 17456 | X68: 11350 | Y68: 0 | Z68: 0 | AA68: 0 | AB68: 0 | AC68: 0 | AD68: 0 | AE68: 0 | AF68: 0 | AG68: 0 | AH68: 0 | AI68: 0 | AJ68: 0 | AK68: 0 | AL68: 0
B69: Arrendamento financeiro a pagar - Direitos de uso CPC 06 | J69: 0 | K69: 0 | L69: 0 | M69: 0 | N69: 7097 | O69: 7250 | P69: 6828 | Q69: 6618 | R69: 6240 | S69: 5853 | T69: 5714 | U69: 5944 | V69: 5464 | W69: 5000 | X69: 4925 | Y69: 4371 | Z69: 14286 | AA69: 17842 | AB69: 17039 | AC69: 16310 | AD69: 15570 | AE69: 16216 | AF69: 16106 | AG69: 20281 | AH69: 18555 | AI69: 17719 | AJ69: 19953 | AK69: 19108 | AL69: 18898
B70: Tributos a Pagar | J70: 0 | K70: 0 | L70: 0 | M70: 0 | N70: 0 | O70: 0 | P70: 0 | Q70: 0 | R70: 0 | S70: 0 | T70: 0 | U70: 0 | V70: 1002 | W70: 1105 | X70: 0 | Y70: 0 | Z70: 56 | AA70: 54 | AB70: 81 | AC70: 77 | AD70: 75 | AE70: 42 | AF70: 63 | AG70: 61 | AH70: 60 | AI70: 58 | AJ70: 2230 | AK70: 0 | AL70: 0
B71: Mutuo a pagar | J71: 3015 | K71: 3939 | L71: 4176 | M71: -4303 | N71: 1813 | O71: 121 | P71: 0 | Q71: 0 | R71: 0 | S71: 0 | T71: 0 | U71: 0 | V71: 0 | W71: 0 | X71: 0 | Y71: 0 | Z71: 901 | AA71: 1975 | AB71: 960 | AC71: 992 | AD71: 1024 | AE71: 0 | AF71: 0 | AG71: 0 | AH71: 0 | AI71: 983 | AJ71: 1008 | AK71: 0 | AL71: 0
B72: Contas a pagar por aquisição societária | J72: 4503 | K72: 8316 | L72: 2373 | M72: -2193 | N72: 2020 | O72: 1836 | P72: 0 | Q72: 0 | R72: 0 | S72: 3894 | T72: 2611 | U72: 3476 | V72: 3312 | W72: 3176 | X72: 2723 | Y72: 2732 | Z72: 2793 | AA72: 2868 | AB72: 2957 | AC72: 15044 | AD72: 22296 | AE72: 19244 | AF72: 20228 | AG72: 20076 | AH72: 13191 | AI72: 19012 | AJ72: 88054 | AK72: 98717 | AL72: 95117
B73: Instrumentos financeiros derivativos | J73: 3333 | K73: 2257 | L73: 1895 | M73: -1855 | N73: 1831 | O73: 1397 | P73: 70 | Q73: 69 | R73: 73 | S73: 0 | T73: 0 | U73: 0 | V73: 0 | W73: 0 | X73: 0 | Y73: 0 | Z73: 0 | AA73: 0 | AB73: 1206 | AC73: 0 | AD73: 0 | AE73: 0 | AF73: 0 | AG73: 0 | AH73: 0 | AI73: 0 | AJ73: 0 | AK73: 3773 | AL73: 3880
B74: Tributos diferidos | J74: 680 | K74: 0 | L74: 0 | M74: 0 | N74: 0 | O74: 0 | P74: 0 | Q74: 0 | R74: 0 | S74: 0 | T74: 0 | U74: 0 | V74: 0 | W74: 0 | X74: 0 | Y74: 0 | Z74: 0 | AA74: 0 | AB74: 0 | AC74: 0 | AD74: 0 | AE74: 0 | AF74: 0 | AG74: 0 | AH74: 0 | AI74: 0 | AJ74: 0 | AK74: 0 | AL74: 0
B75: Provisão para riscos tributários, cíveis e trabalhistas | J75: 5516 | K75: 5268 | L75: 5075 | M75: -4794 | N75: 5051 | O75: 5499 | P75: 5327 | Q75: 5258 | R75: 5096 | S75: 4837 | T75: 4822 | U75: 4093 | V75: 4108 | W75: 4168 | X75: 3917 | Y75: 4273 | Z75: 4331 | AA75: 4478 | AB75: 5477 | AC75: 5706 | AD75: 6508 | AE75: 6590 | AF75: 7087 | AG75: 8953 | AH75: 9576 | AI75: 8350 | AJ75: 7620 | AK75: 7492 | AL75: 7372
B76: Outras provisões | J76: 0 | K76: 0 | L76: 0 | M76: 0 | N76: 0 | O76: 0 | P76: 0 | Q76: 0 | R76: 0 | S76: 0 | T76: 0 | U76: 0 | V76: 0 | W76: 0 | X76: 0 | Y76: 0 | Z76: 0 | AA76: 0 | AB76: 0 | AC76: 0 | AD76: 0 | AE76: 0 | AF76: 0 | AG76: 127 | AH76: 127 | AI76: 0 | AJ76: 0 | AK76: 0 | AL76: 0
B77: Outros passivos não circulantes | J77: 0 | K77: 0 | L77: 0 | M77: 0 | N77: 0 | O77: 264 | P77: 236 | Q77: 219 | R77: 202 | S77: 186 | T77: 169 | U77: 152 | V77: 135 | W77: 118 | X77: 101 | Y77: 84 | Z77: 67 | AA77: 51 | AB77: 28 | AC77: 231 | AD77: 210 | AE77: 195 | AF77: 180 | AG77: 188 | AH77: 172 | AI77: 263 | AJ77: 250 | AK77: 2391 | AL77: 2302
J78: 30999 | K78: 36686 | L78: 29857 | M78: -27047 | N78: 28108 | O78: 86949 | P78: 78678 | Q78: 69752 | R78: 61206 | S78: 58108 | T78: 50536 | U78: 44436 | V78: 38564 | W78: 31843 | X78: 23668 | Y78: 38936 | Z78: 48629 | AA78: 52771 | AB78: 103833 | AC78: 139055 | AD78: 243550 | AE78: 248156 | AF78: 234640 | AG78: 321228 | AH78: 287662 | AI78: 330477 | AJ78: =SUM(AJ66:AJ77) -> 449391 | AK78: =SUM(AK66:AK77) -> 327706 | AL78: 647084
B79: PATRIMÔNIO LÍQUIDO | K79: 0 | L79: 0 | M79: 0 | N79: 0 | O79: 0 | P79: 0 | Q79: 0 | R79: 0 | S79: 0 | T79: 0 | U79: 0 | V79: 0 | W79: 0 | X79: 0 | Y79: 0 | Z79: 0 | AA79: 0 | AB79: 0 | AC79: 0 | AD79: 0 | AE79: 0 | AF79: 0 | AG79: 0 | AH79: 0 | AI79: 0
B80: Capital social | J80: 41867 | K80: 53367 | L80: 53367 | M80: -53367 | N80: 53367 | O80: 53367 | P80: 53367 | Q80: 73367 | R80: 230879 | S80: 230774 | T80: 233049 | U80: 233146 | V80: 233146 | W80: 233451 | X80: 233451 | Y80: 233451 | Z80: 233681 | AA80: 233681 | AB80: 233681 | AC80: 233681 | AD80: 233681 | AE80: 233681 | AF80: 233681 | AG80: 233681 | AH80: 318397 | AI80: 318378 | AJ80: 318378 | AK80: 318284 | AL80: 318284
B81: Reserva de capital | J81: 2298 | K81: 2298 | L81: 2298 | M81: -2298 | N81: 2298 | O81: 2298 | P81: 2298 | Q81: 2298 | R81: 2298 | S81: 2298 | T81: 8104 | U81: 8104 | V81: 8104 | W81: 5518 | X81: 3728 | Y81: 8104 | Z81: 8104 | AA81: 8104 | AB81: 8104 | AC81: 8104 | AD81: 8104 | AE81: 8104 | AF81: 8104 | AG81: 8104 | AH81: 8104.3987 | AI81: 8104 | AJ81: 18356 | AK81: 19790 | AL81: 21224
B82: (-) Ações em tesouraria | K82: 0 | L82: 0 | M82: 0 | N82: 0 | O82: 0 | P82: 0 | Q82: 0 | R82: 0 | S82: 0 | T82: 0 | U82: 0 | V82: 0 | W82: 0 | X82: 0 | Y82: -6581 | Z82: -6581 | AA82: -9303 | AB82: -11978 | AC82: -11978 | AD82: -11978 | AE82: -11978 | AF82: -11978 | AG82: -11978 | AH82: -11978 | AI82: -11978 | AJ82: 0 | AK82: 0 | AL82: 0
B83: Ajuste avaliação patrimonial | K83: 0 | L83: 0 | M83: 0 | N83: 0 | O83: 0 | P83: 0 | Q83: 0 | R83: 0 | S83: 0 | T83: -11278 | U83: -12090 | V83: -12090 | W83: -12090 | X83: -12090 | Y83: -13346 | Z83: -13346 | AA83: -13346 | AB83: -13346 | AC83: -32314 | AD83: -33621 | AE83: -33621 | AF83: -33621 | AG83: -33621 | AH83: -33621 | AI83: -33621 | AJ83: -33621 | AK83: -33621 | AL83: -33621
